Workbook

Sheet 2018
E2: SEGUIMIENTO A COTIZACIONES
B10: Número de cotización | C10: Descripción de la cotización | J10: Valor sin IVA | K10: Fecha de cotización | L10: Fecha de aprobación | M10: Telefono | N10: Persona Encargada | O10: Correo
B13: 1 | C13: Cotización del diseño de extinción de incendios para el proyecto CDI Aures, de la ciudad de Medellín | J13: 2783000 | K13: 43229
B14: 2 | C14: Cotización diseño del diseño de extinción de incendios para el CEDI - Invesa | J14: 22176000 | K14: 43229
B15: 3 | C15: Cotización del diseño de extinción de incendios para el proyecto DISTRIHOGAR | J15: 5845000 | K15: 43230
B16: 4 | C16: COTIZACION DEL DISEÑO DE DETECCIÓN DE INCENDIOS PARA EL PROYECT COOPIMAR | J16: 3500000 | K16: 43230
B17: 5 | C17: COTIZACION DEL DISEÑO DE DETECCIÓN DE INCENDIOS PARA EL PROYECTO OLIVARI | J17: 1990000 | K17: 43231
B18: 6 | C18: COTIZACION DE LOS DISEÑOS DE PROTECCIÓN CONTRA INCENDIOS PARA EL PROYECTO BODEGA FAVITO | J18: 9980000 | K18: 43236
B19: 7 | C19: COTIZACION DE LOS DISEÑOS DE PROTECCIÓN CONTRA INCENDIOS PARA EL PROYECTO LOCAL 152 VIVA ENVIGADO | J19: 735000 | K19: 43236
B20: 8 | C20: COTIZACION DEL REDISEÑO Y VERIFICACIÓN DE CÁLCULOS HIDRÁULICOS PARA EL NUEVO CEDI DE INVESA, DE LA CIUDAD DE GIRARDOTA | J20: 10472000 | K20: 43238
B21: 9 | C21: COTIZACION DE LOS DISEÑOS DE PROTECCIÓN CONTRA INCENDIOS PARA AGUAS DEL BOSQUE | J21: 15092000 | K21: 43242
B22: 10 | C22: COTIZACION DE LOS DISEÑOS DE PROTECCIÓN CONTRA INCENDIOS LOCAL D1 | J22: 1540000 | K22: 43242
B23: 11 | C23: COTIZACION DE LOS DISEÑOS DE PROTECCIÓN CONTRA INCENDIOS AV EL POBLADO - AUTOCAD | J23: 19588800 | K23: 43243
C24: COTIZACION DE LOS DISEÑOS DE PROTECCIÓN CONTRA INCENDIOS AV EL POBLADO - REVIT | J24: 27104000 | K24: 43243 | L24: 43257
B25: 12 | C25: COTIZACION DEL ANÁLISIS DE SEGURIDAD HUMANA - PROYECTO MEDELLÍN | J25: 3670000 | K25: 43243 | L25: 43250
B26: 13 | C26: COTIZACION DEL ANÁLISIS DE SEGURIDAD HUMANA - PROYECTO ENVIGADO | J26: 3670000 | K26: 43243 | L26: 43250
B27: 14 | C27: COTIZACION DEL ANÁLISIS DE SEGURIDAD HUMANA - CUO CIUDADELA UNIVERSITARIA DE OCCIDENTE | J27: 5544000 | K27: 43243 | L27: 43245
B28: 15 | C28: COTIZACION DE LOS DISEÑOS DE PROTECCIÓN CONTRA INCENDIOS RESTAURANTE ASIA | J28: 1970000 | K28: 43248 | L28: 43250
B29: 16 | C29: COTIZACION DE LOS DISEÑOS DE PROTECCIÓN CONTRA INCENDIOS PARA EL PROYECTO CLÍNICA DE LA CIUDAD DE LA CEJA | J29: 16262400 | K29: 43248
B30: 17 | C30: COTIZACION DEL DISEÑO DE EXTINCIÓN DE INCENDIOS PARA EL PROYECTO LOCAL KÓNICO VIVA ENVIGADO | J30: 610000 | K30: 43249 | L30: 43297
B31: 18 | C31: COTIZACION DE LOS DISEÑOS DE DETECCIÓN DE INCENDIOS Y SEGURIDAD HUMANA PARA EL PROYECTO NUEVA FRONTERA | J31: 8000000 | K31: 43249 | L31: 43252
B32: 19 | C32: COTIZACION DE LOS DISEÑOS DE PROTECCIÓN CONTRA INCENDIOS Y SEGURIDAD HUMANA PARA EL PROYECTO MAZANTI | J32: 20328000 | K32: 43227
B33: 20 | C33: COTIZACION DEL DISEÑO DE DETECCIÓN DE INCENDIOS - PUERTO RIONEGRO Y CARGA FASE I | J33: 4174500 | K33: 43250
B34: 21 | C34: COTIZACION DE LOS DISEÑOS DE PROTECCIÓN CONTRA INCENDIOS PARA EL PROYECTO ON BUSINESS MILLA DE ORO | J34: 1830000 | K34: 43256
B35: 22 | C35: COTIZACION DE LOS DISEÑO DE PROTECCIÓN CONTRA INCENDIOS - OFICINAS BODEGA PREMEX | J35: 2340000 | K35: 43256
B36: 23 | C36: COTIZACION DEL DISEÑO DE DETECCIÓN DE INCENDIOS PARA EL TRES CANTOS, EN LA CIUDAD DE MEDELLÍN | J36: 6325000 | K36: 43258
B37: 24 | C37: COTIZACION DEL DISEÑO DE EXTINCIÓN DE INCENDIOS PARA EL PROYECTO CDI AURES | J37: 2783000 | K37: 43259
B38: 25 | C38: COTIZACION DE LOS DISEÑOS DE PROTECCIÓN CONTRA INCENDIOS PARA EL PROYECTO LORITO D´MODA | J38: 2710000 | K38: 43260
B39: 26 | C39: COTIZACION DE LOS DISEÑOS DE PROTECCIÓN CONTRA INCENDIOS PARA EL PROYECTO MERCADOS EL ÁGORA | J39: 5550000 | K39: 43260
B40: 27 | C40: COTIZACION DE LOS DISEÑOS DE PROTECCIÓN CONTRA INCENDIOS Y SEGURIDAD HUMANA PARA EL PROYECTO BORBÓN DE LA MONTAÑA | J40: 20328000 | K40: 43263
B41: 28 | C41: COTIZACION DE LOS DISEÑOS DE PROTECCIÓN CONTRA INCENDIOS Y SEGURIDAD HUMANA PARA EL PROYECTO BEILLIN | J41: 36344000 | K41: 43264
B42: 29 | C42: COTIZACION DE LOS DISEÑO DE PROTECCIÓN CONTRA INCENDIOS PARA EL PROYECTO NACAR | J42: 4930000 | K42: 43265 | L42: 43266
B43: 30 | C43: COTIZACION DE LOS DISEÑOS DE PROTECCIÓN CONTRA INCENDIOS Y SEGURIDAD HUMANA PARA EL PROYECTO COLISEO RUBEN DARIO QUINTERO VILLADA EN LA CIUDAD DE RIONEGRO | J43: 16016000 | K43: 43266
B44: 31 | C44: COTIZACION DE LOS DISEÑOS DE PROTECCIÓN CONTRA INCENDIOS Y SEGURIDAD HUMANA PARA EL PROYECTO HOJARASCA | J44: 6590000 | K44: 43267
B45: 32 | C45: COTIZACION DE LOS DISEÑOS DE PROTECCIÓN CONTRA INCENDIOS PARA EL PROYECTO LOCAL 324 – VIVA ENVIGADO | J45: 2170000 | K45: 43270
B46: 33 | C46: COTIZACION DE LOS DISEÑOS DE PROTECCIÓN CONTRA INCENDIOS PARA EL PROYECTO TRES33 | J46: 15400000 | K46: 43271
B47: 34 | C47: COTIZACION DE LOS DISEÑOS DE PROTECCIÓN CONTRA INCENDIOS PARA EL PROYECTO MANDALA | J47: 16400000 | K47: 43271
B48: 35 | C48: COTIZACION DE LA REVISIÓN DE LOS DISEÑOS DE EXTINCIÓN Y DETECCIÓN DE INCENDIOS DEL PROYECTO CIBELES | J48: 4250000 | K48: 43278
B49: 36 | C49: COTIZACION DEL DISEÑO Y DIMENCIONAMIENTO DE LAS CONEXIONES A LOS EDIFICIOS EXISTENTES DEL PROYECTO PLANTA CEMENTOS MOLINS | J49: 6160000 | K49: 43280
B50: 37 | C50: COTIZACION DEL DISEÑO DE DETECCIÓN DE INCENDIOS PARA EL PROYECTO CABLE EL PICACHO - DWG | J50: 6960000 | K50: 43282
B51: 38 | C51: COTIZACION DEL DISEÑO DE DETECCIÓN DE INCENDIOS PARA EL PROYECTO CABLE EL PICACHO - REVIT | J51: 9000000 | K51: 43282 | L51: 43285
B52: 39 | C52: COTIZACION DE LOS DISEÑOS DE PROTECCIÓN CONTRA INCENDIOS PARA EL PROYECTO HATOVIEJO VIVA ENVIGADO | J52: 2775000 | K52: 43286
B53: 40 | C53: COTIZACION DE LOS DISEÑOS DE PROTECCIÓN CONTRA INCENDIOS PARA EL PROYECTO BIKE HOUSE | J53: 9245000 | K53: 43287
B54: 41 | C54: COTIZACION DE REVISIÓN DE LOS SISTEMAS DE PROTECCIÓN CONTRA INCENDIOS Y SEGURIDAD HUMANA PARA EL PROYECTO CENTRO COMERCIAL ARKADIA | J54: 26980000 | K54: 43290
B55: 42 | C55: COTIZACION DEL DISEÑO DE LA RED GENERAL DE EXTINCIÓN DE INCENDIOS PARA EL PROYECTO ALAS DORADAS | J55: 7000 | K55: 43292
B56: 43 | C56: COTIZACIÓN DEL DISEÑO DE EXTINCIÓN DE INCNEIDOS PARA EL PROYECTO RAMBLER VIVA ENVIGADO | J56: 250000 | K56: 43292 | L56: 43293
B57: 44 | C57: COTIZACIÓN DEL DISEÑO DE EXTINCIÓN DE INCNEIDOS PARA EL PROYECTO TÍPICO ANTOJO VIVA ENVIGADO | J57: 250000 | K57: 43292 | L57: 43293
B58: 45 | C58: COTIZACIÓN DEL DISEÑO DE EXTINCIÓN DE INCNEIDOS PARA EL PROYECTO CROW VIVA ENVIGADO | J58: 250000 | K58: 43292 | L58: 43293
B59: 46 | C59: COTIZACION DEL ANÁLISIS DE SEGURIDAD HUMANA PARA EL PROYECTO CDI LOS LAGOS | J59: 1725000 | K59: 43294
B60: 47 | C60: COTIZACION DEL DISEÑO DE EXTINCIÓN DE INCENDIOS PARA EL PROYECTO LOCAL RANCHERITO VIVA ENVIGADO | J60: 1295000 | K60: 42567 | L60: 43299
B61: 48 | C61: COTIZACION DEL LOS DISEÑOS DE PROTECCIÓN CONTRA INCENDIOS PARA EL PROYECTO POLO CLUB VIVA ENVIGADO | J61: 450000 | K61: 43299
B62: 49 | C62: COTIZACION DEL LOS DISEÑOS DE PROTECCIÓN CONTRA INCENDIOS PARA EL PROYECTO SANDWICH QBANO VIVA ENVIGADO | J62: 250000 | K62: 43299 | L62: 43299
B63: 50 | C63: COTIZACION DEL DISEÑO DE EXTINCIÓN DE INCENDIOS PARA EL PROYECTO MAS X MENOS MAYORCA | J63: 470000 | K63: 43300
B64: 51 | C64: COTIZACION DEL DISEÑO DE EXTINCIÓN DE INCENDIOS PARA EL PROYECTO LOS PARQUEADEROS DE VIVA LA CEJA | J64: 4312000 | K64: 43302
B65: 52 | C65: COTIZACION DEL DISEÑO DE EXTINCIÓN DE INCENDIOS PARA EL PROYECTO HOTEL PARK 10 | J65: 15708000 | K65: 43302
B66: 53 | C66: COTIZACION DE LOS DISEÑOS DE PROTECCIÓN CONTRA INCENDIOS Y SEGURIDAD HUMANA PARA EL PROYECTO FORESTA CAMPESTRE | J66: 6160000 | K66: 43304
B67: 54 | C67: COTIZACION DE LOS DISEÑOS DE PROTECCIÓN CONTRA INCENDIOS Y SEGURIDAD HUMANA PARA EL PROYECTO JARDÍN DE CIMARRONES | J67: 4500000 | K67: 43304
B68: 55 | C68: COTIZACION DE LOS DISEÑOS DE PROTECCIÓN CONTRA INCENDIOS PARA EL PROYECTO PARAÍSO VIVA ENVIGADO | J68: 250000 | K68: 43305
B69: 56 | C69: COTIZACION DEL DISEÑO DE EXTINCIÓN DE INCENDIOS PARA EL PROYECTO URGENCIAS HOSPITAL SAN JUAN DE DIOS | J69: 6410000 | K69: 43306
B70: 57 | C70: COTIZACION DEL ANÁLISIS DE SEGURIDAD HUMANA LAS OFICINAS DEL METRO DE MEDELLÍN EN EL MUNICIPIO DE BELLO | J70: 2980000 | K70: 43307
B71: 58 | C71: COTIZACION DEL DISEÑO DE EXTINCIÓN DE INCENDIOS PARA EL PROYECTO CALICHE CEVICHE LA CENTRAL | J71: 320000 | K71: 43307
B72: 59 | C72: COTIZACION DEL ANÁLISIS DE SEGURIDAD HUMANA PARA EL PROYECTO COWORKING NOI | J72: 1490000 | K72: 43311 | L72: 43328
B73: 60 | C73: COTIZACION DE LOS DISEÑOS DE SEGURIDAD HUMANA Y PROTECCIÓN CONTRA INCENDIOS - AYURA MOTORS ETAPA II | J73: 15917067 | K73: 43312
B74: 61 | C74: COTIZACION DEL SEGUIMIENTO A LAS RECOMENDACIONES Y PRUEBA DE BOMBA - PASTAS DORIA | J74: 1625000 | K74: 43313 | L74: 43334
B75: 62 | C75: COTIZACION DE LOS DISEÑOS DE SEGURIDAD HUMANA Y PROTECCIÓN CONTRA INCENDIOS - OFICINAS 1600 M2 | J75: 8263328.4 | K75: 43313
B76: 63 | C76: COTIZACION DEL ANÁLISIS DE SEGURIDAD HUMANA PARA EL PROYECTO TORRE 3 CAMINO | J76: 880000 | K76: 43314 | L76: 43314
B77: 64 | C77: COTIZACION DEL ANÁLISIS DE SEGURIDAD HUMANA PARA EL PROYECTO TORRE 2 ENSENADA | J77: 880000 | K77: 43314 | L77: 43314
B78: 65 | C78: COTIZACION DEL DISEÑO DE EXTINCIÓN DE INCENDIOS PARA EL PROYECTO LOCAL COMFENALCO VIVA ENVIGADO | J78: 1050000 | K78: 43318 | L78: 43320
B79: 66 | C79: COTIZACION DEL DISEÑO DE LA RED DE EXTINCIÓN DE INCENDIOS PARA EL PROYECTO PLANTA SAN MIGUEL - TROPIGAS VILLANUEVA | J79: 18438 | K79: 43319
B80: 67 | C80: COTIZACION DE LOS DISEÑOS DE PROTECCIÓN CONTRA INCENDIOS PARA EL PROYECTO FRUTA FRESCA VIVA ENVIGADO | J80: 922500 | K80: 43320 | L80: 43326
B81: 68 | C81: COTIZACION DEL ANÁLISIS DE SEGURIDAD HUMANA PARA LA ETAPA 1 Y ETAPA 2 DEL PROYECTO NEWPORT | J81: 5418000 | K81: 43320
B82: 69 | C82: COTIZACION DEL ANÁLISIS DE SEGURIDAD HUMANA PARA LAS TORRES 1 Y 2 DEL PROYECTO PUNTA AZUL | J82: 3520000 | K82: 43320
B83: 70 | C83: COTIZACION DE REVISIÓN DE LOS SISTEMA DE PROTECCIÓN CONTRA INCENDIOS PARA LA ETAPA 1 DEL PROYECTO NEWPORT | J83: 5500000 | K83: 43320
B84: 71 | C84: COTIZACION DEL ANÁLISIS DE SEGURIDAD HUMANA PARA EL PROYECTO MOLISOL | J84: 3000000 | K84: 43320
B85: 72 | C85: COTIZACION DEL DISEÑO DE EXTINCIÓN DE INCENDIOS PARA EL PROYECTO PRODUSA BODEGAS 246, 247, 249 y 250 | J85: 29698688 | K85: 43321
B86: 73 | C86: COTIZACION DEL DISEÑO DE EXTINCIÓN DE INCENDIOS PARA EL PROYECTO PLAZA LINARES | J86: 5420000 | K86: 43322
B87: 74 | C87: COTIZACION DEL DISEÑO DE EXTINCIÓN DE INCENDIOS PARA EL PROYECTO PROMOSA VIVA ENVIGADO | J87: 3975000 | K87: 43325
B88: 75 | C88: COTIZACION DEL DISEÑO DE EXTINCIÓN DE INCENDIOS PARA EL PROYECTO KÓNICO DE MODA | J88: 610000 | K88: 43325
B89: 76 | C89: COTIZACION DE LOS DISEÑOS DE PROTECCIÓN CONTRA INCENDIOS Y SEGURIDAD HUMANA PARA EL PROYECTO LA TAGUA | J89: 9890000 | K89: 43326
B90: 77 | C90: COTIZACION DE LOS DISEÑOS DE PROTECCIÓN CONTRA INCENDIOS PARA EL PROYECTO TECNOLÓGICO DE ANTIOQUIA | J90: 18630000 | K90: 43328
B91: 78 | C91: COTIZACIÓN DEL DISEÑO DEL SISTEMA DE DETECCIÓN DE INCENDIOS PARA LOS LOCALES LEÑOS Y CARBÓN, PAPA JOHN´S Y EL CORRAL | J91: 2573824 | K91: 43328
B92: 79 | C92: COTIZACION DE LOS DISEÑOS DE PROTECCIÓN CONTRA INCENDIOS - CARACOL RADIO | J92: 4940000 | K92: 43328
... B153: 140 | C153: COTIZACION DE LOS DISEÑOS DE PROTECCIÓN CONTRA INCENDIOS - OFICINA SQUARE | J153: 800000 | K153: 43403
B154: 141 | C154: COTIZACION ESTIMADA DE LOS DISEÑOS DE PROTECCIÓN CONTRA INCENDIOS Y SEGURIDAD HUMANA PARA PROYECTOS DE CONSTRUCIÓN Y REMODELACIÓN | J154: Variable | K154: 43404
B155: 142 | C155: COTIZACION DE LOS DISEÑOS DE SEGURIDAD HUMANA Y EXTINCIÓN DE INCENDIOS - HACIENDA NIQUIA | J155: 3557000 | K155: 43410
B156: 143 | C156: COTIZACION DEL DISEÑO DE EXTINCIÓN DE INCENDIOS - MEDICOA PISO 6 | J156: 3293000 | K156: 43410
B157: 144 | C157: COTIZACION DE REVISIÓN DE LOS SISTEMAS DE PROTECCIÓN CONTRA INCENDIOS Y SEGURIDAD HUMANA PARA EL PROYECTO MEDICOA | J157: 7900000 | K157: 43410
B158: 145 | C158: COTIZACION DE LOS DISEÑOS DE PROTECCIÓN CONTRA INCENDIOS Y SEGURIDAD HUMANA PARA EL PROYECTO CLASS 48 | J158: 13435000 | K158: 43410
B159: 146 | C159: COTIZACION DE LA PRUEBA HIDRÁULICA AL SISTEMA DE EXTINCIÓN DE INCENDIOS DE LA EMPRESA INSUMOS & TEXTILES NORBER S.A.S. | J159: 1580000 | K159: 43410
B160: 147 | C160: COTIZACION DE LOS DISEÑOS DE PROTECCIÓN CONTRA INCENDIOS Y SEGURIDAD HUMANA PARA EL PROYECTO EDIFICIO COMERCIAL DE 5 PISOS | J160: 10985000 | K160: 43410
B161: 148 | C161: COTIZACION CAPACITACIÓN - TIP | J161: 1055000 | K161: 43410
B162: 149 | C162: COTIZACION DEL DISEÑO DE EXTINCIÓN DE INCENDIOS PARA EL PROYECTO BANDA CEMEX | J162: 11850000 | K162: 43411
B163: 150 | C163: COTIZACION DE LOS DISEÑOS DE SEGURIDAD HUMANA Y PROTECCIÓN CONTRA INCENDIOS - COTIZACIÓN GENERAL I+CONSTRUCTORA | J163: Variable | K163: 43411
B164: 151 | C164: COTIZACION DEL DISEÑO DE EXTINCIÓN DE INCENDIOS (PRE-ACCIÓN) PARA EL PROYECTO QUIRÓFANOS T.M. EL TESORO | J164: 1450000 | K164: 43417
B165: 152 | C165: COTIZACION DE LOS DISEÑOS DE PROTECCIÓN CONTRA INCENDIOS Y SEGURIDAD HUMANA PARA EL PROYECTO EDIFICIO VIZCAYA | J165: 7112000 | K165: 43417
B166: 153 | C166: COTIZACION DE LOS DISEÑOS DE PROTECCIÓN CONTRA INCENDIOS Y SEGURIDAD HUMANA PARA EL PROYECTO LA PROVINCIA | J166: 13833000 | K166: 43417
B167: 154 | C167: COTIZACION DE REVISIÓN DE LOS SISTEMAS DE PROTECCIÓN CONTRA INCENDIOS Y SEGURIDAD HUMANA PARA EL PROYECTO RESERVA PLAZA | J167: 4890000 | K167: 43417
B168: 155 | C168: COTIZACION DE LOS DISEÑOS DE PROTECCIÓN CONTRA INCENDIOS PARA EL PROYECTO LYFT PISO 5 AVENTURA | J168: 3215000 | K168: 43421
B169: 156 | C169: MODELACIÓN Y CÁLCULOS DEL SISTEMA DE DETECCIÓN DE INCENDIOS PARA EL PROYECTO COMESTIBLES LA ROSA | J169: 2170000 | K169: 43423
B170: 157 | C170: ALKOMPRAR CÚCUTA | J170: 3000000 | K170: 43424
...

Sheet 2019
E2: SEGUIMIENTO A COTIZACIONES
R4: Consecutivo repetido
R5: No encontre informacion
B10: Número de cotización | C10: Descripción de la cotización | J10: Valor sin IVA | K10: Fecha de cotización | L10: Fecha de aprobación | M10: Telefono | N10: Persona Encargada | O10: Correo
B13: 1 | C13: Cotización de la actualización de planos record y rediseño de los sistemas de extinción de incendio para la Terminal de Servicios Aeroportuarios Aeropuerto El Caño Quibdo | J13: 33000000 | K13: 43468 | N13: Juan Camilo Quintero
B14: 2 | C14: COTIZACION DEL REDISEÑO DE DETECCIÓN DE INCENDIOS PARA EL PROYECTO METROCABLE PICACHO | J14: 4450000 | K14: 43468 | N14: Bayron Eliecer Puerta
B15: 3 | C15: COTIZACION DEL DISEÑO DE EXTINCIÓN DE INCENDIOS PARA EL PROYECTO MAM MUSEO DE ARTE MODERNO | J15: 20480000 | K15: 43469 | N15: Julián Suárez Estrada
B16: 4 | C16: COTIZACION DE REVISIÓN DEL SISTEMAS DE EXTINCIÓN DE INCENDIOS PARA LOS LOCALES DEL CENTRO COMERCIAL PALMA GRANDE | J16: 3295000 | K16: 43474 | N16: David Lopera
B17: 5 | C17: COTIZACION DE LOS DISEÑOS DE PROTECCIÓN CONTRA INCENDIOS - CASA RONALD MCDONALD | J17: 3442 | K17: 43474 | N17: Julio Alejandro Llamas
B18: 6 | C18: COTIZACION DE LOS DISEÑOS DE PROTECCIÓN CONTRA INCENDIOS Y SEGURIDAD HUMANA PARA EL PROYECTO EDIFICIO MARIALUCI | J18: 4990000 | K18: 43476 | N18: Jhon Rodriguez
B19: 6 | C19: COTIZACION DE LOS DISEÑOS DE PROTECCIÓN CONTRA INCENDIOS Y SEGURIDAD HUMANA PARA EL PROYECTO EDIFICIO MARIALUCI | J19: 4990000 | K19: 43476 | N19: Johrladiz Úsuga
B20: 7 | C20: COTIZACION DE LOS DISEÑOS DE SEGURIDAD HUMANA Y DETECCIÓN DE INCENDIOS - CANTAZARO | J20: 6000000 | K20: 43479 | N20: José Ignacio Aristizabal
B21: 8 | C21: COTIZACION DE LOS DISEÑOS DE PROTECCIÓN CONTRA INCENDIOS PARA EL PROYECTO COLEGIO UCO CIMARRONAS | J21: 3930000 | K21: 43479 | N21: Estevan Castaño
B22: 9 | C22: COTIZACION DE LOS DISEÑOS DE PROTECCIÓN CONTRA INCENDIOS PARA EL PROYECTO BRISAS DEL SOL 3 | J22: 16800000 | K22: 43479 | N22: Estevan Castaño | O22: estevancastano@gmail.com
B23: 10 | C23: COTIZACION DE LOS DISEÑOS DE PROTECCIÓN CONTRA INCENDIOS - PTAR PAPELSA | J23: 11270000 | K23: 43480 | N23: Diana Carolina Jaramillo
B24: 11 | C24: COTIZACION DEL DISEÑO DE LA RED DE EXTINCIÓN DE INCENDIOS - TROPIGAS SANTO TOMAS | J24: 16016 | K24: 43481 | N24: Julio Alejandro Llamas
B25: 12 | C25: COTIZACION ESTIMADA DE LOS DISEÑOS DE PROTECCIÓN CONTRA INCENDIOS Y SEGURIDAD HUMANA PARA PROYECTOS DE CONSTRUCIÓN Y REMODELACIÓN | J25: Variable | K25: 43486 | N25: Catalina Prieto
B26: 13 | C26: COTIZACION DEL DISEÑO DE EXTINCIÓN DE INCENDIOS PARA EL PROYECTO ALIMENTOS NUOVO PLANTA LA ESTRELLA | J26: 6130000 | K26: 43486 | N26: Carlos Esteban Longas Vélez
B27: 14 | C27: COTIZACION DE LOS DISEÑOS DE PROTECCIÓN CONTRA INCENDIOS PARA EL PROYECTO EVERFIT LA 65 | J27: 3775000 | K27: 43121 | N27: Adriana Jiménez
B28: 15 | C28: COTIZACION DEL DISEÑO DE EXTINCIÓN DE INCENDIOS PARA EL PROYECTO ALIMENTOS NUOVO PLANTA LA ESTRELLA | J28: 4590000 | K28: 43488 | N28: Juan Pablo Grajales
B29: 16 | C29: COTIZACION DEL DISEÑO DE EXTINCIÓN DE INCENDIOS - DATACENTER | J29: 6590000 | K29: 43487 | N29: Daniel Felipe Díaz Beltrán M.Eng.
B30: 17 | C30: COTIZACION DE LOS DISEÑOS DE PROTECCIÓN CONTRA INCENDIOS PARA EL PROYECTO COLEGIO MONSEÑOR ALFONSO URIBE JARAMILLO | J30: 4470000 | K30: 43489 | N30: Edinson Franco
B31: 18 | C31: COTIZACION DE LOS DISEÑOS DE PROTECCIÓN CONTRA INCENDIOS - LOCAL DECORCERÁMICA LLANOGRANDE | J31: 2600000 | K31: 43490 | N31: Jairo Andrés Moncada C.
B32: 19 | C32: COTIZACION DE LOS DISEÑOS DE SEGURIDAD HUMANA Y PROTECCIÓN CONTRA INCENDIOS - LOS MELGUIZO | J32: 31790000 | K32: 43490 | N32: Jhon Anderson Rodriguez
B33: 19 | C33: COTIZACIÓN DE ACTUALIZACIÓN DE PLANOS RECORD Y REDISEÑO DE EXTINCIÓN DE INCENDIOS PARA EL AEROPUERTO EL CAÑO QUIBDÓ | J33: 33000000 | K33: 43468 | N33: Juan Camilo Quintero
B34: 20 | C34: COTIZACION DE LOS DISEÑOS DE PROTECCIÓN CONTRA INCENDIOS PARA EL PROYECTO MALL CIMARRONAS | J34: 9480000 | K34: 43490 | N34: Oscar Salazar
B35: 21 | C35: COTIZACION DEL ANÁLISIS DE SEGURIDAD HUMANA Y PROTECCIÓN CONTRA INCENDIOS - DAVITA | J35: 1950000 | K35: 43493 | N35: Otalvaro Osorio Correa
B36: 22 | C36: COTIZACION DE LOS DISEÑOS DE DE EXTINCIÓN Y DETECCIÓN INCENDIOS - COMFAMA | J36: Variable | K36: 43494 | N36: Ariel Gómez Ruíz
B37: 23 | C37: COTIZACION DEL DISEÑO DE EXTINCIÓN DE INCENDIOS - FEDEX AEROPUERTO RIONEGRO | J37: 8153000 | K37: 43494 | N37: Juan Camilo Quintero Bedoya
B38: 24 | C38: COTIZACION DE LOS DISEÑOS DE PROTECCIÓN CONTRA INCENDIOS - EDIFICIO INTERES SOCIAL LA ESTRELLA | J38: 10865000 | K38: 43494 | N38: Jorge Ruiz E.
B39: 25 | C39: COTIZACION DE LOS DISEÑOS DE SEGURIDAD HUMANA Y PROTECCIÓN CONTRA INCENDIOS - AKI | J39: 32190000 | K39: 43494 | N39: Maribel Osorio
B40: 26 | C40: COTIZACION DE LOS DISEÑOS DE SEGURIDAD HUMANA Y PROTECCIÓN CONTRA INCENDIOS - CASA CASTELLANA | J40: 17491000 | K40: 43494 | N40: Fernando Saldarriaga
B41: 27 | C41: COTIZACION DE LOS DISEÑOS DE SEGURIDAD HUMANA Y PROTECCIÓN CONTRA INCENDIOS - VOLARÉ | J41: 20584000 | K41: 43494 | N41: Fernando Saldarriaga
B42: 28 | C42: COTIZACION DE LOS DISEÑOS DE SEGURIDAD HUMANA Y PROTECCIÓN CONTRA INCENDIOS - VOLARÉ | J42: 20584000 | K42: 43495
A43: ok | B43: 29 | C43: COTIZACION DEL DISEÑO DE DETECCIÓN DE INCENDIOS PARA EL COLEGIO THE NEW SCHOOL | J43: 2980000 | K43: 43496 | N43: Jorge García
A44: ok | B44: 29 | C44: COTIZACION DE LOS DISEÑOS DE SEGURIDAD HUMANA Y PROTECCIÓN CONTRA INCENDIOS - VOLARÉ | J44: Variable | K44: 43495 | N44: Estevan Castaño | O44: estevancastano@gmail.com
B45: 30 | C45: COTIZACION DEL DISEÑO DE EXTINCIÓN DE INCENDIOS PARA EL PROYECTO LOCAL 114 DE JARDINES DE LLANOGRANDE | J45: 320000 | K45: 43496 | N45: David Lopera
B46: 31 | C46: COTIZACION DE LOS DISEÑOS DE PROTECCIÓN CONTRA INCENDIOS PARA EL PROYECTO SUMIMEDICAL | J46: 10835000 | K46: 43131 | N46: Cristiam Mondragón
B47: 32 | C47: COTIZACION DEL DISEÑO DE EXTINCIÓN DE INCENDIOS PARA EL PROYECTO LOCAL 113 DE JARDINES DE LLANOGRANDE | J47: 320000 | K47: 43500 | N47: David Lopera
B48: 33 | C48: COTIZACION DEL DISEÑO DE EXTINCIÓN DE INCENDIOS PARA EL PROYECTO LOCAL 129 DE JARDINES DE LLANOGRANDE | J48: 320000 | K48: 43500 | N48: David Lopera
B49: 34 | C49: COTIZACION DEL DISEÑO DE DETECCIÓN DE INCENDIOS - AIANA VERDE | J49: 5482000 | K49: 43501 | N49: Giovanni Zapata Isaza
B50: 35 | C50: COTIZACION DEL DISEÑO DE DETECCIÓN DE INCENDIOS - EDIFICIO TORRE CENTAL | J50: 2960000 | K50: 43501 | N50: Giovanni Zapata Isaza
B51: 36 | C51: COTIZACION DEL DISEÑO DE DETECCIÓN DE INCENDIOS - CENTRO COMERCIAL SAVANNA | J51: 3250000 | K51: 43501 | N51: Giovanni Zapata Isaza
B52: 37 | C52: COTIZACION DE LOS DISEÑOS DE SEGURIDAD HUMANA Y PROTECCIÓN CONTRA INCENDIOS - ALEJANDRIA | J52: 8655000 | K52: 43501 | N52: Gabriel Paniagua
B53: 38 | C53: COTIZACION DEL DISEÑO CONEXIÓN TANQUE DE EQUILIBRIO VILLA VERDE | J53: 1317000 | K53: 43501 | N53: Mauricio Sepúlveda Rivillas
B54: 39 | C54: COTIZACION DE VISITAS DE INTERVENTORIA A LAS OBRAS DE SISTEMAS EN PROTECCIÓN CONTRA INCENDIOS S.A.S. | J54: 450000 | K54: 43502 | N54: Juan Pablo Grajales
B55: 40 | C55: COTIZACION DEL DISEÑO DE EXTINCIÓN DE INCENDIOS PARA EL PROYECTO LOCAL 111 DE JARDINES DE LLANOGRANDE | J55: 320000 | K55: 43503 | N55: David Lopera
B56: 41 | C56: COTIZACION DEL DISEÑO DE EXTINCIÓN DE INCENDIOS PARA EL PROYECTO TALLER MAZDA MAYORCA | J56: 1882000 | K56: 43503
B57: 42 | C57: COTIZACION DEL DISEÑO DE DETECCIÓN DE INCENDIOS PARA EL PROYECTO OFICINA COMDATA | J57: 1225000 | K57: 43505 | N57: Liseth Molina
A58: ok | B58: 43 | C58: COTIZACION DE LOS DISEÑOS DE PROTECCIÓN CONTRA INCENDIOS Y SEGURIDAD HUMANA PARA EL PROYECTO NOGALES | J58: 18560000 | K58: 43507 | N58: Jaime Laverde
A59: ok | B59: 43 | C59: COTIZACION DE LOS DISEÑOS DE PROTECCIÓN CONTRA INCENDIOS Y SEGURIDAD HUMANA PARA EL PROYECTO EDIFICIO EN LA 33 | J59: 7790000 | K59: 43505 | N59: Juan David Botero
B60: 44 | C60: COTIZACION DE LOS DISEÑOS DE PROTECCIÓN CONTRA INCENDIOS - EDIFICIO DOCENCIA CES | J60: VARIABLE | K60: 43508 | N60: Jhoam Andres Giraldo
B61: 45 | C61: COTIZACION DEL ANÁLISIS DE SEGURIDAD HUMANA - EDIFICIO DOCENCIA CES | J61: 3135000 | K61: 43143 | N61: Jhoam Andres Giraldo
B62: 46 | C62: COTIZACION DE LOS DISEÑOS DE PROTECCIÓN CONTRA INCENDIOS Y SEGURIDAD HUMANA PARA EL PROYECTO EDIFICIO EN ENVIGADO | J62: 5630000 | K62: 43507 | N62: Carlos Andrés Muñoz
A63: si | B63: 48 | C63: COTIZACION DE LOS DISEÑOS DE PROTECCIÓN CONTRA INCENDIOS Y SEGURIDAD HUMANA PARA EL PROYECTO CÁMARA DE COMECIO RIONEGRO | J63: 12535000 | K63: 43507 | N63: Estevan Castaño
A64: si | B64: 48 | C64: COTIZACION DEL DISEÑO DE DETECCIÓN DE INCENDIOS - SUBESTACIÓN LA CUMBRE | J64: 4610000 | K64: 43508 | N64: David Lopera
B65: 49 | C65: COTIZACION DE LOS DISEÑOS DE PROTECCIÓN CONTRA INCENDIOS - EDIFICIO DOCENCIA CES (PARA CIVILSA) | J65: 13800000 | K65: 43508 | N65: Julio Alzate
B66: 50 | C66: COTIZACION DEL DISEÑO DE EXTINCIÓN DE INCENDIOS PARA EL PROYECTO LOCAL 237 – COLCHONES PARAISO JARDINES DE LLANOGRANDE | J66: 2640000 | K66: 43515 | N66: David Lopera
B67: 51 | C67: COTIZACION DE LOS DISEÑOS DE SEGURIDAD HUMANA Y PROTECCIÓN CONTRA INCENDIOS - ALCARAVANES MARINILLA | J67: 9979000 | K67: 43516
B68: 52 | C68: COTIZACION DE LOS DISEÑOS DE EXTINCIÓN DE INCENDIOS Y SEGURIDAD HUMANA PARA EL PROYECTO HOTEL HILTON EL SALVADOR | J68: 4450 | K68: 43518 | N68: Julio Alejandro Llamas
B69: 53 | C69: COTIZACION DE LOS DISEÑOS DE PROTECCIÓN CONTRA INCENDIOS Y SEGURIDAD HUMANA PARA EL PROYECTO JARDINES DEL SUR | J69: 18000000 | K69: 43518
B70: 54 | C70: COTIZACION DE LOS DISEÑOS DE SEGURIDAD HUMANA Y PROTECCIÓN CONTRA INCENDIOS - CÁMARA DE COMERCIO RIONEGRO | J70: 12535000 | K70: 43522 | N70: Cristian Rendón
B71: 55 | C71: COTIZACION DEL ANÁLISIS DE SEGURIDAD HUMANA - TURIN | J71: 2430000 | K71: 43523 | N71: Saray David Barrientos
B72: 56 | C72: COTIZACION DE LOS DISEÑOS DE SEGURIDAD HUMANA Y PROTECCIÓN CONTRA INCENDIOS - EDIFICIO BEDOUT VICTOR | J72: 7985000 | K72: 43523 | N72: Robinson A. Morales García
B73: 57 | C73: COTIZACION DE LOS DISEÑOS DE PROTECCIÓN CONTRA INCENDIOS - ENTRE CEJAS Y PESTAÑAS | J73: 590000 | K73: 43524 | N73: Jhonny Castro
B74: 58 | C74: COTIZACION DEL DISEÑO DE EXTINCIÓN DE INCENDIOS - QUIRÓFANOS MAYORCA | J74: 3293000 | K74: 43525 | N74: Nora Luz Berrio Arango
B75: 59 | C75: COTIZACION DEL DISEÑO DE EXTINCIÓN DE INCENDIOS PARA EL PROYECTO LOCAL TAKOUT SANTAFE | J75: 330000 | K75: 43525 | N75: David Lopera
B76: 60 | C76: COTIZACION DE LOS DISEÑOS DE PROTECCIÓN CONTRA INCENDIOS PARA EL PROYECTO LOCAL NOISE VIVA ENVIGADO | J76: 990000 | K76: 43528 | N76: Camilo López
B77: 61 | C77: COTIZACION DE LOS DISEÑOS DE PROTECCIÓN CONTRA INCENDIOS - CANTAGIRONE SETTE | J77: 14926000 | K77: 43529 | N77: Laura Osorio
B78: 62 | C78: COTIZACION DEL DISEÑO DE EXTINCIÓN DE INCENDIOS PARA EL PROYECTO LOCAL 162 DE PALMAGRANDE | J78: 320000 | K78: 43529 | N78: David Lopera
B79: 63 | C79: COTIZACION DEL DISEÑO DE DETECCIÓN DE INCENDIOS - CASA CULTURAL LA ESTRELLLA | J79: 650000 | K79: 43529 | N79: Laura Osorio
B80: 63 | C80: COTIZACION DEL DISEÑO DE DETECCIÓN DE INCENDIOS PARA EL PROYECTO PALACIO MUNICIPAL CONCORDIA | J80: 1620000 | K80: 43535 | N80: Laura Osorio
B81: 64 | C81: COTIZACION DE LOS DISEÑOS DE PROTECCIÓN CONTRA INCENDIOS - PROYECTO OFICINAS GUATEMALA | J81: 1016 | K81: 43529 | N81: Julio Alejandro Llamas
B82: 65 | C82: COTIZACION DEL DISEÑO DE EXTINCIÓN DE INCENDIOS PARA EL PROYECTO BODEGA FORMAS ÍNTIMAS | J82: 2740000 | K82: 43529 | N82: Liber Restrepo
B83: 66 | C83: COTIZACION DE LOS DISEÑOS DE PROTECCIÓN CONTRA INCENDIOS PARA EL PROYECTO OFICINA 0225 SAN FRANCISCO | J83: 550000 | K83: 43529
B84: 67 | C84: COTIZACION DE LOS DISEÑOS DE SEGURIDAD HUMANA Y PROTECCIÓN CONTRA INCENDIOS - EDIFICIO DOCENCIA CES | J84: 19995000 | K84: 43531 | N84: Jhoam Andres Giraldo
B85: 68 | C85: COTIZACION DEL DISEÑO DE EXTINCIÓN DE INCENDIOS - PARQUE EMPRESARIAL RIONEGRO | J85: Variable | K85: 43531 | N85: Rafael Sánchez
B86: 69 | C86: COTIZACION DE LOS DISEÑOS DE SEGURIDAD HUMANA Y EXTINCIÓN DE INCENDIOS - MAKRO BARRANQUILLA VERSIÓN 1 | J86: 14586000 | K86: 43531 | N86: Andrés Peláez Ospina
B87: 70 | C87: COTIZACION DE LOS DISEÑOS DE SEGURIDAD HUMANA Y PROTECCIÓN CONTRA INCENDIOS - BODEGA PARTEQUIPOS GUARNE | J87: 18440000 | K87: 43531 | N87: Adriana Alarcón
B88: 71 | C88: COTIZACION DE LOS DISEÑOS DE PROTECCIÓN CONTRA INCENDIOS Y SEGURIDAD HUMANA PARA EL PROYECTO MONTPELLIER | J88: 14900000 | K88: 43532 | N88: Giovanni Andrés Usme Osorio
B89: 72 | C89: COTIZACION DE LOS DISEÑOS DE PROTECCIÓN CONTRA INCENDIOS - CLÍNICA META | J89: 11763000 | K89: 43532 | N89: Albeiro Ríos
B90: 73 | C90: COTIZACION DE LOS DISEÑOS DE PROTECCIÓN CONTRA INCENDIOS Y SEGURIDAD HUMANA PARA EL PROYECTO ELITE 2 | J90: 11250000 | K90: 43532 | N90: Ana María Tamayo Correa
B91: 74 | C91: COTIZACION DEL DISEÑO DE DETECCIÓN DE INCENDIOS - PALACIO MUNICIPAL CONCORDIA | J91: 1620000 | K91: 43535
B92: 75 | C92: COTIZACION DE LOS DISEÑOS DE PROTECCIÓN CONTRA INCENDIOS Y SEGURIDAD HUMANA PARA EL PROYECTO PLANTA DE PROCESOS ANTILLANA | J92: 13755000 | K92: 43536 | N92: Juan Pablo Grajales
B93: 76 | C93: COTIZACION DEL DISEÑO DE EXTINCIÓN DE INCENDIOS PARA EL PROYECTO CUARTOS DE 30 m2 CON INERGEN | J93: 2100000 | K93: 43536 | N93: Francisco José Unda Arango
B94: 77 | C94: COTIZACION DEL DISEÑO DE EXTINCIÓN DE INCENDIOS - METRONORTE | J94: 9588 | K94: 43537 | N94: Julio Alejandro Llamas
B95: 78 | C95: COTIZACION DE LOS DISEÑOS DE PROTECCIÓN CONTRA INCENDIOS Y SEGURIDAD HUMANA PARA EL PROYECTO COLEGIO NORMAL SUPERIOR | J95: 16165000 | K95: 43538 | N95: Walther Molina
B96: 79 | C96: COTIZACION DE LOS DISEÑOS DE PROTECCIÓN CONTRA INCENDIOS Y SEGURIDAD HUMANA PARA EL PROYECTO COLEGIO JOSÉ MIGUEL DE LA CALLE | J96: 10720000 | K96: 43538 | N96: Walther Molina
B97: 80 | C97: COTIZACION DE LOS DISEÑOS DE PROTECCIÓN CONTRA INCENDIOS PARA EL PROYECTO MAZDA MAYORCA | J97: 2820000 | K97: 43539 | N97: David Lopera
B98: 81 | C98: COTIZACION DISEÑOS DE EXTINCIÓN Y DETECCIÓN DE INCENDIOS – OFICINAS CITI. | J98: Variable | K98: 43539 | N98: Andrea Sanchez
B99: 82 | C99: COTIZACION DEL DISEÑO DE EXTINCIÓN DE INCENDIOS PARA EL PROYECTO MENTHA APARTAMENTOS | J99: 8955000 | K99: 43539 | N99: Camilo López
B100: 83 | C100: COTIZACION ASESORÍA DE SEGURIDAD HUMANA Y PROTECCIÓN CONTRA INCENDIOS - COLEGIO VILLAS DE ARANJUEZ | J100: 1317000 | K100: 43542
B101: 84 | C101: COTIZACION DEL DISEÑO DE DETECCIÓN DE INCENDIOS - PLANTA GEM | J101: 5990000 | K101: 43542 | N101: Carolina Castaño Velásquez
B102: 85 | C102: COTIZACION DE LOS DISEÑOS DE SEGURIDAD HUMANA Y PROTECCIÓN CONTRA INCENDIOS - FUNDACIÓN UNIVERSITARIA NAVARRA | J102: 9970000 | K102: 43543 | N102: William Navarro
B103: 86 | C103: COTIZACION DEL DISEÑO DE EXTINCIÓN DE INCENDIOS PARA EL PROYECTO ALMENDROS DE LA CALERA | J103: 12800000 | K103: 43543 | N103: Juan Pablo Grajales
B104: 87 | C104: COTIZACION DEL DISEÑO DE EXTINCIÓN DE INCENDIOS - COOPSANA POBLADO | J104: 4450000 | K104: 43545 | N104: Zully Taborda Sepúlveda
B105: 88 | C105: COTIZACION DEL MODELO EN REVIT DE PROTECCIÓN CONTRA INCENDIOS - W21 | J105: 7250000 | K105: 43546 | N105: HUMBERTO ACEVEDO GUTIERREZ
B106: 89 | C106: COTIZACION DE LOS DISEÑOS DE PROTECCIÓN CONTRA INCENDIOS - COLEGIO AVANZAR | J106: 1590000 | K106: 43546 | N106: Camilo Restrepo Acevedo
B107: 90 | C107: COTIZACION DE LOS DISEÑOS DE SEGURIDAD HUMANA Y PROTECCIÓN CONTRA INCENDIOS - BODEGA LOTE LOS PERICOS MONTERÍA | J107: 15935000 | K107: 43550 | N107: María Cecilia Revueltas
B108: 91 | C108: COTIZACION DE LOS DISEÑOS DE PROTECCIÓN CONTRA INCENDIOS - JARDINES SIERRA | J108: 1980000 | K108: 43550 | N108: Oscar Alberto Velandia
...

Sheet 2020
H1: COTIZACION REVISIÓN Y CONSULTORÍA DEL SISTEMA DE EXTINCIÓN DE INCENDIOS ENTREPINOS
E2: SEGUIMIENTO A COTIZACIONES
S5: Consecutivo repetido
S6: No encontre informacion
B10: Número de cotización | C10: Descripción de la cotización | J10: Cliente | K10: Valor sin IVA | L10: Fecha de cotización | M10: Fecha de aprobación | N10: Telefono | O10: Persona Encargada | P10: Correo
B13: 1 | C13: COTIZACION DEL DISEÑO DE EXTINCIÓN DE INCENDIOS - OLIVE | J13: Scala | K13: 8127000 | L13: 43837 | N13: 3006195142 | O13: Jose Ignacio Echeverri | P13: interventoriaolive@gmail.com
B14: 2 | C14: COTIZACION DEL DISEÑO DE EXTINCIÓN DE INCENDIOS - MEDICOA PISO 1 URGENCIAS | J14: SPCI | K14: 2130000 | L14: 43837 | N14: 3104680508 | O14: Juan Pablo Grajales | P14: juan.grajales@spci.com.co
B15: 3 | C15: COTIZACION DE LOS DISEÑOS DE SEÑALIZACION DE EMERGENCIA Y EXTINTORES PORTÁTILES - BIKE HOUSE | J15: HyM | K15: 1500000 | L15: 43838 | N15: 3014487912 | O15: Evelin Rojas | P15: hidraulicaymontajes@gmail.com
B16: 4 | C16: COTIZACION DE LOS DISEÑOS DE PROTECCIÓN CONTRA INCENDIOS Y SEGURIDAD HUMANA PARA EL PROYECTO SELVA TORRE 1 | J16: SPCI | K16: 10660000 | L16: 43838 | N16: 3104680508 | O16: Juan Pablo Grajales | P16: juan.grajales@spci.com.co
B17: 5 | C17: COTIZACION DE LOS DISEÑOS DE PROTECCIÓN CONTRA INCENDIOS Y SEGURIDAD HUMANA PARA EL PROYECTO SELVA COMPLETO | J17: SPCI | K17: 16935000 | L17: 43838 | N17: 3104680508 | O17: Juan Pablo Grajales | P17: juan.grajales@spci.com.co
B18: 6 | C18: COTIZACION DEL DISEÑO DE EXTINCIÓN DE INCENDIOS - GRUPO DIANA | J18: SPCI | K18: 43900000 | L18: 43840 | N18: 3104680508 | O18: Juan Pablo Grajales | P18: juan.grajales@spci.com.co
B19: 7 | C19: COTIZACION DE LOS DISEÑOS DE PROTECCIÓN CONTRA INCENDIOS - CONSULTORIO 405 CITY MEDICA | J19: SOCOMES | K19: 900000 | L19: 43843 | N19: 3137851941 | O19: David Lopera | P19: david.lopera@socomes.com
B20: 8 | C20: COTIZACION DEL DISEÑO DE EXTINCIÓN DE INCENDIOS - SALA DE LACTANCIA VIVA BARRANQUILLA | J20: SPCI | K20: 900000 | L20: 43843 | M20: X | N20: 3104680508 | O20: Juan Pablo Grajales | P20: juan.grajales@spci.com.co
B21: 9 | C21: COTIZACION DEL DISEÑO DE EXTINCIÓN DE INCENDIOS - PUNTO CERO HYM VIVA BARRANQUILLA | J21: SPCI | K21: 1200000 | L21: 43843 | M21: X | N21: 3104680508 | O21: Juan Pablo Grajales | P21: juan.grajales@spci.com.co
B22: 10 | C22: COTIZACION DE LOS DISEÑOS DE SEGURIDAD HUMANA Y PROTECCIÓN CONTRA INCENDIOS - ADECUACIÓN OFICINA ISA 300 M2 | J22: ENSAMBLE | K22: 3670000 | L22: 43844 | M22: X | O22: Paola A. López Cadavid
B23: 11 | C23: COTIZACION DE LOS DISEÑOS DE PROTECCIÓN CONTRA INCENDIOS Y SEGURIDAD HUMANA PARA EL PROYECTO BODEGA CALDAS PRIMAVERA | J23: SPCI | K23: 19460000 | L23: 43846 | N23: 3104680508 | O23: Juan Pablo Grajales | P23: juan.grajales@spci.com.co
B24: 12 | C24: REVISIÓN DE LOS DISEÑOS DE EXTINCIÓN DE INCENDIOS PARA EL PROYECTO WE WORK ANTEJARDIN | J24: SPCI | K24: 1500000 | L24: 43967 | N24: 3104680508 | O24: Juan Pablo Grajales | P24: juan.grajales@spci.com.co
B25: 13 | C25: COTIZACION DE LOS DISEÑOS DE PROTECCIÓN CONTRA INCENDIOS Y SEGURIDAD HUMANA PARA EL PROYECTO VALLE CENTRAL | J25: SAHA | K25: 8780000 | L25: 43851 | O25: Carlos Darío Mejía
B26: 14 | C26: COTIZACION DE LOS DISEÑOS DE SEGURIDAD HUMANA Y PROTECCIÓN CONTRA INCENDIOS - IE VILLAS DE ARANJUEZ | J26: ESTUDIO CENTRAL | K26: 16000000 | L26: 43851 | M26: X | O26: Alejandro Restrepo Montoya
B27: 15 | C27: COTIZACION DE LOS DISEÑOS DE SEGURIDAD HUMANA Y PROTECCIÓN CONTRA INCENDIOS - PALACIO MUNICIPAL ENVIGADO | J27: LAUREANO FORERO | K27: 19435000 | L27: 43854 | O27: David Gómez
B28: 16 | C28: COTIZACION DE LOS DISEÑOS DE SEGURIDAD HUMANA Y PROTECCIÓN CONTRA INCENDIOS - PAJARO LIMON | J28: PAJARO LIMON | K28: 1305000 | L28: 43489 | O28: Pájaro limón
B29: 17 | C29: COTIZACION DE LOS DISEÑOS DE PROTECCIÓN CONTRA INCENDIOS Y SEGURIDAD HUMANA PARA EL PROYECTO PORTAL DE CANEY | J29: ESTEVAN CASTAÑO | K29: 7940000 | L29: 43493 | O29: Estevan Castaño
B30: 18 | C30: COTIZACION DE LOS DISEÑOS DE PROTECCIÓN CONTRA INCENDIOS Y SEGURIDAD HUMANA PARA EL PROYECTO PARTEQUIPOS | J30: JORGE COLORADO | K30: 25710000 | L30: 43859 | O30: Jorge Humberto Colorado
B31: 19 | C31: COTIZACION DEL DISEÑO DE EXTINCIÓN DE INCENDIOS - TINKKO | J31: HYM | K31: 2500000 | L31: 43860 | O31: Evelin Rojas
B32: 20 | C32: COTIZACIÓN DE LOS PLANOS AS-BUILT DE LA RED GENERAL DE EXTINCIÓN DE INCENDIOS DEL PROYECTO PIZARRA | J32: SPCI | K32: 675000 | L32: 43860 | N32: 3137546144 | O32: Juan Camilo Quintero | P32: proyectos1spci@gmail.com
B33: 21 | C33: COTIZACION DE LOS DISEÑOS DE PROTECCIÓN CONTRA INCENDIOS PARA EL PROYECTO CASA DE LA CULTURA JARDÍN | J33: CIVILSA | K33: 4140000 | L33: 43861 | O33: Julio Alzate
B34: 22 | C34: COTIZACION DE LOS DISEÑOS DE PROTECCIÓN CONTRA INCENDIOS Y SEGURIDAD HUMANA PARA EL PROYECTO VECINO PATIO | J34: ALG PROYECTOS | K34: 3700000 | L34: 43861 | O34: Juan Londoño
B35: 23 | C35: DISEÑOS DE EXTINTORES PORTÁTILES CONTRA INCENDIOS PARA BANCOLOMBIA FLORIDA PARQUE | J35: CONDISEÑO | K35: 1000000 | L35: 43833 | N35: 3175594091 | O35: Nakary García Romero | P35: n.garcia@condiseno.co
B36: 24 | C36: COTIZACION DISEÑO DETECCION HOTEL TEQUENDAMA | J36: RAPIDO | K36: VARIABLE | L36: 43864 | O36: Álvaro Manosalva
B37: 25 | C37: COTIZACION DEL DISEÑO DE DETECCIÓN DE INCENDIOS - TORRE 2 UNIVERSIDAD REMINGTON | J37: SERVICIOS IPM | K37: 4990000 | L37: 43865 | O37: Juan Santiago Londoño Quiceno
B38: 25 | C38: DISEÑO DE DETECCIÓN DE INCENDIOS PARA EL PROYECTO TORRE 2 UNIVERSIDAD REMINGTON | J38: UNIREMINGTON | K38: 5590000 | L38: 43881 | O38: Gloria María González Villa
B39: 26 | C39: COTIZACION DE LOS DISEÑOS DE SEGURIDAD HUMANA Y PROTECCIÓN CONTRA INCENDIOS - COMEDOR CLÍNICA LAS AMÉRICAS | J39: INTERVÉ | K39: 3765000 | L39: 43866 | O39: Martha Lucía Ferrer
B40: 27 | C40: COTIZACION DE LOS DISEÑOS DE PROTECCIÓN CONTRA INCENDIOS Y SEGURIDAD HUMANA PARA EL PROYECTO CITADELLA JERUSALEN | J40: SOCOMES | K40: 13920000 | L40: 43867 | N40: 3137851941 | O40: David Lopera | P40: david.lopera@socomes.com
B41: 28 | C41: COTIZACION DEL DISEÑO DE DETECCIÓN DE INCENDIOS - ALMACENAMIENTO DE 60.000 BRLS CHACHAGÜI – NARIÑO | J41: SPCI | K41: 6915000 | L41: 43869 | N41: 310 4278593 | O41: Daniel Uribe | P41: duribe86@gmail.com
B42: 29 | C42: COTIZACION DEL DISEÑO DE EXTINCIÓN DE INCENDIOS - TUGO | J42: TUGO | K42: 13550000 | L42: 43869 | O42: Leidy Johana Alarcón
B43: 30 | C43: COTIZACION DE LOS DISEÑOS DE PROTECCIÓN CONTRA INCENDIOS Y SEGURIDAD HUMANA PARA EL PROYECTO MANOS ACTIVAS | J43: ESTEVAN CASTAÑO | K43: 6270000 | L43: 43873 | O43: Estevan Castaño
B44: 31 | C44: COTIZACION DEL DISEÑO DE EXTINCIÓN DE INCENDIOS - TH EL TESORO | J44: SERVICIOS BYR | K44: 1055000 | L44: 43873 | O44: Sergio Andrés Ramos Carmona
B45: 32 | C45: COTIZACION DEL DISEÑO DE DETECCIÓN DE INCENDIOS - PROYECTO GO | J45: FCR SAS | K45: 5500000 | L45: 43874 | M45: X | O45: Judith Elena Trujillo R
B46: 33 | C46: COTIZACION DE LOS DISEÑOS DE PROTECCIÓN CONTRA INCENDIOS EXTERIORES PARA EL PROYECTO FIC-NORTE | J46: AIA | K46: 21320000 | L46: 43875 | O46: Francisco Posada
B47: 34 | C47: COTIZACION DE LOS DISEÑOS DE PROTECCIÓN CONTRA INCENDIOS - EDIFICIO CARMEN VIBORAL CONCIVELSA | J47: MAKROHABITAT | K47: 7605000 | L47: 43875 | O47: David Vélez
B48: 35 | C48: COTIZACION DE LOS DISEÑOS DE SEGURIDAD HUMANA Y DETECCIÓN DE INCENDIOS - HOTEL LLERAS | J48: ORLANDO DELGADO | K48: 3470000 | L48: 43878 | O48: Orlando Delgado Ghunaim
B49: 36 | C49: COTIZACION DE LOS DISEÑOS DE SEGURIDAD HUMANA Y PROTECCIÓN CONTRA INCENDIOS - MIRADOR DEL SUR | J49: MIRADOR DEL SUR | K49: 12870000 | L49: 43878 | O49: Juan Diego León Toro
B50: 37 | C50: COTIZACION DEL DISEÑO DE DETECCIÓN DE INCENDIOS PARA EL PROYECTO PLAY TIME ARKADIA | J50: SPCI | K50: 1500000 | L50: 43879 | O50: Mauricio Gutiérrez B.
B51: 38 | C51: COTIZACION DE LOS DISEÑOS DE SEGURIDAD HUMANA Y PROTECCIÓN CONTRA INCENDIOS - BOSCO SILVESTRE | J51: DBG | K51: 7215000 | L51: 43880 | O51: Andrés Sierra
B52: 39 | C52: COTIZACION DE LOS DISEÑOS DE SEGURIDAD HUMANA Y PROTECCIÓN CONTRA INCENDIOS - AWA LIVING | J52: SAHA | K52: 21960000 | L52: 43880 | M52: X | O52: Juan Carlos Martínez P.
B53: 40 | C53: COTIZACION DEL ANÁLISIS DE SEGURIDAD HUMANA - LABORATORIO CIB UNIVERSIDAD NACIONAL | J53: CONDISEÑO | K53: 4610000 | L53: 43880 | O53: Santiago Arroyave López
B54: 41 | C54: COTIZACION DE LOS DISEÑOS DE PROTECCIÓN CONTRA INCENDIOS - BOEGA NUEVA APIX | J54: APIX | K54: 14360000 | L54: 43881 | O54: Yennifer Tatiana Rico
B55: 42 | C55: COTIZACION DE LOS DISEÑOS DE PROTECCIÓN CONTRA INCENDIOS - BODEGA ARARY | J55: JUAN CARLOS RAMIREZ | K55: 13170000 | L55: 43881 | O55: Juan Carlos Ramírez
B56: 43 | C56: COTIZACION DE LOS DISEÑOS DE SEGURIDAD HUMANA Y PROTECCIÓN CONTRA INCENDIOS - BLOQUE 41 UNIVERSIDAD NACIONAL | J56: CONDISEÑO | K56: 4955000 | L56: 43881 | M56: X | N56: 3175594091 | O56: Nakary García Romero | P56: n.garcia@condiseno.co
B57: 44 | C57: COTIZACION DE LOS DISEÑOS DE PROTECCIÓN CONTRA INCENDIOS - EDIFICIO DEL CAFÉ | J57: SOCOMES | K57: 3430000 | L57: 43881 | N57: 3137851941 | O57: David Lopera | P57: david.lopera@socomes.com
B58: 45 | C58: COTIZACION DE LOS DISEÑOS DE PROTECCIÓN CONTRA INCENDIOS - EDIFICIO DEL CAFÉ | J58: PROCOI | K58: 3760000 | L58: 43882 | O58: Brayan Agudelo
B59: 46 | C59: COTIZACION DE LOS DISEÑOS DE PROTECCIÓN CONTRA INCENDIOS - FLEXIWORK | J59: MENSULA | K59: 6900000 | L59: 43883
B60: 47 | C60: COTIZACION DEL ANÁLISIS DE SEGURIDAD HUMANA - FLEXIWORK | J60: MENSULA | K60: 1380000 | L60: 43885 | O60: Sebastián Giraldo Hoyos
B61: 48 | C61: COTIZACION DE LOS DISEÑOS DE PROTECCIÓN CONTRA INCENDIOS Y SEGURIDAD HUMANA PARA EL PROYECTO ANTALYA | J61: GISAICO | K61: 16210000 | L61: 43886 | O61: Claudia Ramírez
B62: 49 | C62: COTIZACION DEL DISEÑO DE EXTINCIÓN DE INCENDIOS - CONEXIONES DE MANGUERA TODA LA PLANTA | J62: HyM | K62: 12290000 | L62: 43886 | N62: 3014487912 | O62: Evelin Rojas | P62: hidraulicaymontajes@gmail.com
B63: 50 | C63: COTIZACION DEL DISEÑO DE EXTINCIÓN DE INCENDIOS - CONEXIONES DE MANGUERA CDI | J63: HyM | K63: 5020000 | L63: 43886 | N63: 3014487912 | O63: Evelin Rojas | P63: hidraulicaymontajes@gmail.com
B64: 51 | C64: DISEÑO DE SEGURIDAD HUMANA Y EXTINCIÓN DE INCENDIOS - EDIFICIO CONQUISTADORES | J64: ALEJANDRO GOMEZ | K64: 6575000 | L64: 43886 | O64: Alejandro Gómez
B65: 52 | C65: COTIZACION DE LOS DISEÑOS DE PROTECCIÓN CONTRA INCENDIOS - RACKETBALL EL TESORO | J65: MAKROHABITAT | K65: 1260000 | L65: 43886 | O65: David Vélez
B66: 53 | C66: COTIZACION DE LOS DISEÑOS DE PROTECCIÓN CONTRA INCENDIOS Y SEGURIDAD HUMANA PARA EL PROYECTO EDIFICIO WEDSTON | J66: Ingeniería y Espacios Arquitectos | K66: 8780000 | L66: 43889 | O66: José David Román
B67: 54 | C67: COTIZACION DEL MODELO EN REVIT DE PROTECCIÓN CONTRA INCENDIOS - CENTRO DE NEGOCIOS MANGA | J67: Inversiones Arbo | K67: 5270000 | L67: 43889 | O67: Juan Camilo Aristizabal
B68: 55 | C68: COTIZACION DE LOS DISEÑOS DE SEGURIDAD HUMANA Y PROTECCIÓN CONTRA INCENDIOS - PUNTOS COLOMBIA | J68: GERENCIA INTEGRAL | K68: 3955000 | L68: 43889 | O68: Humberto Duque
B69: 56 | C69: COTIZACION DE LA INGENIERÍA DE DETALLE DE LA EXTINCIÓN DE INCENDIOS - TELEPERFORMANCE | J69: TELEPERFORMANCE | K69: 12950000 | L69: 43889 | O69: Javier Bohorquez Poveda
B70: 57 | C70: COTIZACION DE LOS DISEÑOS DE PROTECCIÓN CONTRA INCENDIOS - PISO 3 PLAZA FABRICATO REVIT | J70: INTERVÉ | K70: 3500000 | L70: 43892 | O70: Darío Saldarriaga
A71: 59 | B71: 58 | C71: COTIZACION DEL DISEÑO DE EXTINCIÓN DE INCENDIOS - BODEGA 500 700 EXITO | J71: JOMARK | K71: 46115000 | L71: 43892
B72: 59 | C72: COTIZACION DE LOS DISEÑOS DE PROTECCIÓN CONTRA INCENDIOS - BLOQUE 2 ESUMER | J72: JOMARK | K72: 7950000 | L72: 43892 | O72: Angélica Montoya
B73: 60 | C73: COTIZACION DE LOS DISEÑOS DE SEGURIDAD HUMANA Y PROTECCIÓN CONTRA INCENDIOS - LIBERTE | J73: IAC | K73: 34575000 | L73: 43894 | O73: David Álvarez.
B74: 61 | C74: COTIZACION DEL DISEÑO DE DETECCIÓN DE INCENDIOS - BODEGA INDUSTRIAS KENT | J74: INDUSTRIAS KENT | K74: 3200000 | L74: 43896 | O74: Vanesa Muñoz
B75: 62 | C75: COTIZACION DEL DISEÑO DE EXTINCIÓN DE INCENDIOS - NEUROMÉDICA PLAZA CENTRAL | J75: JOMARK | K75: 2031000 | L75: 43899 | O75: Angélica Montoya
B76: 63 | C76: COTIZACION DEL DISEÑO DE DETECCIÓN DE INCENDIOS - HANGAR 28 X 25 | J76: CONSTRUCCIONES SAFEST | K76: 2630000 | L76: 43899 | N76: 3004827270 | O76: Gabriel Jaime Sánchez | P76: gerencia@construccionessafest.com
B77: 64 | C77: COTIZACION DEL DISEÑO DE DETECCIÓN DE INCENDIOS PARA EL PROYECTO 4 TORRES DEL PROYECTO ÍNDIGO | J77: SOCOMES | K77: 4330000 | L77: 43899 | O77: Jhon Anderson Gómez
B78: 65 | C78: COTIZACION DE LOS DISEÑOS DE SEGURIDAD HUMANA Y PROTECCIÓN CONTRA INCENDIOS - LA CUMBRE | J78: I+CONSTRUCTORA | K78: 23560000 | L78: 43900 | O78: William Londoño
B79: 66 | C79: COTIZACION DEL DISEÑO DE DETECCIÓN DE INCENDIOS - HOTEL SAN JOAQUIN | J79: SPCI | K79: 3950000 | L79: 43907 | N79: 3104278593 | O79: Daniel Uribe | P79: duribe86@gmail.com
B80: 67 | C80: COTIZACIÓN REDISEÑO PISO 5 ARKADIA CLÍNICA LAS AMÉRICAS | J80: INTERVÉ | K80: 439000 | L80: 43907 | M80: X | O80: Martha Lucía Ferrer
B81: 68 | C81: COTIZACION DE LOS DISEÑOS DE SEGURIDAD HUMANA Y PROTECCIÓN CONTRA INCENDIOS - LA CUMBRE | J81: SPCI | K81: 23560000 | L81: 43908 | N81: 3104680508 | O81: Juan Pablo Grajales | P81: juan.grajales@spci.com.co
B82: 69 | C82: COTIZACION DE LOS DISEÑOS DE SEGURIDAD HUMANA Y PROTECCIÓN CONTRA INCENDIOS - LA CUMBRE | J82: SECURETEC | K82: 23560000 | L82: 43917 | M82: X | O82: Jhonny Castro
A83: 69 | B83: 70 | C83: COTIZACION DE LOS DISEÑOS DE PROTECCIÓN CONTRA INCENDIOS PARA EL PROYECTO PARCELACIÓN MONTESOL VILLAS DE VERANO | J83: SOCOMES | K83: 3980000 | L83: 43917 | N83: 3137851941 | O83: David Lopera | P83: david.lopera@socomes.com
B84: 71 | C84: COTIZACION DE LOS DISEÑOS DE SEGURIDAD HUMANA Y PROTECCIÓN CONTRA INCENDIOS - ASOCIA | J84: ALBERTO ALVAREZ | K84: 7905000 | L84: 43920 | O84: Juliana Valencia
B85: 72 | C85: COTIZACION DEL REDISEÑO DE EXTINCIÓN DE INCENDIOS - APTOS ACUARELA DEL PARQUE | J85: ARQUITECTURA Y CONCRETO | K85: 990000 | L85: 43922 | M85: X | O85: David Velásquez
B86: 73 | C86: COTIZACION DE LOS DISEÑOS DE SEGURIDAD HUMANA Y PROTECCIÓN CONTRA INCENDIOS - VERTICALL | J86: PVG | K86: 24170000 | L86: 43923 | O86: Verónica Lopera Aguirre
B87: 74 | C87: COTIZACION DE LOS DISEÑOS DE SEGURIDAD HUMANA Y EXTINCIÓN DE INCENDIOS - SAN NICOLAS ETAPA 3 | J87: HIDRO F SALILNAS | K87: 26960000 | L87: 43923 | M87: X | O87: Carolina Volkmar
B88: 75 | C88: COTIZACION DEL DISEÑO DE EXTINCIÓN DE INCENDIOS - MADELO | J88: JOMARK | K88: 1000000 | L88: 43923 | O88: Angélica Montoya
B89: 76 | C89: COTIZACION DE LOS DISEÑOS DE SEGURIDAD HUMANA - ASOCIA | J89: ALBERTO ALVAREZ | K89: 2195000 | L89: 43924 | M89: 44124 | O89: Juliana Valencia
B90: 77 | C90: COTIZACION DE LOS DISEÑOS DE PROTECCIÓN CONTRA INCENDIOS Y SEGURIDAD HUMANA PARA EL PROYECTO REFORMA DE 3 PISOS UNIVERSIDAD DEL ROSARIO | J90: SPCI | K90: 11850000 | L90: 43924 | N90: 3104680508 | O90: Juan Pablo Grajales | P90: juan.grajales@spci.com.co
B91: 78 | C91: REDISEÑOS ARAGUA | J91: SPCI | K91: 1820000 | L91: 43928 | M91: X | N91: 3104680508 | O91: Juan Pablo Grajales | P91: juan.grajales@spci.com.co
B92: 79 | C92: COTIZACION DE LOS DISEÑOS DE SEGURIDAD HUMANA Y PROTECCIÓN CONTRA INCENDIOS - CERVECERÍA GUARDIAN | J92: CERVECERIA GUARDIAN | K92: 8480000 | L92: 43936 | O92: Oscar Contreras / Manuel Contreras
B93: 80 | C93: COTIZACION DE LOS DISEÑOS DE SEGURIDAD HUMANA Y PROTECCIÓN CONTRA INCENDIOS - OZ | J93: RRP | K93: 15985000 | L93: 43936 | M93: X | N93: 3104300137 | O93: Roberto Pineda | P93: roberto.pineda@rrp.com.co
B94: 81 | C94: COTIZACION DE LOS DISEÑOS DE SEGURIDAD HUMANA Y PROTECCIÓN CONTRA INCENDIOS - BODEGA PRIMAVERA RED GRAL | J94: MENSULA | K94: 22370000 | L94: 43944
B95: 82 | C95: COTIZACION DE LOS DISEÑOS DE SEGURIDAD HUMANA Y PROTECCIÓN CONTRA INCENDIOS - BODEGA PRIMAVERA TOTAL | J95: MENSULA | K95: 49955000 | L95: 43944 | O95: María Eugenia Ospina A
B96: 83 | C96: COTIZACION DE INTERVENTORÍA A LA INSTALACIÓN DE LOS SISTEMAS DE PROTECCIÓN CONTRA INCENDIOS PARA LA PLANTA RIDUCO | J96: RIDUCO | K96: 1100000 | L96: 43955 | O96: Luis Felipe Pérez
B97: 84 | C97: COTIZACION DE LOS DISEÑOS DE SEGURIDAD HUMANA Y PROTECCIÓN CONTRA INCENDIOS - MARSH & MCLENNAN | J97: STUDIO SUR | K97: 19780000 | L97: 43951 | O97: Andrea Pineda
B98: 85 | C98: COTIZACION DEL ANÁLISIS DE SEGURIDAD HUMANA PARA EL PROYECTO OFICINAS MARSH & MCLENNAN BOGOTÁ | J98: STUDIO SUR | K98: 3525000 | L98: 43951 | M98: X | O98: Andrea Pineda
B99: 86 | C99: COTIZACION DE LOS DISEÑOS DE PROTECCIÓN CONTRA INCENDIOS PARA EL PROYECTO FRUTOS VERDES | J99: CONINTEL | K99: 14990000 | L99: 43957 | O99: Doris Duarte
B100: 87 | C100: COTIZACION DE LOS DISEÑOS DE PROTECCIÓN CONTRA INCENDIOS Y SEGURIDAD HUMANA PARA EL PROYECTO COLEGIO JHON F KENNEDY | J100: RRP | K100: 13990000 | L100: 43958 | O100: Álvaro Rojas
B101: 88 | C101: COTIZACION DE LOS DISEÑOS DE PROTECCIÓN CONTRA INCENDIOS Y SEGURIDAD HUMANA PARA EL PROYECTO CDI ENVIGADO | J101: RRP | K101: 7520000 | L101: 43958 | O101: Álvaro Rojas
B102: 89 | C102: COTIZACION DE LOS DISEÑOS DE PROTECCIÓN CONTRA INCENDIOS Y SEGURIDAD HUMANA PARA EL PROYECTO TERRAZZINO SUR | J102: GINO | K102: VARIABLE | L102: 43959 | O102: Lina Gonzáles
B103: 90 | C103: COTIZACION DE LOS DISEÑOS DE SEGURIDAD HUMANA Y PROTECCIÓN CONTRA INCENDIOS - BOSQUE SAGRADO | J103: GINO | K103: 14240000 | L103: 43960 | N103: 310 4242961 | O103: Ana Maria Escobar
B104: 91 | C104: COTIZACION DE LOS DISEÑOS DE PROTECCIÓN CONTRA INCENDIOS Y SEGURIDAD HUMANA PARA EL PROYECTO BLOQUES 42 Y 42A UNAL | J104: GINO | K104: 9055000 | L104: 43962 | O104: Johan Ferney Tamayo
B105: 92 | C105: COTIZACION DE LOS DISEÑOS DE PROTECCIÓN CONTRA INCENDIOS Y SEGURIDAD HUMANA PARA EL PROYECTO RESIDENCIAL PINARES | J105: GINO | K105: 14895000 | L105: 43962 | N105: 310 4242961 | O105: Ana Maria Escobar
B106: 93 | C106: COTIZACION DEL RE-DISEÑO DE EXTINCIÓN DE INCENDIOS PARA EL PROYECTO PLEXA | J106: SPCI | K106: 5400000 | L106: 43964 | M106: X | N106: 310 4278593 | O106: Daniel Uribe | P106: duribe86@gmail.com
B107: 94 | C107: COTIZACION DEL ANÁLISIS DE SEGURIDAD HUMANA PARA EL PROYECTO AUDITORIO | J107: JOMARK | K107: 1945000 | L107: 43964 | N107: 319 4913179 | O107: Carlos Almanya
...

Sheet 2021
E2: SEGUIMIENTO A COTIZACIONES
S5: Consecutivo repetido
S6: No encontre informacion
B10: Número de cotización | C10: Descripción de la cotización | J10: Cliente | K10: Valor sin IVA | L10: Fecha de cotización | M10: Fecha de aprobación | N10: Telefono | O10: Persona Encargada | P10: Correo
B13: 1 | C13: COTIZACION DE LOS DISEÑOS DE PROTECCIÓN CONTRA INCENDIOS - CLUB HOUSE VIVA ENVIGADO | J13: AREAS FLEXIBLES | K13: 2850000 | L13: 44202 | N13: 319 280 96 29 | O13: Andrés López Gallón | P13: arquitecto@areasflexibles.com
B14: 2 | C14: COTIZACION DE LOS DISEÑOS DE SEGURIDAD HUMANA Y PROTECCIÓN CONTRA INCENDIOS - BANCOLOMBIA FIC48 | J14: STUDIO SUR | K14: 19930000 | L14: 44209 | N14: 3134669894 | O14: Andrea Sanchez | P14: andrea.sanchez@studiosur.net
B15: 3 | C15: COTIZACION DE LOS DISEÑOS DE SEGURIDAD HUMANA Y PROTECCIÓN CONTRA INCENDIOS - EDIFICIO CATTLEYA | J15: SPCI | K15: 19940000 | L15: 44209 | N15: 3104680508 | O15: Juan Pablo Grajales | P15: juan.grajales@spci.com.co
B16: 4 | C16: COTIZACION DE LOS DISEÑOS DE SEGURIDAD HUMANA Y PROTECCIÓN CONTRA INCENDIOS - BORAL RIONEGRO | J16: MÉNSULA | K16: 19950000 | L16: 44210 | N16: 3207091752 | O16: Cristian Londoño Montoya | P16: cristianlondono@mensulaingenieros.com
B17: 5 | C17: COTIZACION DIAGNÓSTICO SEGURIDAD HUMANA Y PROTECCIÓN CONTRA INCENDIOS - La FLA | J17: RISK | K17: 6000000 | L17: 44211 | N17: 3104473509 | O17: Carlos Alberto Gil Valencia | P17: carlos.gil@risksg.com
B18: 6 | C18: COTIZACION DE LOS DISEÑOS DE PROTECCIÓN CONTRA INCENDIOS - LABORATORIO CLINICA LAS AMÉRICAS | J18: INTERVÉ | K18: 3580000 | L18: 44211 | N18: 57(4) 352 3434 | O18: Humberto Acevedo | P18: hacevedo@interve.co
B19: 7 | C19: COTIZACION DE LOS DISEÑOS DE SEGURIDAD HUMANA Y PROTECCIÓN CONTRA INCENDIOS - EDIFICIO BLOQUE 3 SONSÓN UDEA | J19: SERVICIOS IPM | K19: 7200000 | L19: 44214 | M19: X | N19: 3015421412 | O19: Juan Londoño | P19: juan.londono@serviciosipm.com
B20: 8 | C20: COTIZACION DE LOS DISEÑOS DE SEGURIDAD HUMANA Y PROTECCIÓN CONTRA INCENDIOS - CAMPO NUEVO | J20: SECURETEC | K20: 14450000 | L20: 44214 | N20: 312 405 4584 | O20: Maribel Osorio | P20: ascomercial@securetec.com.co
B21: 9 | C21: COTIZACION PLANOS ASBUILT PLAZA FABRICATO PISO 1 | J21: SPCI | K21: 750000 | L21: 44215 | N21: 3104165783 | O21: Cristiam Mondragón | P21: cristiamondragon.spci@gmail.com
B22: 10 | C22: COTIZACION DEL DISEÑO DE DETECCIÓN DE INCENDIOS - MALL COMERCIAL CIMARRONAS | J22: CIMARRONAS | K22: 3500000 | L22: 44216 | N22: 301 3859970 | O22: Juan Carlos Gallego | P22: sptcimarronas@gmail.com
B23: 11 | C23: COTIZACION DE LOS DISEÑOS DE PROTECCIÓN CONTRA INCENDIOS - PLANTA RIONEGRO CLC | J23: SPCI | K23: 9900000 | L23: 44216 | N23: 3104680508 | O23: Juan Pablo Grajales | P23: juan.grajales@spci.com.co
B24: 12 | C24: COTIZACION DE LOS DISEÑOS DE SEGURIDAD HUMANA Y PROTECCIÓN CONTRA INCENDIOS - PLANTA RDC INDURAL | J24: DGB | K24: 13950000 | L24: 44217 | N24: 3127075530 | O24: Paula Jimenez | P24: pjimenezdgb@gmail.com
B25: 13 | C25: COTIZACION DEL DISEÑO DE DETECCIÓN DE INCENDIOS - ACRE | J25: CASA SANA | K25: 4950000 | L25: 44221 | N25: 3108945703 | O25: Jose Estrada | P25: joseestrada@casasana.com.co
B26: 14 | C26: COTIZACION CONCEPTO TÉCNICO DE PROTECCIÓN TANQUE DE ACPM EDIFICIO EPM | J26: INFRATELCO | K26: 2650000 | L26: 44221 | M26: X | N26: 312 7726924 | O26: Andres Muñoz | P26: infratelcosas@gmail.com
B27: 15 | C27: COTIZACION DEL DISEÑO DE EXTINCIÓN DE INCENDIOS PARA EL PROYECTO BODEGA SECADO ECOCEMENTOS | J27: SPCI | K27: 6900000 | L27: 44221 | N27: 3137546144 | O27: Juan Camilo Quintero | P27: proyectos1spci@gmail.com
B28: 16 | C28: COTIZACION DE LOS DISEÑOS DE PROTECCIÓN CONTRA INCENDIOS - ALAMEDA | J28: ARPRE | K28: 1550000 | L28: 44225 | N28: 3052925725 | O28: Luz Marina Restrepo | P28: elarpre.deco@gmail.com
B29: 17 | C29: COTIZACION DEL ANÁLISIS DE SEGURIDAD HUMANA - HOUSSING | J29: JHON ARISTIZABAL | K29: 2250000 | L29: 44225 | N29: 311 4337099 | O29: John Aristizabal | P29: jad@unoendiez.com.co
B30: 18 | C30: COTIZACION DE LOS DISEÑOS DE PROTECCIÓN CONTRA INCENDIOS - AGN PERÚ | J30: FPSG | K30: 17540 | L30: 44225 | N30: 3108227462 | O30: Álvaro Manosalva | P30: alvaromanosalva@sfiregroup.com
B31: 19 | C31: COTIZACION DE LOS DISEÑOS DE SEGURIDAD HUMANA Y PROTECCIÓN CONTRA INCENDIOS - CAOBA | J31: SPCI | K31: 23460000 | L31: 44225 | N31: 4487724 | O31: Laura Montoya | P31: lmontoyaspci@gmail.com
B32: 20 | C32: COTIZACION DE LOS DISEÑOS DE SEGURIDAD HUMANA Y PROTECCIÓN CONTRA INCENDIOS - PRATO | J32: SPCI | K32: 21190000 | L32: 44225 | N32: 4487725 | O32: Laura Montoya | P32: lmontoyaspci@gmail.com
B33: 21 | C33: COTIZACION DE LOS DISEÑOS DE SEGURIDAD HUMANA Y PROTECCIÓN CONTRA INCENDIOS - LIVORINO | J33: SPCI | K33: 21190000 | L33: 44225 | N33: 4487726 | O33: Laura Montoya | P33: lmontoyaspci@gmail.com
B34: 22 | C34: COTIZACION DE LOS DISEÑOS DE SEGURIDAD HUMANA Y PROTECCIÓN CONTRA INCENDIOS - BODEGA ITAGUÍ LAFLA | J34: GINO | K34: 25710000 | L34: 44225 | N34: 3113396273 | O34: Gino Montoya | P34: gino1037@hotmail.com
B35: 23 | C35: COTIZACION DE LOS DISEÑOS DE SEGURIDAD HUMANA Y PROTECCIÓN CONTRA INCENDIOS - ENTREMONTES | J35: INGENIERÍA Y VIVIENDA | K35: 19950000 | L35: 44229 | N35: 3124592 | O35: Alejandro Yepes | P35: alejandroyepes@ingenieriayvivienda.com
B36: 24 | C36: COTIZACION DE LOS DISEÑOS DE SEGURIDAD HUMANA Y PROTECCIÓN CONTRA INCENDIOS - TOPICARIO | J36: TROPICARIO | K36: 7550000 | L36: 44229 | N36: 300 864 37 10 | O36: Cristina Palacio Pérez | P36: cristinapalacio@mensulaingenieros.com
B37: 25 | C37: COTIZACION DE LOS DISEÑOS DE SEGURIDAD HUMANA Y PROTECCIÓN CONTRA INCENDIOS - SIER BUCARAMANGA | J37: ENSAMBLE | K37: 3250000 | L37: 44229 | N37: 3117477239 | O37: Paola López Cadavid | P37: paolopez@ensambleespaciosvivos.com
B38: 26 | C38: COTIZACION DE LOS DISEÑOS DE EXTINCIÓN DE INCENDIOS - ACUARELA DEL RIO | J38: SPCI | K38: 10035000 | L38: 44230 | N38: 3104203649 | O38: Mauricio Guzman | P38: mauroguzmanspci@gmail.com
B39: 27 | C39: COTIZACION DE LOS DISEÑOS DE SEGURIDAD HUMANA Y PROTECCIÓN CONTRA INCENDIOS - ZIMA | J39: SOCOMES | K39: 11920000 | L39: 44230 | N39: 3137851941 | O39: David Lopera | P39: david.lopera@socomes.com
B40: 28 | C40: COTIZACION DEL ANÁLISIS DE SEGURIDAD HUMANA PARA EL PROYECTO BLOQUE 42 A UNAL | J40: UNAL | K40: 3500000 | L40: 44230 | N40: 3113396273 | O40: Gino Montoya | P40: gino1037@hotmail.com
B41: 29 | C41: COTIZACION DEL DISEÑO DE DETECCIÓN DE INCENDIOS - VINOS Y LICORES SAS | J41: SPCI | K41: 9880000 | L41: 44230 | N41: 3104680508 | O41: Juan Pablo Grajales | P41: juan.grajales@spci.com.co
B42: 30 | C42: COTIZACION DE LOS DISEÑOS DE SEGURIDAD HUMANA Y PROTECCIÓN CONTRA INCENDIOS - PLANTA DE ALIMENTOS GUARNE | J42: SOCOMES | K42: 24960000 | L42: 44231 | N42: 3137851941 | O42: David Lopera | P42: david.lopera@socomes.com
B43: 31 | C43: COTIZACION DE LOS DISEÑOS DE SEGURIDAD HUMANA Y PROTECCIÓN CONTRA INCENDIOS - BANCOLOMBIA FIC48 | J43: ESPIRAL | K43: 18190000 | L43: 44231 | N43: 3207198907 | O43: Cristian Marín | P43: cristian.marin@espiral.com.co
B44: 32 | C44: COTIZACION DEL DISEÑO DE DETECCIÓN DE INCENDIOS PARA EL PROYECTO LA MARINA | J44: SPCI | K44: 3760000 | L44: 44231 | M44: X | N44: 3104680508 | O44: Juan Pablo Grajales | P44: juan.grajales@spci.com.co
B45: 33 | C45: COTIZACION DEL ANÁLISIS DE SEGURIDAD HUMANA PARA EL PROYECTO CAMPO NUEVO | J45: ADMIRIS | K45: 2000000 | L45: 44231 | M45: X | N45: 3014188503 | O45: Andrés Velázquez | P45: avelasquez@admirisltda.com
B46: 34 | C46: COTIZACION DEL DISEÑO DE DETECCIÓN DE INCENDIOS PARA EL PROYECTO PLANTA ITAGUÍ | J46: COLPA | K46: 6270000 | L46: 44232 | N46: 3014325966 | O46: Juan Camilo Betancur | P46: colpafireinnovationsas@gmail.com
B47: 35 | C47: COTIZACION DEL ANÁLISIS DE SEGURIDAD HUMANA PARA EL PROYECTO BLOQUE 42 A UNAL | J47: ADMIRIS | K47: 2500000 | L47: 44236 | N47: 3014188503 | O47: Andrés Velázquez | P47: avelasquez@admirisltda.com
B48: 36 | C48: COTIZACION DEL ANÁLISIS DE SEGURIDAD HUMANA PARA EL PROYECTO CENTRO DE NEGOCIOS SUR | J48: ADMIRIS | K48: 250000 | L48: 44236 | M48: X | N48: 3014188503 | O48: Andrés Velázquez | P48: avelasquez@admirisltda.com
B49: 37 | C49: COTIZACIÓN DEL SISTEMA DE EXTINCIÓN DE INCENDIOS PARA EL PROYECTO BLOQUE 41 UNAL | J49: CONDISEÑO | K49: 4740000 | L49: 44236 | M49: X | N49: 3175594091 | O49: Nakary García Romero | P49: n.garcia@condiseno.co
B50: 38 | C50: COTIZACION DE LOS DISEÑOS DE SEGURIDAD HUMANA Y PROTECCIÓN CONTRA INCENDIOS - APTOS BELÉN | J50: GINO | K50: 7960000 | L50: 44236 | N50: 3113396273 | O50: Gino Montoya | P50: gino1037@hotmail.com
B51: 39 | C51: COTIZACION EVALUACIÓN DEL SISTEMA DE BOMBA CONTRA INCENDIOS - MITSUBISHI ELECTRIC | J51: MITSUBISHI | K51: 2500000 | L51: 44238 | M51: X | N51: 3178167881 | O51: Carolina Castaño | P51: carolina.castano@melcol.com.co
B52: 40 | C52: COTIZACION DE LOS DISEÑOS DE SEGURIDAD HUMANA Y PROTECCIÓN CONTRA INCENDIOS - EDIFICIO BE SIDE | J52: SOCOMES | K52: 10270000 | L52: 44238 | N52: 3137851941 | O52: David Lopera | P52: david.lopera@socomes.com
B53: 41 | C53: COTIZACION DE LOS DISEÑOS DE SEGURIDAD HUMANA Y PROTECCIÓN CONTRA INCENDIOS - EDIFICIO ATMÓSFERA | J53: SOCOMES | K53: 6770000 | L53: 44238 | N53: 3137851941 | O53: David Lopera | P53: david.lopera@socomes.com
B54: 42 | C54: COTIZACION DEL DISEÑO DE EXTINCIÓN DE INCENDIOS VORTEX - SAN CRISTOBAL Y FRAIJANES | J54: HIDROMAQ | K54: 6200 | L54: 44240 | N54: (502) 5874-6870 | O54: Julio Llamas | P54: jllamas@hidromaq-gt.com
B55: 43 | C55: COTIZACION DE LOS DISEÑOS DE SEGURIDAD HUMANA Y PROTECCIÓN CONTRA INCENDIOS - LA HEREDIA | J55: CONTEX | K55: 8200000 | L55: 44240 | N55: 3014841003 | O55: Anderson Zapata | P55: jzapata@contex.com.co
B56: 44 | C56: COTIZACION DE LOS DISEÑOS DE SEGURIDAD HUMANA Y PROTECCIÓN CONTRA INCENDIOS - TRIBUNALES LA ALPUJARRA | J56: CONVEL | K56: 29950000 | L56: 44242 | N56: 3508866 Ext 130 | O56: Elizabeth Acevedo | P56: elizabethacevedo@convel.co
B57: 45 | C57: COTIZACION DE LOS DISEÑOS DE SEGURIDAD HUMANA Y PROTECCIÓN CONTRA INCENDIOS - CGR SEDE RISARALDA | J57: VHZ INGENIERÍA | K57: 13980000 | L57: 44242 | M57: X | N57: 3166205380 | O57: Daniel Sánchez | P57: administracion@vhz-ingenieria.com
B58: 46 | C58: COTIZACION DE REVISIÓN Y PRUEBAS DE LOS SISTEMAS DE PROTECCIÓN CONTRA INCENDIOS INSTALADOS Y LA SEGURIDAD HUMANA PARA EL PROYECTO SQUARE | J58: GERENCIA INTEGRAL | K58: 6550000 | L58: 44242 | M58: X | N58: 3014383931 | O58: Yury Vélez | P58: yvelez@hdgerenciaintegral.com
B59: 47 | C59: COTIZACION DE LOS DISEÑOS DE PROTECCIÓN CONTRA INCENDIOS Y SEGURIDAD HUMANA PARA EL PROYECTO HOSPITAL | J59: GINO | K59: 5645000 | L59: 44242 | N59: 3113396273 | O59: Gino Montoya | P59: gino1037@hotmail.com
B60: 48 | C60: COTIZACION DEL DISEÑO DE EXTINCIÓN DE INCENDIOS - TANQUES GLP PLANTA JUMBO | J60: SPCI | K60: 10035000 | L60: 44242 | N60: 3104680508 | O60: Juan Pablo Grajales | P60: juan.grajales@spci.com.co
B61: 49 | C61: COTIZACION DEL DISEÑO DE EXTINCIÓN DE INCENDIOS - TANQUES GLP PLANTA PUERTO SALGAR | J61: SPCI | K61: 13250000 | L61: 44242 | N61: 3104680508 | O61: Juan Pablo Grajales | P61: juan.grajales@spci.com.co
B62: 50 | C62: COTIZACION DEL DISEÑO DE EXTINCIÓN DE INCENDIOS PARA EL PROYECTO LOCAL SANTA PARRILLA VIVA ENVIGADO | J62: SANTA PARRILLA | K62: 1700000 | L62: 44243 | N62: 3122322355 | O62: Juan David Ochoa | P62: juan.8arq@gmail.com
B63: 51 | C63: COTIZACION DE LOS DISEÑOS DE SEGURIDAD HUMANA Y PROTECCIÓN CONTRA INCENDIOS - PROYECTO SAN ANTONIO | J63: SOCOMES | K63: 7520000 | L63: 44257 | N63: 3137851941 | O63: David Lopera | P63: david.lopera@socomes.com
B64: 52 | C64: COTIZACION DE LOS DISEÑOS DE SEGURIDAD HUMANA Y EXTINCIÓN DE INCENDIOS - PISO 11 QUIRÓFANOS SALUD VEGAS | J64: INTERVÉ | K64: 2960000 | L64: 44244 | M64: X | N64: 57(4) 352 3434 | O64: Humberto Acevedo | P64: hacevedo@interve.co
B65: 53 | C65: COTIZACION DE LOS DISEÑOS DE SEGURIDAD HUMANA Y PROTECCIÓN CONTRA INCENDIOS - SATURNO | J65: ALEJANDRO GÓMEZ | K65: 11950000 | L65: 44244 | N65: 314 773 90 63 | O65: Alejandro Gómez | P65: alejandrogomezvillegas@gmail.com
B66: 54 | C66: COTIZACIÓN DEL ANÁLISIS DE SEGURIADAD HUMANA PARA PROYECTO ACUARELA DEL RIO | J66: SPCI | K66: 3515000 | L66: 44244 | M66: X | N66: 3104203649 | O66: Mauricio Guzman | P66: mauroguzmanspci@gmail.com
B67: 55 | C67: COTIZACION DEL ANÁLISIS DE SEGURIDAD HUMANA PARA EL PROYECTO UPTOWN 127 | J67: ADMIRIS | K67: 2800000 | L67: 44244 | M67: X | N67: 3014188503 | O67: Andrés Velázquez | P67: avelasquez@admirisltda.com
B68: 56 | C68: COTIZACION DE LOS DISEÑOS DE PROTECCIÓN CONTRA INCENDIOS Y SEGURIDAD HUMANA PARA EL PROYECTO AWA | J68: CONSTRUGEN | K68: 16940000 | L68: 44245 | M68: X | N68: 3174376208 | O68: William Hernandez | P68: william.hernandez@construgen.com
B69: 57 | C69: COTIZACION DE LOS DISEÑOS DE SEGURIDAD HUMANA Y PROTECCIÓN CONTRA INCENDIOS - EDIFICIO FONADE | J69: CONVEL | K69: 27950000 | L69: 44246 | N69: 3508866 Ext 130 | O69: Elizabeth Acevedo | P69: elizabethacevedo@convel.co
B70: 58 | C70: COTIZACION DEL DISEÑO DE EXTINCIÓN DE INCENDIOS - TORRE DE SERVICIOS PLAZA FABRICATO | J70: CONEXO | K70: 3500000 | L70: 44246 | M70: X | N70: 3005861916 | O70: John Jaramillo | P70: jjaramillo@conexoinmobiliario.com
A71: 59 | B71: 59 | C71: COTIZACION DE LOS DISEÑOS DE SEGURIDAD HUMANA Y PROTECCIÓN CONTRA INCENDIOS - PLANTA DE ALIMENTOS GUARNE | J71: SPCI | K71: 20500000 | L71: 44247 | N71: 3017213541 | O71: Juan Camilo Echavarría | P71: dir.comercial@spcisas.com.co
B72: 60 | C72: COTIZACION DE LOS DISEÑOS DE PROTECCIÓN CONTRA INCENDIOS - CENTRO ACEROS | J72: PEDRO PABLO RESTREPO | K72: 2000000 | L72: 44249 | N72: 3004240239 | O72: Pedro Pablo Restrepo Santa Maria. | P72: pedroprpo@gmail.com
B73: 61 | C73: COTIZACIÓN DEL ANÁLISIS DE SEGURIADAD HUMANA PARA PROYECTO SENA LA CEJA | J73: SPCI | K73: 4200000 | L73: 44249 | N73: 3017213541 | O73: Juan Camilo Echavarría | P73: dir.comercial@spcisas.com.co
B74: 62 | C74: COTIZACION DE LOS DISEÑOS DE SEGURIDAD HUMANA Y PROTECCIÓN CONTRA INCENDIOS - SPIAGGIA DI CARTAGENA | J74: IA&C | K74: 22500000 | L74: 44249 | N74: 314 667 5509 | O74: Andres Reinosa | P74: andresreinosa@iayc.co
B75: 63 | C75: COTIZACION DE LOS DISEÑOS DE SEGURIDAD HUMANA Y PROTECCIÓN CONTRA INCENDIOS - CARTÓN DE COLOMBIA | J75: ARQUITECTURA Y CONCRETO | K75: 21350000 | L75: 44251 | N75: 3123618 ext: 2111 | O75: Blanca Saldarriaga Restrepo | P75: blancasaldarriaga@arquitecturayconcreto.com
B76: 64 | C76: COTIZACION DE COMISIONAMIENTO Y PRUEBAS DE LOS SISTEMAS DE PROTECCIÓN CONTRA INCENDIOS INSTALADOS EN LA CENTRAL AMOYA | J76: SPCI | K76: 4500000 | L76: 44252 | M76: X | N76: 3104278593 | O76: Daniel Uribe | P76: duribe86@gmail.com
B77: 65 | C77: COTIZACION DEL DISEÑO DE EXTINCIÓN DE INCENDIOS - PARKLOG | J77: SPCI | K77: 12550000 | L77: 44252 | N77: 3104203649 | O77: Mauricio Guzman | P77: mauroguzmanspci@gmail.com
B78: 66 | C78: COTIZACION DE LOS DISEÑOS DE SEGURIDAD HUMANA Y PROTECCIÓN CONTRA INCENDIOS - PTAR TRANVÍA | J78: SPCI | K78: 37630000 | L78: 44256 | M78: X | N78: 3104203649 | O78: Mauricio Guzman | P78: mauroguzmanspci@gmail.com
B79: 67 | C79: COTIZACION PLANOS ASBUILT VIVA ENVIGADO | J79: SPCI | K79: 25000000 | L79: 44256 | N79: 3137546144 | O79: Juan Camilo Quintero | P79: proyectos1spci@gmail.com
B80: 68 | C80: COTIZACION DEL ANÁLISIS DE SEGURIDAD HUMANA PARA EL PROYECTO VIVE | J80: ADMIRIS | K80: 2800000 | L80: 44256 | M80: X | N80: 3014188503 | O80: Andrés Velázquez | P80: avelasquez@admirisltda.com
B81: 69 | C81: COTIZACION REVISIÓN Y CONSULTORÍA DEL SISTEMA DE PROTECCIÓN CONTRA INCENDIOS QUARTIER | J81: QUARTIER | K81: 950000 | L81: 44257 | M81: X | N81: 310 8372505 | O81: Juan Fernando | P81: okobra3@gmail.com
B82: 70 | C82: COTIZACION DEL DISEÑO DE EXTINCIÓN DE INCENDIOS PARA EL PROYECTO BODEGA CRUZ ROJA GUAYABAL MEDELLÍN | J82: CRUZ ROJA | K82: 7525000 | L82: 44257 | N82: 312 2543533 | O82: Juan Camilo Gomez Bustamante | P82: jcgomez@crantioquia.org.co
A83: 69 | B83: 71 | C83: COTIZACION DEL DISEÑO DE DETECCIÓN DE INCENDIOS - SUBESTACIONES ELECTRICARIBE | J83: SPCI | K83: 2500000 | L83: 44257 | M83: X | N83: 3104203649 | O83: Mauricio Guzman | P83: mauroguzmanspci@gmail.com
B84: 72 | C84: COTIZACION DE LOS DISEÑOS DE SEGURIDAD HUMANA Y PROTECCIÓN CONTRA INCENDIOS - EDIFICIO BE SIDE | J84: PROCOI | K84: 11300000 | L84: 44257 | N84: 3012224544 | O84: Andrés Mauricio Correa | P84: proyectos@procoi.com
B85: 73 | C85: COTIZACION DE LOS DISEÑOS DE SEGURIDAD HUMANA Y PROTECCIÓN CONTRA INCENDIOS - EDIFICIO ATMÓSFERA | J85: CONSTRUTEC | K85: 7450000 | L85: 44257 | O85: Heydy Natalia Marín | P85: heydynaty@gmail.com
B86: 74 | C86: COTIZACION PLANOS DE SEGURIDAD HUMANA - DISTRITO AVIGNON | J86: INDUSTRIAS CRUCE | K86: 1050000 | L86: 44258 | N86: 3147005714 | O86: Juan Manuel Serrano | P86: jmaserrano@gmail.com
B87: 75 | C87: COTIZACION DEL DISEÑO DE EXTINCIÓN DE INCENDIOS PARA LA PLANTA DE MITSUBISHI ELECTRIC BELLO | J87: MITSUBISHI | K87: 3135000 | L87: 44258 | N87: 3178167881 | O87: Carolina Castaño | P87: carolina.castano@melcol.com.co
B88: 76 | C88: COTIZACION DE LOS DISEÑOS DE SEGURIDAD HUMANA Y PROTECCIÓN CONTRA INCENDIOS - HOGAR CALDAS | J88: FUNDACIÓN EMILIANI | K88: 3000000 | L88: 44258 | N88: 315 451 00 01 | O88: Gustavo Betancourt | P88: Gustavo.betancourt@homeideal.com.co
B89: 77 | C89: COTIZACION DEL DISEÑO DE EXTINCIÓN DE INCENDIOS PARA EL PROYECTO ÁREA PISO 1 VIVA ENVIGADO – 1.000 m2 APROX | J89: SPCI | K89: 2950000 | L89: 44259 | N89: 3137546144 | O89: Juan Camilo Quintero | P89: proyectos1spci@gmail.com
B90: 78 | C90: COTIZACION DEL DISEÑO DE EXTINCIÓN DE INCENDIOS PARA EL PROYECTO ÁREA PISO 1 VIVA ENVIGADO – 2.000 m2 APROX | J90: SPCI | K90: 4950000 | L90: 44259 | N90: 3137546144 | O90: Juan Camilo Quintero | P90: proyectos1spci@gmail.com
B91: 79 | C91: COTIZACION DEL DISEÑO DE EXTINCIÓN DE INCENDIOS PARA EL PROYECTO ÁREA PISO 1 VIVA ENVIGADO – 4.500 m2 APROX | J91: SPCI | K91: 8970000 | L91: 44259 | N91: 3137546144 | O91: Juan Camilo Quintero | P91: proyectos1spci@gmail.com
B92: 80 | C92: COTIZACION DEL ANÁLISIS DE SEGURIDAD HUMANA - HYGGE PALMAS | J92: GINO | K92: 3990000 | L92: 44259 | N92: 3113396273 | O92: Gino Montoya | P92: gino1037@hotmail.com
B93: 81 | C93: COTIZACION DEL ANÁLISIS DE SEGURIDAD HUMANA - PARQUE DEL SOL | J93: GINO | K93: 1500000 | L93: 44259 | N93: 3113396273 | O93: Gino Montoya | P93: gino1037@hotmail.com
B94: 82 | C94: COTIZACION DE LOS DISEÑOS DE PROTECCIÓN CONTRA INCENDIOS - EMPANADAS | J94: GINO | K94: 1800000 | L94: 44259 | N94: 3113396273 | O94: Gino Montoya | P94: gino1037@hotmail.com
B95: 83 | C95: COTIZACION DEL DISEÑO DE EXTINCIÓN DE INCENDIOS - ZONAS DESPROTEGIDAS PLAZA FABRICATO | J95: SPCI | K95: 1000000 | L95: 44259 | N95: 3104165783 | O95: Cristiam Mondragón | P95: cristiamondragon.spci@gmail.com
B96: 84 | C96: COTIZACION DEL DISEÑO DE EXTINCIÓN DE INCENDIOS - ALTIPAL GIRARDOTA | J96: ALTIPAL | K96: 24950000 | L96: 44260 | N96: 3203470297 | O96: Juan Carlos Diaz Mayorga | P96: juan.diaz@altipal.com.co
B97: 85 | C97: COTIZACION DEL ANÁLISIS DE SEGURIDAD HUMANA - GO LIVING | J97: INTERVENTORIA FCR | K97: 3750000 | L97: 44260 | M97: X | N97: 3008246874 | O97: Aura Taborda | P97: interventoriagoliving@gmail.com
B98: 86 | C98: COTIZACION DE LOS DISEÑOS DE PROTECCIÓN CONTRA INCENDIOS Y SEGURIDAD HUMANA PARA EL EDIFICIO CARVAJAL PABÓN | J98: RRP ARQUITECTOS | K98: 11920000 | L98: 44264 | M98: X | N98: 310 4300137 | O98: Roberto Pineda | P98: roberto.pineda@rrp.com.co
B99: 87 | C99: COTIZACION DE LOS DISEÑOS DE SEGURIDAD HUMANA Y PROTECCIÓN CONTRA INCENDIOS - SAINT JOSEPH | J99: JAIME AGUILAR | K99: 9410000 | L99: 44263 | N99: 320 7254044 | O99: Jaime Andrés Aguilar | P99: aguilargomez@une.net.co
B100: 88 | C100: COTIZACION DE LOS DISEÑOS DE SEGURIDAD HUMANA Y PROTECCIÓN CONTRA INCENDIOS - ARARAT | J100: JAIME AGUILAR | K100: 8530000 | L100: 44263 | N100: 320 7254044 | O100: Jaime Andrés Aguilar | P100: aguilargomez@une.net.co
B101: 89 | C101: COTIZACION DE LOS DISEÑOS DE SEGURIDAD HUMANA Y PROTECCIÓN CONTRA INCENDIOS - TESORO LIVING | J101: JAIME AGUILAR | K101: 9280000 | L101: 44263 | N101: 320 7254044 | O101: Jaime Andrés Aguilar | P101: aguilargomez@une.net.co
B102: 90 | C102: COTIZACION DE LOS DISEÑOS DE SEGURIDAD HUMANA Y PROTECCIÓN CONTRA INCENDIOS - NUEVA SEDE CLÍNICA SOHEC | J102: GINO | K102: 22195000 | L102: 44263 | N102: 3113396273 | O102: Gino Montoya | P102: gino1037@hotmail.com
B103: 91 | C103: COTIZACION DE LOS DISEÑOS DE SEGURIDAD HUMANA Y PROTECCIÓN CONTRA INCENDIOS - CALLE FLORA | J103: TRAZOS URBANOS | K103: 24950000 | L103: 44264 | N103: 314-773-93-14 | O103: Ana Paulina Isaza E. | P103: paulinaisaza@trazosurbanos.com.co
B104: 92 | C104: COTIZACION DEL DISEÑO DE EXTINCIÓN DE INCENDIOS - INVERPRIMOS | J104: INVERPRIMOS | K104: 11990000 | L104: 44264 | N104: 3137851941 | O104: David Lopera | P104: david.lopera@socomes.com
B105: 93 | C105: COTIZACION DEL RE-DISEÑO DE DETECCIÓN DE INCENDIOS - CAMINO REAL | J105: SANTIAGO ROJAS | K105: 950000 | L105: 44264 | M105: X | N105: 3022295772 | O105: Aurora Rios | P105: proyectos@santiagorojas.com.co
B106: 94 | C106: COTIZACION DEL DISEÑO DE DETECCIÓN DE INCENDIOS - HALL CAJEROS VALLEDUPAR | J106: SANTIAGO ROJAS | K106: 750000 | L106: 44264 | M106: X | N106: 3022295773 | O106: Aurora Rios | P106: proyectos@santiagorojas.com.co
B107: 95 | C107: COTIZACION DEL ANÁLISIS DE SEGURIDAD HUMANA PARA LA UNIVERSIDAD CES SEDE APARTADÓ | J107: CES | K107: 1820000 | L107: 44265 | M107: X | N107: 316 5793596 | O107: Carlos Andrés Saldarriaga | P107: obras@ces.edu.co
B108: 96 | C108: COTIZACION DEL DISEÑO DE EXTINCIÓN DE INCENDIOS - DECATHLON PLAZA FABRICATO | J108: CONEXO | K108: 4200000 | L108: 44265 | N108: 3005861916 | O108: John Jaramillo | P108: jjaramillo@conexoinmobiliario.com
...

Sheet 2022
E3: SEGUIMIENTO A COTIZACIONES
B11: Número de cotización | C11: Descripción de la cotización | J11: Cliente | K11: Valor sin IVA | L11: Fecha de cotización | M11: Aprobado | N11: Telefono | O11: Persona Encargada | P11: Correo
B12: 1 | C12: COTIZACION DEL DISEÑO DE EXTINCIÓN DE INCENDIOS PARA EL PROYECTO KOAJ ALEGRA | J12: JOMARK SEGURIDAD | K12: 2800000 | L12: 44568 | M12: X | N12: 3167344808 | O12: Daniel Echeverry Pérez | P12: proyectos3@jomarkseguridad.com
B13: 2 | C13: COTIZACION DE LOS DISEÑOS DE SEGURIDAD HUMANA Y PROTECCIÓN CONTRA INCENDIOS - PROYECTO 23 LIVING | J13: MENSULA | K13: 18550000 | L13: 44573 | N13: 300 864 37 10 | O13: Cristina Palacio Pérez | P13: cristinapalacio@mensulaingenieros.com
B14: 3 | C14: COTIZACION DEL DISEÑO DE EXTINCIÓN DE INCENDIOS - IBC CALDAS | J14: SPCI | K14: 9950000 | L14: 44573 | N14: 3104680508 | O14: Juan Pablo Grajales | P14: juan.grajales@spci.com.co
B15: 4 | C15: COTIZACION DEL DISEÑO DE DETECCIÓN DE INCENDIOS - ATENEA FAMLIA SANCELA | J15: SERIINCO | K15: 4500000 | L15: 44573 | M15: X | N15: 4442074 | O15: Francisco Unda | P15: francisco.unda@seriinco.com
B16: 5 | C16: COTIZACION DEL DISEÑO DE DETECCIÓN DE INCENDIOS PARA EL PROYECTO LOCAL FRISBY VIVA PALMA | J16: SPCI | K16: 950000 | L16: 44574 | N16: 3137546144 | O16: Juan Camilo Quintero Bedoya | P16: camilo.quintero@spci.com.co
B17: 6 | C17: COTIZACION DE LOS DISEÑOS DE PROTECCIÓN CONTRA INCENDIOS Y SEGURIDAD HUMANA PARA EL PROYECTO PLANTA Mr BONO | J17: SERVICIO IPM | K17: 22750000 | L17: 44574 | N17: 301 542 1412 | O17: Juan Santiago Londoño Quiceno | P17: juan.londono@serviciosipm.com
B18: 7 | C18: COTIZACION DE LOS DISEÑOS DE PROTECCIÓN CONTRA INCENDIOS PARA EL PROYECTO CAMINO DEL VIENTO TORRE 4 | J18: BIENES Y BIENES | K18: 11800000 | L18: 44575 | M18: X | N18: 311 - 8500 Ext.187 | O18: Jazzmín Restrepo Ortiz | P18: jrestrepo@bienesybienes.com.co
B19: 8 | C19: COTIZACION DEL DISEÑO SOPORTES SISMORRESISTENTE ZENÚ SPCI | J19: SPCI | K19: 690000 | L19: 44578 | M19: X | N19: 3104278593 | O19: Daniel Uribe | P19: dir.tecnico@spcisas.com.co
B20: 9 | C20: COTIZACION DE LOS DISEÑOS DE PROTECCIÓN CONTRA INCENDIOS Y SEGURIDAD HUMANA PARA EL PROYECTO HOTEL LA CASTELLANA | J20: RRP ARQUITECTOS | K20: 9400000 | L20: 44579 | O20: Gustavo Canchila | P20: gustavo.canchila@udea.edu.co
B21: 10 | C21: COTIZACION DEL DISEÑO DE EXTINCIÓN DE INCENDIOS PARA EL PROYECTO LOCAL VIVA ENVIGADO- QBANO | J21: SPCI | K21: 1000000 | L21: 44579 | M21: X | O21: Ana Maria Restrepo Mayo | P21: ana.restrepo@spci.com.co
B22: 11 | C22: COTIZACION DE LOS DISEÑOS DE PROTECCIÓN CONTRA INCENDIOS PARA EL PROYECTO PLANTA COOLFOOD | J22: INGENIO BIM | K22: 7450000 | L22: 44581 | N22: 3012311524 | O22: Luisa Fernanda Londoño Ciro | P22: luisa.londono@ingeniobim.co
B23: 12 | C23: COTIZACION DE REVISIÓN Y PRUEBAS DE LOS SISTEMAS DE PROTECCIÓN CONTRA INCENDIOS INSTALADOS Y LA SEGURIDAD HUMANA PARA EL PROYECTO BIO26 | J23: GERENCIA INTEGRAL | K23: 11750000 | L23: 44580 | N23: 57 312 2967935 | O23: Maria Teresa | P23: mlopez@hdgerenciaintegral.com
B24: 13 | C24: COTIZACION DE LOS DISEÑOS DE EXTINCIÓN DE INCENDIOS Y SEGURIDAD HUMANA PARA EL PROYECTO LOCAL COMFAMA CIS PLAZA FABRICATO | J24: INTERVE | K24: 5850000 | L24: 44580 | M24: X | N24: 310 386 17 63 | O24: Dario Antonio Saldarriaga Ramirez | P24: dsaldarriaga@interve.co
B25: 14 | C25: COTIZACION DEL DISEÑO DE EXTINCIÓN DE INCENDIOS - VORTEX AEROCAFE | J25: SFIRE | K25: 3150000 | L25: 44581 | N25: (57) 3108227462 | O25: Alvaro Manosalva | P25: alvaromanosalva@sfiregroup.com
B26: 15 | C26: COTIZACION DE LOS DISEÑOS DE PROTECCIÓN CONTRA INCENDIOS PARA EL PROYECTO FELICITY TORRE 3 Y 4 | J26: GINO | K26: No se cotizó | L26: 44581 | O26: Gino Montoya | P26: gino1037@hotmail.com
B27: 16 | C27: COTIZACION DE LOS DISEÑOS DE PROTECCIÓN CONTRA INCENDIOS PARA EL PROYECTO URBANIZACION SAN MIGUEL | J27: GINO | K27: 25930000 | L27: 44582 | O27: Gino Montoya | P27: gino1037@hotmail.com
B28: 17 | C28: COTIZACION DEL DISEÑO DE EXTINCIÓN DE INCENDIOS PARA EL PROYECTO OFICINA JOMARK | J28: JOMARK SEGURIDAD | K28: 1350000 | L28: 44582 | N28: 3147943785 | O28: Laura Duque Betancur | P28: proyectos2@jomarkseguridad.com
B29: 18 | C29: COTIZACION DEL DISEÑO DE EXTINCIÓN DE INCENDIOS PARA EL PROYECTO TANQUES SUR Y NORTE | J29: SERIINCO | K29: 11290000 | L29: 44586 | N29: 3113391008 | O29: Carlos Enrique Henao | P29: carlos.henao@seriinco.com
B30: 19 | C30: COTIZACION DE LOS DISEÑOS DE PROTECCIÓN CONTRA INCENDIOS PARA EL PROYECTO NOMBRE PROYECTO OFICINA JOMARK | J30: JOMARK SEGURIDAD | K30: 2025000 | L30: 44582 | N30: 3147943785 | O30: Laura Duque Betancur | P30: proyectos2@jomarkseguridad.com
B31: 20 | C31: COTIZACION DEL DISEÑO DE EXTINCIÓN DE INCENDIOS PARA EL PROYECTO VIVACE TORRE 3 | J31: SPCI | K31: 3135000 | L31: 44586 | M31: X | N31: 310 420 3649 | O31: Mauricio Guzmán Urrea | P31: mauricio.guzman@spci.com.co
B32: 21 | C32: COTIZACION DEL DISEÑO DE EXTINCIÓN DE INCENDIOS PARA EL PROYECTO LOCAL GLOW PARTY 11 | J32: SPCI | K32: 1000000 | L32: 44586 | N32: 3104680508 | O32: Juan Pablo Grajales | P32: juan.grajales@spci.com.co
B33: 22 | C33: COTIZACION DEL DISEÑO DE EXTINCIÓN DE INCENDIOS PARA EL PROYECTO LOCAL KUBIKA 7 | J33: SPCI | K33: 1000000 | L33: 44586 | N33: 3104680508 | O33: Juan Pablo Grajales | P33: juan.grajales@spci.com.co
B34: 23 | C34: COTIZACION DE LOS DISEÑOS DE PROTECCIÓN CONTRA INCENDIOS PARA EL PROYECTO MALL ZONA SUR | J34: PROJECT&SOLUCTION | K34: 9970000 | L34: 44586 | O34: Sebastián López Duque | P34: gerencia@projectsolutions.com.co
B35: 24 | C35: COTIZACION DE LOS DISEÑOS DE PROTECCIÓN CONTRA INCENDIOS PARA EL PROYECTO CES CENTRO AMBULATORIO CONSULTA EXTERNA CLINICA | J35: JOMARK SEGURIDAD | K35: 8150000 | L35: 44586 | M35: X | N35: 3147943785 | O35: Laura Duque Betancur | P35: proyectos2@jomarkseguridad.com
B36: 25 | C36: COTIZACION DEL ANÁLISIS DE SEGURIDAD HUMANA PARA EL PROYECTO COLSANITAS CARTAGENA DEL MAR | J36: CONDISEÑO | K36: 5500000 | L36: 44586 | N36: 3175594091 | O36: Nakary García Romero | P36: n.garcia@condiseno.co
B37: 26 | C37: COTIZACION DE LOS RE-DISEÑOS DE PROTECCIÓN CONTRA INCENDIOS Y SEGURIDAD HUMANA PARA EL PROYECTO MAZANTI ETAPA 1 Y 2 | J37: CONSTRUIR OBRAS CIVILES | K37: 6590000 | L37: 44593 | M37: X | N37: 3206284446 | O37: Diana Marcela Cardona Lopez | P37: direccionmazanti@gmail.com
B38: 27 | C38: COTIZACION DE LOS DISEÑOS DE SEGURIDAD HUMANA Y PROTECCIÓN CONTRA INCENDIOS - BANREP BOGOTA | J38: CONVEL | K38: 6590000 | L38: 44587 | N38: 300 258 90 33 | O38: Diana Perez | P38: dianaperez@convel.co
B39: 28 | C39: COTIZACION DE REVISIÓN DE LOS DISEÑOS DE PROTECCIÓN CONTRA INCENDIO - PROYECTO DV | J39: MENSULA | K39: 5400000 | L39: 44465 | M39: X | N39: 57 314 619 81 44 | O39: Angela Bravo | P39: angelabravo@mensulaingenieros.com
B40: 29 | C40: COTIZACION DEL ANÁLISIS DE SEGURIDAD HUMANA PARA EL PROYECTO PISCINAS DEL COMPLEJO ACUATICO | J40: DESUR | K40: 2500000 | L40: 44588 | M40: X | N40: 4801300 Ext. 137 | O40: Olmes Fernando Rodríguez Álzate | P40: olmes.rodriguez@desur.gov.co
B41: 30 | C41: COTIZACION DEL ANÁLISIS DE SEGURIDAD HUMANA - CEDI MARINILLA | J41: CONCONCRETO | K41: 7950000 | L41: 44588 | N41: 314 8646158 | O41: Francisco Restrepo | P41: fjrestrepo@conconcreto.com
B42: 31 | C42: COTIZACION DEL ANÁLISIS DE SEGURIDAD HUMANA - AMPLIACIÓN SEDE PALMIRA | J42: CONCONCRETO | K42: 4750000 | L42: 44588 | N42: 314 8646158 | O42: Francisco Restrepo | P42: fjrestrepo@conconcreto.com
B43: 32 | C43: COTIZACION DE LOS DISEÑOS DE PROTECCIÓN CONTRA INCENDIOS Y SEGURIDAD HUMANA PARA EL PROYECTO LEGADO ETAPA 1 | J43: FCR SAS | K43: 8470000 | L43: 44589 | M43: X | O43: LUZ STELLA IBARRA ARCILA | P43: stellaibarra@gmail.com
B44: 33 | C44: COTIZACION DE LOS DISEÑOS DE PROTECCIÓN CONTRA INCENDIOS Y SEGURIDAD HUMANA PARA EL PROYECTO RUTA 39 | J44: FCR SAS | K44: 17890000 | L44: 44589 | O44: LUZ STELLA IBARRA ARCILA | P44: stellaibarra@gmail.com
B45: 34 | C45: COTIZACION DEL DISEÑO DE EXTINCIÓN DE INCENDIOS PARA EL PROYECTO COMPLEX | J45: GINO | K45: 15000000 | L45: 44593 | O45: Gino Montoya | P45: gino1037@hotmail.com
B46: 35 | C46: COTIZACION DE LOS DISEÑOS DE PROTECCIÓN CONTRA INCENDIOS PARA EL PROYECTO SAJONIA | J46: CONTEX | K46: 5950000 | L46: 44592 | M46: X | O46: Astrid Jhoana Montoya Arias | P46: amontoya@contex.com.co
B47: 36 | C47: COTIZACION DE LOS DISEÑOS DE PROTECCIÓN CONTRA INCENDIOS Y SEGURIDAD HUMANA PARA EL PROYECTO MOKARA | J47: FCR SAS | K47: 18990000 | L47: 44593 | M47: X | O47: Daniela Vélez Cortés | P47: danielavelez.fcr@gmail.com
B48: 37 | C48: COTIZACION DEL DISEÑO DE DETECCIÓN DE INCENDIOS PARA EL PROYECTO AGENCIA MEDELLIN | J48: SPCI | K48: 3950000 | L48: 44593 | O48: Daniel Uribe Sierra | P48: daniel.uribe@spci.com.co
B49: 38 | C49: COTIZACION DE LOS DISEÑOS DE PROTECCIÓN CONTRA INCENDIOS Y SEGURIDAD HUMANA PARA EL PROYECTO FRAGUA (BELVERDE 3) | J49: CONTEX | K49: 20500000 | L49: 44593 | M49: X | O49: Elisa Pantoja Bohorquez | P49: epantoja@contex.com.co
B50: 39 | C50: COTIZACION DE LOS DISEÑOS DE PROTECCIÓN CONTRA INCENDIOS PARA EL PROYECTO CLINICA BEILLÍN | J50: SOLUCIONES INMOBILIARIAS | K50: 8800000 | L50: 44593 | O50: Julian David Giraldo Pineda | P50: jgiraldo@solucionesinmobiliariassas.com6
B51: 40 | C51: COTIZACION DE LOS DISEÑOS DE PROTECCIÓN CONTRA INCENDIOS Y SEGURIDAD HUMANA PARA EL PROYECTO MAZANTI ETAPA 1 Y 2 REV-B | J51: CONSTRUIR OBRAS CIVILES | K51: 6000000 | L51: 44594 | M51: X | N51: 3206284446 | O51: Diana Marcela Cardona Lopez | P51: direccionmazanti@gmail.com
B52: 41 | C52: COTIZACION DE LOS DISEÑOS DE PROTECCIÓN CONTRA INCENDIOS Y SEGURIDAD HUMANA PARA EL PROYECTO BESIDE | J52: CRISTIAN GAÑAN | K52: 9660000 | L52: 44594 | N52: 3105104288 | O52: Cristian Gañan
B53: 42 | C53: COTIZACION DE LOS DISEÑOS DE PROTECCIÓN CONTRA INCENDIOS PARA EL PROYECTO CLINICA BEILLÍN | J53: SPCI | K53: 8800000 | L53: 44594 | N53: 3214826168 | O53: Ana Maria Restrepo Mayo | P53: ana.restrepo@spci.com.co
B54: 43 | C54: COTIZACION DE LOS DISEÑOS DE PROTECCIÓN CONTRA INCENDIOS Y SEGURIDAD HUMANA PARA EL PROYECTO LOCAL DE SERREZUELA | J54: Santiago Rojas | K54: 5630000 | L54: 44595 | N54: 3022295772 | O54: Maria Aurora Rios Ballesteros | P54: proyectos@santiagorojas.com.co
B55: 44 | C55: COTIZACION DEL DISEÑO DE EXTINCIÓN DE INCENDIOS PARA EL PROYECTO BODEGA YUMBO | J55: SPCI | K55: 9990000 | L55: 44596 | N55: 3214826168 | O55: Ana Maria Restrepo Mayo | P55: ana.restrepo@spci.com.co
B56: 45 | C56: COTIZACION DE LOS DISEÑOS DE PROTECCIÓN CONTRA INCENDIOS PARA EL PROYECTO CLINICA LAS VEGAS PISO 10 | J56: SPCI | K56: 5970000 | L56: 44597 | N56: 3214826168 | O56: Ana Maria Restrepo Mayo | P56: ana.restrepo@spci.com.co
B57: 46 | C57: COTIZACION DEL DISEÑO DE DETECCIÓN DE INCENDIOS PARA EL PROYECTO BANCOLOMBIA HALL DE AUTOSERVICIOS PALMETTO | J57: Santiago Rojas | K57: 750000 | L57: 44597 | N57: 3122973291 | O57: Isabel Cristina Jaramillo Pérez | P57: proyectos@santiagorojas.com.co
B58: 47 | C58: COTIZACION DE LOS DISEÑOS DE PROTECCIÓN CONTRA INCENDIOS Y SEGURIDAD HUMANA PARA EL PROYECTO BESIDE | J58: SOCOMES | K58: 9660000 | L58: 44596 | N58: 3137851941 | O58: David Lopera Medina | P58: david.lopera@socomes.com
B59: 48 | C59: COTIZACION DE LOS DISEÑOS DE PROTECCIÓN CONTRA INCENDIOS PARA EL PROYECTO LOCAL 3061B | J59: PROJECT&SOLUCTION | K59: 2260000 | L59: 44597 | N59: 311 3079477 | O59: Sebastian Lopez Duque | P59: gerencia@projectsolutions.com.co
B60: 49 | C60: COTIZACION DE LOS DISEÑOS DE PROTECCIÓN CONTRA INCENDIOS PARA EL PROYECTO LOCAL NUEVO TALLER | J60: PROJECT&SOLUCTION | K60: 5640000 | L60: 44597 | N60: 311 3079477 | O60: Sebastian Lopez Duque | P60: gerencia@projectsolutions.com.co
B61: 50 | C61: COTIZACION DE LOS DISEÑOS DE EXTINCIÓN DE INCENDIOS PARA EL PROYECTO LOCAL 131 LEMONT | J61: SPCI | K61: 1500000 | L61: 44597 | M61: X | N61: 3214826168 | O61: Ana Maria Restrepo Mayo | P61: ana.restrepo@spci.com.co
B62: 51 | C62: COTIZACION DE LOS DISEÑOS DE PROTECCIÓN CONTRA INCENDIOS PARA EL PROYECTO TERRAZINO | J62: TERRAZINO | K62: 8000000 | L62: 44600 | N62: 313 6214678 | O62: Lina Gonzáles | P62: linagonzalez@terrazino.co
B63: 52 | C63: COTIZACION DE LOS DISEÑOS DE PROTECCIÓN CONTRA INCENDIOS Y SEGURIDAD HUMANA PARA EL PROYECTO COLEGIO LA SALLE | J63: CONDISEÑO | K63: 47300000 | L63: 44601 | M63: X | N63: 3175594091 | O63: Nakary García Romero | P63: n.garcia@condiseno.co
B64: 53 | C64: COTIZACION DEL ANÁLISIS DE SEGURIDAD HUMANA PARA EL PROYECTO MIN TORRE 3 | J64: SPCI | K64: 1880000 | L64: 44601 | M64: X | N64: 3214826168 | O64: Ana Maria Restrepo Mayo | P64: ana.restrepo@spci.com.co
B65: 54 | C65: COTIZACION DEL DISEÑO DE EXTINCIÓN DE INCENDIOS PARA EL PROYECTO LOCAL SYNLAB CENTRO COMERCIAL VIVA ENVIGADO | J65: SPCI | K65: 2500000 | L65: 44601 | N65: 3137546144 | O65: Juan Camilo Quintero Bedoya | P65: camilo.quintero@spci.com.co
B66: 55 | C66: COTIZACION DE LOS DISEÑOS DE PROTECCIÓN CONTRA INCENDIOS Y SEGURIDAD HUMANA PARA EL PROYECTO TERRAZINO LIVING | J66: TERRAZINO SAS | K66: 22670000 | L66: 44601 | M66: X | N66: 3136214678 | O66: Lina Gonzalez | P66: linagonzalez@terrazino.co
B67: 56 | C67: COTIZACION DEL LEVANTAMIENTO DE EXTINCIÓN DE INCENDIOS - COMFAMA CITY PLAZA | J67: SPCI | K67: 2000000 | L67: 44601 | M67: X | N67: 3137546144 | O67: Juan Camilo Quintero Bedoya | P67: camilo.quintero@spci.com.co
B68: 57 | C68: COTIZACION DEL ANÁLISIS DE SEGURIDAD HUMANA PARA EL PROYECTO LA PURISIMA | J68: ADMIRIS | K68: 500000 | L68: 44602 | N68: 3014188503 | O68: Andrés Velázquez | P68: avelasquez@admirisltda.com
B69: 58 | C69: COTIZACION DEL DISEÑO DE EXTINCIÓN DE INCENDIOS PARA EL PROYECTO PRIMERA ETAPA DEL PROYECTO PALERMO | J69: FONDO INMOBILIARIO COLOMBIA | K69: 24960000 | L69: 44602 | N69: 3003943395 | O69: Manuela Acevedo Callejas | P69: manaceve@bancolombia.com.co
B70: 59 | C70: COTIZACION DEL ANÁLISIS DE SEGURIDAD HUMANA PARA LA PRIMERA ETAPA DEL PROYECTO PALERMO | J70: FONDO INMOBILIARIO COLOMBIA | K70: 6520000 | L70: 44602 | N70: 3003943395 | O70: Manuela Acevedo Callejas | P70: manaceve@bancolombia.com.co
B71: 60 | C71: COTIZACION DEL ANÁLISIS DE SEGURIDAD HUMANA PARA EL PROYECTO CENTRO COMERCIAL GRAN PLAZA SOACHA | J71: CONCONCRETO | K71: 4950000 | L71: 44602 | N71: 3003675022 | O71: Andrés Restrepo Escobar | P71: arestrepoe@conconcreto.com
B72: 61 | C72: COTIZACION DE LOS DISEÑOS DE PROTECCIÓN CONTRA INCENDIOS Y SEGURIDAD HUMANA PARA EL PROYECTO HARAS DE SANTA LUCIA | J72: MENSULA | K72: 11950000 | L72: 44602 | N72: 320 666 1899 | O72: Santiago López González | P72: santiagolopez@mensulaingenieros.com
B73: 62 | C73: COTIZACION REVISIÓN Y PRUEBAS SISTEMAS CONTRA INCENDIOS INSTALADOS Y LA SEGURIDAD HUMANA PARA EL PROYECTO SALUD VEGAS | J73: GERENCIA INTEGRAL | K73: 9850000 | L73: 44603 | M73: X | N73: 57 312 2967935 | O73: Maria Teresa | P73: mlopez@hdgerenciaintegral.com
B74: 63 | C74: COTIZACION DEL DISEÑO DE EXTINCIÓN DE INCENDIOS PARA EL PROYECTO CONSULTORIO EN AMSTERDAN OFTALMOLOGICO | J74: A.L. GAS POR RED & REDES CONTRA INCENDIO S.A.S | K74: 1500000 | L74: 44603 | O74: Alejandro López Gómez
B75: 64 | C75: COTIZACION DE LOS DISEÑOS DE PROTECCIÓN CONTRA INCENDIOS PARA EL PROYECTO CAMPOSOL | J75: SPCI | K75: 19950000 | L75: 44607 | N75: 3003675022 | O75: Ana Maria Restrepo Mayo | P75: ana.restrepo@spci.com.co
B76: 65 | C76: COTIZACION DE LOS DISEÑOS DE PROTECCIÓN CONTRA INCENDIOS Y SEGURIDAD HUMANA PARA EL PROYECTO PARQUE CHIGUÍ | J76: RRP ARQUITECTOS | K76: 6960000 | L76: 44607 | O76: Valeria Haydar Valderrama | P76: valeriahaydar@gmail.com
B77: 66 | C77: COTIZACION DE LOS DISEÑOS DE PROTECCIÓN CONTRA INCENDIOS Y SEGURIDAD HUMANA PARA EL PROYECTO EDIFICIO OLAVE | J77: AGROINDUSTRIALES HIDRÁULICA DIAZ | K77: 17990000 | L77: 44607 | N77: 3183832571 | O77: Daniel Felipe Diaz | P77: dfelipediaz@gmail.com
B78: 67 | C78: COTIZACION DEL DISEÑO DE EXTINCIÓN DE INCENDIOS PARA EL PROYECTO HOTEL GO | J78: Project&Solution | K78: 1250000 | L78: 44609 | O78: Sebastián López Duque
B79: 68 | C79: COTIZACION DE LOS DISEÑOS DE PROTECCIÓN CONTRA INCENDIOS Y SEGURIDAD HUMANA PARA EL PROYECTO MENTE PLENA | J79: LAB.INMOBILIARIO | K79: 16100000 | L79: 44609 | N79: 3135178966 | O79: Maria Paulina Cuca | P79: arquitectura@labinmobiliario.com
B80: 69 | C80: COTIZACION DEL DISEÑO DE EXTINCIÓN DE INCENDIOS PARA EL PROYECTO DISTRITO VERA ETAPA B4 | J80: FONDO INMOBILIARIO COLOMBIA | K80: 17950000 | L80: 44609 | N80: 3003943395 | O80: Manuela Acevedo Callejas | P80: manaceve@bancolombia.com.co
B81: 70 | C81: COTIZACION DE LOS DISEÑOS DE PROTECCIÓN CONTRA INCENDIOS PARA EL PROYECTO VAXTHERA | J81: INTERVE SAS | K81: 29900000 | L81: 44609 | N81: 3004659012 | O81: Interventoría Preoperativa | P81: mferrer@interve.co
B82: 71 | C82: COTIZACION DEL ANÁLISIS DE SEGURIDAD HUMANA PARA EL PROYECTO BALCONES DE RIASCOS | J82: STRATEGO | K82: 3260000 | L82: 44582 | N82: 3116725581 | O82: Daniel Henao Correa | P82: d.henao@stratego.com.co
B83: 72 | C83: COTIZACION DEL ANÁLISIS DE SEGURIDAD HUMANA PARA EL PROYECTO BOSKETO | J83: ADMIRIS | K83: 2800000 | L83: 44614 | N83: 3014188503 | O83: Andrés Velázquez | P83: avelasquez@admirisltda.com
B84: 73 | C84: COTIZACION DEL DISEÑO DE EXTINCIÓN DE INCENDIOS PARA EL PROYECTO VILLAGE | J84: OVIEDO | K84: 2950000 | L84: 44614 | O84: Marcel M Agudelo Ramirez | P84: direccionoperativa@oviedo.com.co
B85: 74 | C85: COTIZACION DEL DISEÑO DE DETECCIÓN DE INCENDIOS PARA EL PROYECTO PLANTA DE ALMACENAMIENTO | J85: SECURETEC | K85: 3950000 | L85: 44615 | N85: 3206678830 | O85: Jhonny Castro | P85: dirproyectos@securetec.com.co
B86: 75 | C86: COTIZACION DE LOS DISEÑOS DE PROTECCIÓN CONTRA INCENDIOS PARA EL PROYECTO PLANTA DE ALMACENAMIENTO | J86: SECURETEC | K86: 9500000 | L86: 44615 | N86: 3206678830 | O86: Jhonny Castro | P86: dirproyectos@securetec.com.co
B87: 76 | C87: COTIZACION DE LOS DISEÑOS DE PROTECCIÓN CONTRA INCENDIOS PARA EL PROYECTO G1 CONNECTA | J87: TELEPERFORMANCE | K87: 11950000 | L87: 44615 | O87: Oscar Hernandez | P87: Oscar.AcunaHernandez@teleperformance.com
B88: 77 | C88: COTIZACION DE LOS DISEÑOS DE PROTECCIÓN CONTRA INCENDIOS PARA EL PROYECTO ESCUELA FERNANDO GONZALEZ DE ENVIGADO | J88: Marcela Jimenez | K88: 3750000 | L88: 44616
B89: 78 | C89: COTIZACION DE LOS DISEÑOS DE PROTECCIÓN CONTRA INCENDIOS PARA EL PROYECTO PORTAL SANTAFE | J89: ESPACIOS DE HOGAR | K89: 2260000 | L89: 44616 | O89: Juan David Giraldo | P89: espaciosdehogar@gmail.com
B90: 79 | C90: COTIZACION DE LOS DISEÑOS DE PROTECCIÓN CONTRA INCENDIOS Y SEGURIDAD HUMANA PARA EL PROYECTO DIAGNOSTICO IPS BOGOTA | J90: Condiseño | K90: 4950000 | L90: 44616 | M90: X | O90: Nakary Garcia Romero | P90: n.garcia@condiseno.co
B91: 80 | C91: COTIZACION DE LOS DISEÑOS DE PROTECCIÓN CONTRA INCENDIOS Y SEGURIDAD HUMANA PARA EL PROYECTO PIENSALO BIEN SAN ANTERO | J91: SPCI | K91: 4890000 | L91: 44616 | M91: X | N91: 310 468 0508 | O91: Juan Pablo Grajales Gómez | P91: juan.grajales@spci.com.co
B92: 81 | C92: COTIZACION DE LOS DISEÑOS DE EXTINCIÓN DE INCENDIOS PARA EL PROYECTO HACEB | J92: SPCI | K92: 49990000 | L92: 44617 | N92: 321 482 61 68 | O92: Ana Maria Restrepo Mayo. | P92: ana.restrepo@spci.com.co
B93: 82 | C93: COTIZACION DE LOS DISEÑOS DE PROTECCIÓN CONTRA INCENDIOS Y SEGURIDAD HUMANA PARA EL PROYECTO INDECAP | J93: BRICK CONSTRUCCION&ARQUITECTURA | K93: 7500000 | L93: 44620 | N93: 322-16-91 | O93: Omar Ivan Garcia Montoya. | P93: ingenieriabrickcya@gmail.com
B94: 83 | C94: COTIZACION DEL DISEÑO DE DETECCIÓN DE INCENDIOS PARA EL PROYECTO IVS SEDE ESPECIALIZADA 4636 | J94: SOCOMES | K94: 680000 | L94: 44628 | O94: David Lopera Medina | P94: david.lopera@socomes.com
B95: 84 | C95: COTIZACION DEL DISEÑO DE EXTINCIÓN DE INCENDIOS PARA EL PROYECTO IVS SEDE ESPECIALIZADA 4636 | J95: SOCOMES | K95: 1250000 | L95: 44628 | O95: David Lopera Medina | P95: david.lopera@socomes.com
B96: 85 | C96: COTIZACION DEL ANÁLISIS DE SEGURIDAD HUMANA PARA EL PROYECTO FORTINET | J96: SS STUDIO SUR | K96: 2950000 | L96: 44622 | N96: 2357612 | O96: LAURA ARIAS ABAD | P96: laura.arias@studiosur.net
B97: 86 | C97: COTIZACION DEL DISEÑO DE EXTINCIÓN DE INCENDIOS PARA EL PROYECTO UNIVERSIDAD LUIS AMIGO | J97: SPCI | K97: No se cotizó | L97: 44628 | N97: 3104165783 | O97: Cristiam Gustavo Mondragón Cortés | P97: cristiam.mondragon@spci.com.co
B98: 87 | C98: COTIZACION DEL ANÁLISIS DE SEGURIDAD HUMANA PARA EL PROYECTO CENTRO DE ACONDICIONAMIENTO | J98: DESUR | K98: 2850000 | L98: 44627 | N98: 4801300 | O98: Simon Mesa Betancur | P98: simon.mesa@desur.gov.co
B99: 88 | C99: COTIZACION DEL DISEÑO DE EXTINCIÓN DE INCENDIOS PARA EL PROYECTO PLANTA DE PINTURAS | J99: SPCI | K99: 12500000 | L99: 44628 | M99: X | N99: 3137546144 | O99: Juan Camilo Quintero Bedoya | P99: camilo.quintero@spci.com.co
B100: 89 | C100: COTIZACION DE LOS DISEÑOS DE PROTECCIÓN CONTRA INCENDIOS - ESTACIÓN DE GAS TIPO VENTILADOR | J100: INGENIERÍA DE RIEGOS | K100: 16250000 | L100: 44627 | O100: Luis Esteban Ramírez
B101: 90 | C101: COTIZACION DEL DISEÑO DE EXTINCIÓN DE INCENDIOS PARA EL PROYECTO LAYOUT CDBQ | J101: INGESED | K101: 19950000 | L101: 44628 | N101: 301 4201614 | O101: Jhon Rodriguez | P101: jrodriguez@ingesed.com
B102: 91 | C102: COTIZACION DEL DISEÑO DE DETECCIÓN DE INCENDIOS PARA EL PROYECTO PLANTA SUMICOL | J102: Sumicol | K102: 9500000 | L102: 44628 | N102: (311) 532 70 51 | O102: Juan Felipe Gil | P102: fgil@corona.com.co
B103: 92 | C103: COTIZACION DEL DISEÑO DE EXTINCIÓN DE INCENDIOS PARA EL PROYECTO PLANTA SUMICOL | J103: Sumicol | K103: 3500000 | L103: 44628 | N103: (311) 532 70 51 | O103: Juan Felipe Gil | P103: fgil@corona.com.co
B104: 93 | C104: COTIZACION DE LOS DISEÑOS DE PROTECCIÓN CONTRA INCENDIOS PARA EL PROYECTO OFICINA | J104: Soluciones Civiles | K104: 2990000 | L104: 44628 | M104: X | N104: 4483960 | O104: Gustavo Aguirre Arcila | P104: gaguirre@solciviles.com
B105: 94 | C105: COTIZACION DE REVISIÓN DE LOS SISTEMAS DE PROTECCIÓN CONTRA INCENDIOS INSTALADOS Y SEGURIDAD HUMANA PARA LA RIVIERE TORRE 3 | J105: CONINSA RAMÓN H | K105: 3500000 | L105: 44628 | M105: X | N105: 300 3501774 | O105: Wilson Sanchez | P105: wilsonsanchez@coninsa.co
B106: 95 | C106: DEBORA ARANGO VARIOS SERVICIOS | J106: LUIS LÓPEZ | K106: Variable | L106: 44628 | N106: 3147743362 | O106: Luis Alberto López | P106: lalopez@utp.edu.co
B107: 96 | C107: COTIZACION DEL ANÁLISIS DE SEGURIDAD HUMANA PARA EL PROYECTO IUE | J107: DESUR | K107: 9900000 | L107: 44628 | M107: X | N107: 4801300 Ext. 128 | O107: Alejandra Cuervo Gómez | P107: alejandra.cuervo@desur.gov.co
B108: 97 | C108: COTIZACION DE LOS DISEÑOS DE PROTECCIÓN CONTRA INCENDIOS Y SEGURIDAD HUMANA PARA EL PROYECTO JUAN PABLO II ETAPA 1B | J108: SÓLIDA VIVIENDA | K108: 7550000 | L108: 44630 | N108: 4487500 ext 4912 | O108: Yaddy Giron Martinez | P108: yaddy.giron@solida.com.co
B109: 98 | C109: COTIZACION DE LOS DISEÑOS DE PROTECCIÓN CONTRA INCENDIOS PARA EL PROYECTO COLEGIO LA SALLE DE ENVIGADO | J109: Sóportica ingenieria & arquitectura | K109: 39950000 | L109: 44630 | N109: 3117997210 | O109: David Guzmán Ortega | P109: david.guzman@soportica.com
...

Sheet 2023
E3: SEGUIMIENTO A COTIZACIONES
B11: Número de cotización | C11: Descripción de la cotización | J11: Cliente | K11: Valor sin IVA | L11: Fecha de cotización | M11: Aprobado | N11: Telefono | O11: Persona Encargada | P11: Correo
B12: 1 | C12: COTIZACION DE LOS DISEÑOS DE PROTECCIÓN CONTRA INCENDIOS - PROYECTO SOLAR | J12: SFIRE | L12: 44929 | N12: 310 8227462 | O12: Alvaro Manosalva | P12: alvaromanosalva@sfiregroup.com
B13: 2 | C13: COTIZACION DEL DISEÑO DE DETECCIÓN DE INCENDIOS - LA ESTRELLA | J13: GINO MONTOYA | K13: 5500000 | L13: 44930 | N13: 3044003430 | O13: Gino Montoya | P13: gino1037@hotmail.com
B14: 3 | C14: COTIZACION DEL DISEÑO DE DETECCIÓN DE INCENDIOS - LA MAYORISTA | J14: GINO MONTOYA | K14: 2500000 | L14: 44930 | N14: 3044003430 | O14: Gino Montoya | P14: gino1037@hotmail.com
B15: 4 | C15: COTIZACION DEL DISEÑO DE EXTINCIÓN DE INCENDIOS - MODELACIÓN Y CÁLCULOS LA CAUSA PF | J15: MAURICIO SEPULVEDA | K15: 500000 | L15: 44930 | N15: 301 2547727 | O15: Mauricio Sepulveda | P15: obrasms84@gmail.com
B16: 5 | C16: COTIZACION DE LOS DISEÑOS DE PROTECCIÓN CONTRA INCENDIOS Y SEGURIDAD HUMANA PARA EL PROYECTO LIBERTAD DE LA FORTUNA | J16: CONSTRUGEN | K16: 9910000 | L16: 44938 | N16: 3044830834 | O16: Jhonatan Aguirre Pulgarin | P16: jhonatan.aguirre@construgen.com
B17: 6 | C17: COTIZACION DE LOS DISEÑOS DE PROTECCIÓN CONTRA INCENDIOS - HOSPITAL REGIONAL DE DUITAMA | J17: HOSPITAL REGIONAL DE DUITAMA | K17: 29970000 | L17: 44942 | N17: 3133195098 | O17: Luis Orlando Cepeda Zarate | P17: mantenimiento@hrd.gov.co
B18: 7 | C18: COTIZACION DEL DISEÑO DE DETECCIÓN DE INCENDIOS - BODEGA LEBRIJA | J18: SPCI | K18: 6270000 | L18: 44942 | M18: X | N18: 310 3939739 | O18: Victor Saldarriaga | P18: victor.saldarriaga@spci.com.co
B19: 8 | C19: COTIZACION DEL DISEÑO DE EXTINCIÓN DE INCENDIOS - ÁREAS SIN PROTECCIÓN BODEGA LEBRIJA | J19: SPCI | K19: 5890000 | L19: 44942 | M19: X | N19: 310 3939739 | O19: Victor Saldarriaga | P19: victor.saldarriaga@spci.com.co
B20: 9 | C20: COTIZACION DE LOS DISEÑOS DE SEGURIDAD HUMANA Y PROTECCIÓN CONTRA INCENDIOS - OFICINAS ANDERCOL | J20: INGENIO BIM | K20: 5070000 | L20: 44942 | M20: X | N20: 301 2311524 | O20: Luisa Londoño | P20: luisa.londono@ingeniobim.co
B21: 10 | C21: COTIZACION DE LOS DISEÑOS DE PROTECCIÓN CONTRA INCENDIOS PARA EL PROYECTO JUAN VALDÉZ C.C VIVA BARRANQUILLA | J21: SPCI | K21: 2250000 | L21: 44945 | N21: 3214826168 | O21: Ana Maria Restrepo Mayo | P21: ana.restrepo@spci.com.co
B22: 11 | C22: COTIZACION DEL DISEÑO DE DETECCIÓN DE INCENDIOS PARA EL PROYECTO HOTEL AYACUCHO | J22: SOCOMES | K22: 2990000 | L22: 44945 | N22: 3137851941 | O22: David Lopera Medina | P22: david.lopera@socomes.com
B23: 12 | C23: COTIZACION DEL DISEÑO DE EXTINCIÓN DE INCENDIOS PARA EL PROYECTO HOTEL AYACUCHO | J23: SOCOMES | K23: 6270000 | L23: 44945 | N23: 3137851941 | O23: David Lopera Medina | P23: david.lopera@socomes.com
B24: 13 | C24: COTIZACION DE LOS DISEÑOS DE SEGURIDAD HUMANA Y PROTECCIÓN CONTRA INCENDIOS - PROYECTO ALLEGRO | J24: CENTRO SUR | K24: 7470000 | L24: 44944 | M24: X | N24: 4480648 | O24: Daniel Pernett Patiño | P24: danielpernett@centrosur.co
B25: 14 | C25: COTIZACION DE LOS DISEÑOS DE PROTECCIÓN CONTRA INCENDIOS PARA EL PROYECTO EDIFICIO LA 33 | J25: CONSTRUCTORA MANZANARES | K25: 7900000 | L25: 44946 | N25: 312 8667618 | O25: Álvaro Pérez | P25: apb2573@yahoo.es
B26: 15 | C26: COTIZACION DEL ANÁLISIS DE SEGURIDAD HUMANA PARA EL PROYECTO JAC DEL OASIS | J26: DESUR | K26: 2500000 | L26: 44946 | N26: 4801300 Ext. 130 | O26: Valentina Chacon | P26: valentina.chacon@desur.gov.co
B27: 16 | C27: COTIZACION DE LOS DISEÑOS DE PROTECCIÓN CONTRA INCENDIOS Y SEGURIDAD HUMANA PARA EL PROYECTO CIUDAD DEL RIO | J27: 4RQ STUDIO | K27: 31520000 | L27: 44953 | N27: 3128882282 | O27: Katherine Lopez Ramirez | P27: equipo@4rqstudio.com
B28: 17 | C28: COTIZACION DEL DISEÑO DE EXTINCIÓN DE INCENDIOS - PROYECTO VIVACE TORRE 2 | J28: SPCI | K28: 3600000 | L28: 44949 | M28: X | N28: 310 420 3649 | O28: Mauricio Guzmán Urrea | P28: mauricio.guzman@spci.com.co
B29: 17 | C29: COTIZACION DE LOS DISEÑOS DE PROTECCIÓN CONTRA INCENDIOS Y SEGURIDAD HUMANA PARA EL PROYECTO EDIFICIO NUEVO COLEGIO THE COLUMBUS SCHOOL | J29: Colegio The Columbus School | K29: 3450000 | L29: 44950 | M29: X | N29: 312 2886611 | O29: Paula Andrea Duque | P29: pduque@columbus.edu.co
B30: 18 | C30: COTIZACION DE LOS DISEÑOS DE PROTECCIÓN CONTRA INCENDIOS PARA EL PROYECTO HOSPITALIZACION TPH SEDE 80 | J30: AUNA | K30: 1950000 | L30: 44951 | M30: X | N30: 57 60 4 342 10 10 | O30: Cristian David Cano | P30: cristian.cano@lasamericas.com.co
B31: 19 | C31: COTIZACION DE LOS DISEÑOS DE PROTECCIÓN CONTRA INCENDIOS PARA EL PROYECTO LOCAL CONSULTORIO ODONTOLOGICO C.C VIVA SINCELEJO | J31: SPCI | K31: 2510000 | L31: 44952 | N31: 3214826168 | O31: Ana Maria Restrepo Mayo | P31: licitaciones@spci.com.co
B32: 20 | C32: COTIZACION DE LOS DISEÑOS DE PROTECCIÓN CONTRA INCENDIOS PARA EL PROYECTO CALLE 7 A | J32: PARADIGMA ARQUITECTURA | K32: 23650000 | L32: 44952 | O32: Juliana Cardona | P32: paradigmaarquitecturasas@gmail.com
B33: 21 | C33: COTIZACION DE LOS DISEÑOS DE PROTECCIÓN CONTRA INCENDIOS Y SEGURIDAD HUMANA PARA EL PROYECTO CALLE 7A | J33: SECURETEC | K33: 23650000 | L33: 44952 | O33: Harold Camacho | P33: gerencia@securetec.com.co
B34: 22 | C34: COTIZACION PLANOS DE SEGURIDAD HUMANA - PROYECTO FRAGUA | J34: CONTEX | K34: 2350000 | L34: 44952 | M34: X | N34: 317 3789177 | O34: Elisa Pantoja | P34: epantoja@contex.com.co
B35: 23 | C35: COTIZACION DEL DISEÑO DE EXTINCIÓN DE INCENDIOS PARA EL PROYECTO GENERSOL | J35: SFIRE | K35: 12550000 | L35: 44953 | N35: 3108227462 | O35: ALVARO MANOSALVA | P35: alvaromanosalva@sfiregroup.com
B36: 24 | C36: COTIZACION DE LOS DISEÑOS DE PROTECCIÓN CONTRA INCENDIOS PARA EL PROYECTO BANCOLOMBIA UNICENTRO | J36: CONDISEÑO | L36: 44953 | N36: 3175594091 | O36: Nakary García Romero | P36: n.garcia@condiseno.co
B37: 25 | C37: COTIZACION DEL ANÁLISIS DE SEGURIDAD HUMANA PARA EL PROYECTO OFICINAS | J37: STUDIO SUR | K37: 3550000 | L37: 44953 | M37: X | P37: liliana.gutierrez@studiosur.net -laura.arias@studiosur.net
B38: 26 | C38: COTIZACION DEL DIAGNÓSTICO DE LOS SISTEMAS DE PROTECCIÓN CONTRA INCENDIOS - CLÍNICA IMBANACO CALI | J38: IMBANACO | K38: 14300000 | L38: 44957 | N38: 3205535416 | O38: Camilo Andrés Chávez Sandoval | P38: Camilo.Chavez@quironsalud.com
B39: 27 | C39: COTIZACION DE LOS DISEÑOS DE PROTECCIÓN CONTRA INCENDIOS PARA EL PROYECTO PORCI CARNES | J39: SPCI | K39: 6900000 | L39: 44957 | N39: 310 4165783 | O39: Cristiam Gustavo Mondragon Cortes | P39: cristiam.mondragon@spci.com.co
B40: 28 | C40: COTIZACION DE LOS DISEÑOS DE PROTECCIÓN CONTRA INCENDIOS PARA EL PROYECTO BODEGA 23 REPOTENCIACION SCI | J40: SPCI | K40: 39950000 | L40: 44957 | N40: 310 4165783 | O40: Cristiam Gustavo Mondragon Cortes | P40: cristiam.mondragon@spci.com.co
B41: 29 | C41: COTIZACION DEL ANÁLISIS DE SEGURIDAD HUMANA PARA EL PROYECTO REASENTAMIENTO GRAMALOTE FASE 1 EN COLOMBIA | J41: CONCONCRETO | K41: 3950000 | L41: 44957 | M41: X | O41: Sara Restrepo
B42: 30 | C42: COTIZACION DEL ANÁLISIS DE SEGURIDAD HUMANA PARA EL PROYECTO TULIO OSPINA | J42: Kevin Batista | K42: 13540000 | L42: 44957 | N42: 3023105548 | O42: Kevin Batista | P42: kevin15batista@gmail.com
B43: 31 | C43: COTIZACION DEL DISEÑO SOPORTES SISMORRESISTENTE RESERVA DEL PARQUE | J43: SPCI | K43: 690000 | L43: 44958 | N43: 3146920966 | O43: Daniel Uribe | P43: daniel.uribe@spci.com.co
B44: 32 | C44: COTIZACION DE LOS DISEÑOS DE PROTECCIÓN CONTRA INCENDIOS Y SEGURIDAD HUMANA PARA EL PROYECTO COLEGIO JOSE MARIA MANYANET | J44: Aguas Ingeniería Medellín | K44: 11790000 | L44: 44959 | N44: 3015743970-3192090844-3226861576 | O44: Andrés Ardila Duque | P44: aguasingenieriamed@gmail.com
B45: 33 | C45: COTIZACION DE LOS DISEÑOS DE PROTECCIÓN CONTRA INCENDIOS Y SEGURIDAD HUMANA PARA EL PROYECTO CLINICA KRA 49B | J45: VIVA 1A IPS | K45: 10970000 | L45: 44959 | N45: 3156648484 | O45: Juan Alberto Fontalvo Polo | P45: jfontalvo@viva1a.com.co
B46: 34
B47: 35 | C47: COTIZACION DE LOS DISEÑOS DE PROTECCIÓN CONTRA INCENDIOS Y SEGURIDAD HUMANA PARA EL PROYECTO CAFETERIA ELEMENTAL | J47: Colegio The Columbus School | K47: 7450000 | L47: 44959 | M47: X | N47: 312 2886611 | O47: Paula Andrea Duque | P47: pduque@columbus.edu.co
B48: 36 | C48: COTIZACION DE LOS DISEÑOS DE PROTECCIÓN CONTRA INCENDIOS Y SEGURIDAD HUMANA PARA EL PROYECTO VERMONTE MODIFICACION PISO 1 | J48: Con-axion S.A.S. | K48: 7450000 | L48: 44959 | M48: X | N48: (4) 440 9310 | O48: JORGE O. TORO MONTES | P48: jtoro@con-axion.com
B49: 37 | C49: COTIZACION DEL ANÁLISIS DE SEGURIDAD HUMANA PARA EL PROYECTO LOS CAMBULOS | J49: Constructora Guasandi s.a.s | K49: 4500000 | L49: 44960 | N49: 323 5893023 y/o (604)5609600 ext.104. | O49: Angélica Patiño | P49: diseno@constructoradeobras.com
B50: 38 | C50: COTIZACION DE LOS DISEÑOS DE PROTECCIÓN CONTRA INCENDIOS Y SEGURIDAD HUMANA PARA EL PROYECTO SINCELEJO | J50: FCR | K50: 14450000 | L50: 44960 | O50: Oscar Andres Alvarez
B51: 39 | C51: COTIZACION DE LOS DISEÑOS DE PROTECCIÓN CONTRA INCENDIOS PARA EL PROYECTO COLCHONES EL DORADO | J51: SPCI | K51: 19980000 | L51: 44960 | N51: 3146920966 | O51: Daniel Uribe Sierra | P51: daniel.uribe@spci.com.co
B52: 40 | C52: COTIZACION DE LOS DISEÑOS DE PROTECCIÓN CONTRA INCENDIOS Y SEGURIDAD HUMANA PARA EL PROYECTO LA SALLE | J52: Coninsa | K52: 23990000 | L52: 44960 | N52: 300 754 96 49 | O52: Zully Milena López Molina | P52: zmlopez@coninsa.co
B53: 41 | C53: COTIZACION DEL DISEÑO DE EXTINCIÓN DE INCENDIOS - MODELACIÓN Y CÁLCULOS CONSULTORIO CALI | J53: MAURICIO SEPULVEDA | K53: 630000 | L53: 44961 | N53: 301 2547727 | O53: Mauricio Sepulveda | P53: obrasms84@gmail.com
B54: 42 | C54: COTIZACION DE LOS DISEÑOS DE PROTECCIÓN CONTRA INCENDIOS Y SEGURIDAD HUMANA PARA EL PROYECTO CENTRAL DE SERVICIOS LA CEJA | J54: SOCOMES | K54: 13790000 | L54: 44964 | N54: 3137851941 | O54: DAVID LOPERA MEDINA | P54: david.lopera@socomes.com
B55: 43 | C55: COTIZACION DE LOS DISEÑOS DE PROTECCIÓN CONTRA INCENDIOS PARA EL PROYECTO PCH VENTANA | J55: SPCI | K55: 9970000 | L55: 44964 | N55: 310 4165783 | O55: Cristiam Gustavo Mondragon Cortes | P55: cristiam.mondragon@spci.com.co
B56: 44 | C56: COTIZACION DEL DISEÑO DE DETECCIÓN DE INCENDIOS - PORTAL DEL ORO | J56: GINO MONTOYA | K56: 1950000 | L56: 44964 | N56: 3044003430 | O56: Gino Montoya | P56: gino1037@hotmail.com
B57: 45 | C57: COTIZACIÓN DE LA MODELACIÓN Y CÁLCULOS DE LA RED GENERAL Y CONEXIONES DE MANGUERA PARA EL PROYECTO GIRASOLES | J57: SPCI | K57: 950000 | L57: 44965 | N57: 314 6082856 | O57: Bayron Eliecer Puerta | P57: bayron.puerta@spci.com.co
B58: 46 | C58: COTIZACION DE LOS DISEÑOS DE PROTECCIÓN CONTRA INCENDIOS Y SEGURIDAD HUMANA PARA EL PROYECTO BANCOLOMBIA SOLEDAD | J58: SANTIAGO ROJAS | K58: 5890000 | L58: 44965 | N58: 3022806727 | O58: Manuela Arboleda Pajoy | P58: sraic.diseno@gmail.com
B59: 47 | C59: COTIZACION DEL DISEÑO DE EXTINCIÓN DE INCENDIOS - VORTEX MINIPACK | J59: SFIRE | K59: 7550000 | L59: 44965 | N59: 3108227462 | O59: ALVARO MANOSALVA | P59: alvaromanosalva@sfiregroup.com
B60: 48 | C60: COTIZACION DE LA REVISIÓN DE LOS DISEÑOS DE EXTINCIÓN DE INCENDIOS - MINIPACK | J60: SFIRE | K60: 6950000 | L60: 44965 | N60: 3108227462 | O60: ALVARO MANOSALVA | P60: alvaromanosalva@sfiregroup.com
B61: 49 | C61: COTIZACION DEL DISEÑO DE EXTINCIÓN DE INCENDIOS - RANSA YUMBO | J61: SPCI | K61: 19950000 | L61: 44966 | N61: 310 468 0508 | O61: Juan Pablo Grajales Gómez | P61: juan.grajales@spci.com.co
B62: 50 | C62: spc | J62: RRP ARQUITECTOS | K62: 5640000 | L62: 44966 | N62: 311 6101334 | O62: Sebastián Rojas
B63: 51 | C63: COTIZACION DE LOS DISEÑOS DE SEGURIDAD HUMANA Y EXTINCIÓN DE INCENDIOS - ACUARELA DEL RIO TORRE 2 | J63: SPCI | K63: 6960000 | L63: 44967 | M63: X | N63: 310 420 3649 | O63: Mauricio Guzmán Urrea | P63: mauricio.guzman@spci.com.co
B64: 52 | C64: COTIZACION DEL DISEÑO DE EXTINCIÓN DE INCENDIOS PARA EL PROYECTO FERROFELEJES | J64: Ferroflejes | K64: 12550000 | L64: 44970 | O64: Mauricio Gaviria | P64: maurogavi@une.net.co
B65: 53 | C65: COTIZACION DEL ANÁLISIS DE SEGURIDAD HUMANA PARA EL PROYECTO RIO 53 AGUACATALA | J65: MACCA Desarrollo Inmobiliario | K65: 4350000 | L65: 44970 | M65: X | O65: Jorge Ivan Molano Bedoya | P65: jorgemolano@macca.com.co
B66: 54 | C66: COTIZACION DEL DISEÑO DE DETECCIÓN DE INCENDIOS PARA EL PROYECTO TEATRO METROPOLITANO JOSE GUTIERREZ GOMEZ | J66: SECURETEC | K66: 5650000 | L66: 44970 | O66: Julian David Cmacho Galvis | P66: ascomercial2@securetec.com.co
B67: 55 | C67: COTIZACION DE LOS DISEÑOS DE SEGURIDAD HUMANA Y PROTECCIÓN CONTRA INCENDIOS - PROYECTO BESIDE | J67: SOCOMES | K67: 1660000 | L67: 44970 | N67: 3137851941 | O67: DAVID LOPERA MEDINA | P67: david.lopera@socomes.com
B68: 56 | C68: COTIZACION DEL REDISEÑO DE EXTINCIÓN DE INCENDIOS - KUO | J68: CONTEX | K68: 5000000 | L68: 44970 | M68: X | N68: 3104145629 | O68: Matria Camila Velásquez | P68: mcvelasquez@contex.com.co
B69: 57 | C69: COTIZACION DE LOS DISEÑOS DE PROTECCIÓN CONTRA INCENDIOS - ACUEDUCTO DE BOGOTÁ | J69: SPCI | K69: 19940000 | L69: 44970 | N69: 310 468 0508 | O69: Juan Pablo Grajales Gómez | P69: juan.grajales@spci.com.co
B70: 58 | C70: COTIZACION DEL ANÁLISIS DE SEGURIDAD HUMANA PARA EL PROYECTO OFICINAS GOOGLE BOGOTA | J70: SSTUDIO SUR | K70: 3150000 | L70: 44970 | M70: X | N70: 315 3046377 | O70: Laura Arias Abad | P70: laura.arias@studiosur.net
B71: 59 | C71: COTIZACION DE LOS DISEÑOS DE PROTECCIÓN CONTRA INCENDIOS Y SEGURIDAD HUMANA PARA EL PROYECTO LOTE CAROLICA PEREIRA | J71: SERIINCO | K71: 28220000 | L71: 44972 | N71: 311 3391008 | O71: Carlos Henao | P71: carlos.henao@seriinco.com
B72: 60 | C72: COTIZACION DEL DISEÑO DE EXTINCIÓN DE INCENDIOS PARA EL PROYECTO POLÍGONO 120 | J72: SOHINCO | K72: 9950000 | L72: 44972 | N72: 304 5430256 | O72: Maritza Muñoz | P72: maritzam@sohinco.com
B73: 61 | C73: COTIZACION DE LOS DISEÑOS DE PROTECCIÓN CONTRA INCENDIOS PARA EL PROYECTO EDIFICIO BIENESTAR OPERARIOS COMIDISIMOS | J73: SECURETEC | K73: 8700000 | L73: 44972 | N73: 3206678830 | O73: Jhonny Castro | P73: dirproyectos@securetec.com.co
B74: 62 | C74: COTIZACION DE LOS DISEÑOS DE PROTECCIÓN CONTRA INCENDIOS PARA EL PROYECTO LOCAL 158A CC VIVA VILLAVICENCIO | J74: SPCI | K74: 2510000 | L74: 44973 | N74: 310 4165783 | O74: Cristiam Gustavo Mondragon Cortes | P74: cristiam.mondragon@spci.com.co
B75: 63 | C75: COTIZACION DE LOS DISEÑOS DE PROTECCIÓN CONTRA INCENDIOS Y SEGURIDAD HUMANA PARA EL PROYECTO VIVIENDA LAKE PALMS | J75: IA&C | K75: 19550000 | L75: 44973 | N75: 312 6536246 | O75: Jorge Andres Rojas Cadavid | P75: jorgerojas@iayc.co
B76: 64 | C76: COTIZACION DEL DISEÑO DE DETECCIÓN DE INCENDIOS PARA EL PROYECTO WOW GALERIA ÉXITO VIVA ENVIGADO | J76: SPCI | K76: 630000 | L76: 44973 | M76: X | N76: 3214826168 | O76: Ana Maria Restrepo Mayo | P76: ana.restrepo@spci.com.co
B77: 65 | C77: COTIZACION DE LOS DISEÑOS DE PROTECCIÓN CONTRA INCENDIOS PARA EL PROYECTO PCH VENTANA | J77: Comex Internacional | K77: 19940000 | L77: 44973 | N77: 316 4962026 | O77: Juan David Ossa. | P77: comercial@comexinternacional.com.co
B78: 66 | C78: COTIZACION DEL DISEÑO DE EXTINCIÓN DE INCENDIOS PARA EL PROYECTO COLEGIO COLOMBUS SCHOOL COORDENAS 2019 | J78: Colegio The Columbus School | K78: 7550000 | L78: 44973 | N78: 312 2886611 | O78: Paula Andrea Duque | P78: pduque@columbus.edu.co
B79: 67 | C79: COTIZACION DEL DISEÑO DE EXTINCIÓN DE INCENDIOS PARA EL PROYECTO TORRE DE CONSULTORIOS | J79: INTERVÉ | K79: 1950000 | L79: 44974 | M79: X | N79: 310 386 17 63 | O79: Dario Antonio Saldarriaga | P79: dsaldarriaga@interve.co
B80: 68 | C80: COTIZACION DE LOS DISEÑOS DE PROTECCIÓN CONTRA INCENDIOS Y SEGURIDAD HUMANA PARA EL PROYECTO LIBERTADA DE LA FORTUNA | J80: JOMARK | K80: 10200000 | L80: 44974 | N80: 324 2594697 | O80: Laura Duque betancur | P80: proyectos2@jomarkseguridad.com
B81: 69 | C81: COTIZACION DE LOS DISEÑOS DE PROTECCIÓN CONTRA INCENDIOS Y SEGURIDAD HUMANA PARA EL PROYECTO POLITECNICO GRAN COLOMBIANO | J81: CONDISEÑO | K81: 19950000 | L81: 44974 | N81: 3175594091 | O81: Nakary Garcia Romero | P81: n.garcia@condiseno.co
B82: 70 | C82: COTIZACION DE LOS DISEÑOS DE PROTECCIÓN CONTRA INCENDIOS PARA EL PROYECTO VILLAS DEL CARMEN | J82: HIDRAULICA Y MONTAJES | K82: 7530000 | L82: 44978 | N82: 313 731 01 01 | O82: Evelin Rojas | P82: hidraulicaymontajes@gmail.com
B83: 71 | C83: COTIZACION DEL ANÁLISIS DE SEGURIDAD HUMANA PARA EL PROYECTO LOS CAMBULOS | J83: SOCOMES | K83: 4500000 | L83: 44974 | N83: 313 7851941 | O83: DAVID LOPERA MEDINA | P83: david.lopera@socomes.com
B84: 72 | C84: COTIZACION DE LOS DISEÑOS DE PROTECCIÓN CONTRA INCENDIOS Y SEGURIDAD HUMANA PARA EL PROYECTO POLÍGONO 120 | J84: SOHINCO | K84: 16250000 | L84: 44974 | M84: X | N84: 304 5430256 | O84: Maritza Muñoz | P84: maritzam@sohinco.com
B85: 73 | C85: COTIZACION DE LOS DISEÑOS DE PROTECCIÓN CONTRA INCENDIOS Y SEGURIDAD HUMANA PARA EL PROYECTO MIC GUARNE | J85: SOHINCO | K85: 19950000 | L85: 44974 | N85: 304 5430256 | O85: Maritza Muñoz | P85: maritzam@sohinco.com
B86: 74 | C86: COTIZACION DEL ANÁLISIS DE SEGURIDAD HUMANA PARA EL PROYECTO LABORATORIO COLSANITAS | J86: CONDISEÑO | K86: 4640000 | L86: 44977 | N86: 3175594091 | O86: Nakary Garcia Romero | P86: n.garcia@condiseno.co
B87: 75 | C87: COTIZACION DEL ANÁLISIS DE SEGURIDAD HUMANA PARA EL PROYECTO PUERTO AZUL | J87: CONCONCRETO | K87: 3150000 | L87: 44977 | N87: 3003404902 | O87: Pilar Arango Restrepo | P87: parangor@conconcreto.com
B88: 76 | C88: COTIZACION DEL ANÁLISIS DE SEGURIDAD HUMANA PARA EL PROYECTO PARQUEADEROS VIERZO LIVINGS | J88: CONINTEL SA | K88: 1950000 | L88: 44977 | M88: X | N88: 316 6226809 | O88: Laura Gaviria | P88: posventasconintel@gmail.com
B89: 77 | C89: COTIZACION DEL DISEÑO DE EXTINCIÓN DE INCENDIOS PARA EL PROYECTO OFICINAS | J89: John Velez | K89: 1250000 | L89: 44977 | N89: 313 652 51 94 | O89: John Vélez | P89: johnvelezconsultorias@gmail.com
B90: 78 | C90: COTIZACION DE LOS DISEÑOS DE PROTECCIÓN CONTRA INCENDIOS PARA EL PROYECTO SECRETARIA DE MOVILIDAD DE ENVIGADO | J90: GINO MONTOYA | K90: 7500000 | L90: 44980 | N90: 3044003430 | O90: Gino Montoya | P90: gino1037@hotmail.com
B91: 79 | C91: COTIZACION DEL DISEÑO DE EXTINCIÓN DE INCENDIOS PARA EL PROYECTO TANQUES GLP | J91: ByR Ingeniería | K91: Variable | L91: 44981 | N91: 3136603779 | O91: Edwin Alberto Ortiz | P91: eortiz@byr.com.co
B92: 80 | C92: COTIZACION DEL DISEÑO DE DETECCIÓN DE INCENDIOS PARA EL PROYECTO GUAYACANES | J92: SPCI | K92: 3950000 | L92: 44984 | N92: 3146082856 | O92: Bayron Elicer Puerta Toro | P92: bayron.puerta@spci.com.co
B93: 81 | C93: COTIZACION DE LOS DISEÑOS DE PROTECCIÓN CONTRA INCENDIOS PARA EL PROYECTO PROYECTO INDUSTRIAL | J93: COINSI | K93: 24950000 | L93: 44984 | N93: 3126658022 | O93: Sergio Rodriguez | P93: diseno4@gyd.com.co
B94: 82 | C94: COTIZACION DE LOS DISEÑOS DE PROTECCIÓN CONTRA INCENDIOS Y SEGURIDAD HUMANA PARA EL PROYECTO CEDI IBAGUE | J94: SPCI | K94: 23830000 | L94: 44984 | N94: 3104680508 | O94: Juan Pablo Grajales Gomez | P94: juan.grajales@spci.com.co
B95: 83 | C95: COTIZACION DEL DISEÑO DE EXTINCIÓN DE INCENDIOS PARA EL PROYECTO CUARTO COV VIVA ENVIGADO | J95: SPCI | K95: 1650000 | L95: 44986 | N95: 313 693 88 55 | O95: David Velez Valencia | P95: david.velez@spci.com.co
B96: 84 | C96: COTIZACION DEL DISEÑO DE EXTINCIÓN DE INCENDIOS PARA EL PROYECTO GUAYACANES | J96: SPCI | K96: 8780000 | L96: 44984 | N96: 3146082856 | O96: Bayron Elicer Puerta Toro | P96: bayron.puerta@spci.com.co
B97: 85 | C97: COTIZACION DEL DISEÑO DE DETECCIÓN DE INCENDIOS PARA EL PROYECTO PEPSICO AREA ADMINISTRATIVO | J97: SERIINCO | K97: 3950000 | L97: 44984 | N97: 311 3391008 | O97: Carlos Henao | P97: carlos.henao@seriinco.com
B98: 86 | C98: COTIZACION DEL DISEÑO DE DETECCIÓN DE INCENDIOS PARA EL PROYECTO PEPSICO PLANTA ORIENTE | J98: SERIINCO | K98: 2950000 | L98: 44984 | N98: 311 3391008 | O98: Carlos Henao | P98: carlos.henao@seriinco.com
B99: 87 | C99: COTIZACION DE LOS DISEÑOS DE PROTECCIÓN CONTRA INCENDIOS Y SEGURIDAD HUMANA PARA EL PROYECTO ACTION LIVING | J99: MACCA Desarrollo Inmobiliario | K99: 19950000 | L99: 44984 | M99: X | N99: 3154558533 | O99: Jorge Ivan Molano Bedoya | P99: jorgemolano@macca.com.co
B100: 88 | C100: COTIZACION DE LOS DISEÑOS DE PROTECCIÓN CONTRA INCENDIOS Y SEGURIDAD HUMANA PARA EL PROYECTO SAN JORGE COMERCIO | J100: Vertice | K100: 32270000 | L100: 44992 | N100: (604) 4486800 Ext. 138 | O100: Esteban Ramirez | P100: e.ramirez@verticeing.com
B101: 89 | C101: COTIZACION DE LOS DISEÑOS DE PROTECCIÓN CONTRA INCENDIOS PARA EL PROYECTO LOCALES RESERVA PLAZA | J101: SPCI | K101: 2000000 | L101: 44986 | N101: 310 4165783 | O101: Cristiam Gustavo Mondragon Cortes | P101: cristiam.mondragon@spci.com.co
B102: 90 | C102: COTIZACION DE LOS DISEÑOS DE PROTECCIÓN CONTRA INCENDIOS PARA EL PROYECTO CHAK FOODTECH | J102: SPCI | K102: 2000000 | L102: 44986 | M102: X | N102: 310 4165783 | O102: Cristiam Gustavo Mondragon Cortes | P102: cristiam.mondragon@spci.com.co
B103: 91 | C103: COTIZACION DE LOS DISEÑOS DE PROTECCIÓN CONTRA INCENDIOS Y SEGURIDAD HUMANA PARA EL PROYECTO HOTEL CLICK CLACK | J103: CONEXO | K103: 27950000 | L103: 44988 | N103: 3005861916 | O103: John Jairo Jaramillo Ochoa | P103: jjaramillo@conexoinmobiliario.com
B104: 92 | C104: COTIZACION DE LOS DISEÑOS DE PROTECCIÓN CONTRA INCENDIOS Y SEGURIDAD HUMANA PARA EL PROYECTO ALLEGRO CARTAGO | J104: Mensula | K104: 9950000 | L104: 44988 | N104: 3207091752 | O104: Cristian Londoño | P104: cristianlondono@mensulaingenieros.com
B105: 93 | C105: COTIZACION DE LOS DISEÑOS DE PROTECCIÓN CONTRA INCENDIOS Y SEGURIDAD HUMANA PARA EL PROYECTO CLINICA MEDICADIZ | J105: CONDISEÑO | K105: 13920000 | L105: 44991 | N105: 3175594091 | O105: Nakary Garcia Romero | P105: n.garcia@condiseno.co
B106: 94 | C106: COTIZACION DE LOS DISEÑOS DE PROTECCIÓN CONTRA INCENDIOS PARA EL PROYECTO BODEGA 924 SK BOGOTA | J106: SERIINCO | K106: 21950000 | L106: 44994 | N106: 3113391008 | O106: Carlos Henao | P106: carlos.henao@seriinco.com
B107: 95 | C107: COTIZACION DEL DISEÑO DE DETECCIÓN DE INCENDIOS PARA EL PROYECTO CONDOMINIO HOUZEZ | J107: ESPIRAL | K107: 1250000 | L107: 44991 | M107: X | N107: 3176461961 | O107: Jorge Escobar | P107: jorge.escobar@espiral.com.co
B108: 96 | C108: COTIZACION DEL DISEÑO DE EXTINCIÓN DE INCENDIOS PARA EL PROYECTO PABELLONES BLANCO Y AZUL DE PLAZA MAYOR MEDELLIN | J108: SECURETEC | K108: 16950000 | L108: 44991 | O108: Julio Zapata
B109: 97 | C109: COTIZACION DE LOS DISEÑOS DE SEGURIDAD HUMANA Y PROTECCIÓN CONTRA INCENDIOS - MOTEL MARINILLA | J109: JUAN CAMILO CARDONA | K109: 7530000 | L109: 44991 | N109: 311 3693748 | O109: Juan Camilo Cardona | P109: jcardonm@gmail.com
...

Sheet 2024
E3: SEGUIMIENTO A COTIZACIONES
B11: Número de cotización | C11: Descripción de la cotización | J11: Cliente | K11: Valor sin IVA | L11: Fecha de cotización | M11: Aprobado | N11: Telefono | O11: Persona Encargada | P11: Correo
B12: 1
B13: 2 | C13: COTIZACION DE LOS DISEÑOS DE PROTECCIÓN CONTRA INCENDIOS Y SEGURIDAD HUMANA PARA EL PROYECTO ENTRE AIRES | J13: INSERCO | K13: 34950000 | L13: 45303 | N13: 3104131109 | O13: Leandro Herrera Gutierrez | P13: directorlean@inserco.com.co
B14: 3 | C14: COTIZACION DEL DISEÑO DE EXTINCIÓN DE INCENDIOS - SERVICENTRO EL CAMPESTRE | J14: K&J INGENIEROS S.A.S | K14: 6950000 | L14: 45303 | O14: Karla Rendón | P14: krendon@kyjingenieros.co
B15: 4 | C15: COTIZACION DE LOS DISEÑOS DE SEGURIDAD HUMANA Y PROTECCIÓN CONTRA INCENDIOS - LICEO FRANCES EXISTENTE | J15: LICEO FRANCES | K15: 11950000 | L15: 45303 | O15: Andrés Ramírez | P15: administrativo2@lf.edu.co
B16: 5 | C16: COTIZACION DEL ANÁLISIS DE SEGURIDAD HUMANA PARA EL PROYECTO NUEVA SEDE DE LA TORRE ESE HOSPITAL SAN VICENTE | J16: Consorcio HSVA | K16: 4250000 | L16: 45303 | N16: 3164313039 | O16: CARLOS ORJUELA | P16: caleorca26@gmail.com
B17: 6 | C17: COTIZACION DE LOS DISEÑOS DE PROTECCIÓN CONTRA INCENDIOS PARA EL PROYECTO OFICINA 11-01 DEL CCI | J17: SPCI | K17: 2830000 | L17: 45308 | N17: 3104165783 | O17: Cristiam Gustavo Mondragon | P17: dir.tecnico@spci.com.co
B18: 7 | C18: COTIZACION DEL REDISEÑO DE EXTINCIÓN DE INCENDIOS PARA EL PROYECTO ARAGUA | J18: SPCI | K18: 1000000 | L18: 45308 | N18: 3104165783 | O18: Cristiam Gustavo Mondragon | P18: dir.tecnico@spci.com.co
B19: 8 | C19: COTIZACION DEL DISEÑO DE DETECCIÓN DE INCENDIOS PARA EL PROYECTO PLANTA ZEUUS GIRARDOTA | J19: SERIINCO | K19: 7950000 | L19: 45306 | N19: 3113391008 | O19: Carlos Henao | P19: carlos.henao@seriinco.com
B20: 9 | C20: COTIZACION DE LOS DISEÑOS DE PROTECCIÓN CONTRA INCENDIOS Y SEGURIDAD HUMANA PARA EL PROYECTO HOTEL HAVEN | J20: Mensula | K20: 11950000 | L20: 45306 | N20: 311 6751810 | O20: Valentina Ortega Morales | P20: valentinaortega@mensulaingenieros.com
B21: 10 | C21: COTIZACION DE LOS DISEÑOS DE PROTECCIÓN CONTRA INCENDIOS PARA EL PROYECTO BELIVE | J21: COMEX INTERNACIONAL SAS | K21: 14950000 | L21: 45307 | N21: 316 496 20 26 | O21: Juan David Ossa Salazar | P21: comercial@comexinternacional.com.co
B22: 11 | C22: COTIZACION DEL ANÁLISIS DE SEGURIDAD HUMANA PARA EL PROYECTO PLANTA SIKA RIONEGRO | J22: JOMARK | K22: 7950000 | L22: 45308 | N22: 3194913179 | O22: Carlos Almanya Patiño | P22: calmanya@jomarkseguridad.com
B23: 12 | C23: COTIZACIÓN REDISEÑO DE EXTINCIÓN DE INCENDIOS PARA EL PROYECTO OFICINAS LEBRIJA PISO 2 MEZANINE | J23: SPCI | K23: 2950000 | L23: 45308 | N23: 3229057647 | O23: José Luis Ojeda Caarvajal | P23: jose.ojeda@spci.com.co
B24: 13 | C24: COTIZACION DE LA INGENIERÍA CONCEPTUAL DE PROTECCIÓN CONTRA INCENDIOS PARA EL PROYECTO - PLANTA DE ACEITE | J24: INGESED | K24: 9950000 | L24: 45310 | N24: 313 540 17 14 | O24: Eliana Isabel Cardona Ríos | P24: comercial@ingesed.com
B25: 14 | C25: COTIZACION DE LOS DISEÑOS DE SEGURIDAD HUMANA Y PROTECCIÓN CONTRA INCENDIOS - RESERVA CENTRAL | J25: GO INGENIERÍA Y SOLUCIONES | K25: 19940000 | L25: 45309 | N25: 310 5104288 | O25: Cristian Gañan
B26: 15 | C26: COTIZACION DE LOS DISEÑOS DE SEGURIDAD HUMANA Y PROTECCIÓN CONTRA INCENDIOS - 380 M2 CLÍNICA NOEL | J26: GO INGENIERÍA Y SOLUCIONES | K26: 4760000 | L26: 45309 | N26: 310 5104288 | O26: Cristian Gañan
B27: 16 | C27: COTIZACIÓN DE LA MODELACIÓN DE LA RED GENERAL DE EXTINCIÓN DE INCENDIOS PARA EL PROYECTO | J27: SOCOMES | K27: 2500000 | L27: 45309 | N27: 3137851941 | O27: David Lopera medina | P27: david.lopera@socomes.com
B28: 17 | C28: COTIZACION DE LOS DISEÑOS DE PROTECCIÓN CONTRA INCENDIOS Y SEGURIDAD HUMANA PARA EL PROYECTO ARMENIA | J28: CONTEX | K28: 19950000 | L28: 45313 | N28: 3104145629 | O28: Maria Camila Velásquez | P28: mcvelasquez@contex.com.co
B29: 18 | C29: COTIZACIÓN DE LA ASESORIA EN SALIDA DE EMERGENCIA PARA PRIMER PISO DE EDUARDO BOTERO SOTO S.A. | J29: EDUARDO BOTERO SOTO S.A. | K29: 1880000 | L29: 45313 | N29: 3113507944 | O29: Milena Echeverri
B30: 19 | C30: COTIZACION DE LOS DISEÑOS DE PROTECCIÓN CONTRA INCENDIOS Y SEGURIDAD HUMANA PARA EL PROYECTO INCODOL MEDICAL TOWER | J30: SOLUCIONES INMOBILIARIAS | K30: 7530000 | L30: 45314 | N30: 3182079204 | O30: Deyner Jimenez | P30: residente3@solucionesinmobiliariassas.com
B31: 20 | C31: COTIZACION DE LOS DISEÑOS DE PROTECCIÓN CONTRA INCENDIOS Y SEGURIDAD HUMANA PARA EL PROYECTO NEUROMEDICA MEDICAL TOWER | J31: SOLUCIONES INMOBILIARIAS | K31: 14430000 | L31: 45314 | N31: 3182079204 | O31: Deyner Jimenez | P31: residente3@solucionesinmobiliariassas.com
B32: 21 | C32: COTIZACION DE LOS DISEÑOS DE PROTECCIÓN CONTRA INCENDIOS PARA EL PROYECTO ARL SURA VIVA ENVIGADO | J32: Ingenieria y Montajes | K32: 6250000 | L32: 45314 | N32: 3175179593 | O32: Diego Alejandro Correa Bedoya | P32: dacorrea@rcimontajes.co
B33: 22 | C33: COTIZACION DE REVISIÓN DE LOS DISEÑOS DE PROTECCIÓN CONTRA INCENDIO Y SEGURIDAD HUMANA - PTAR ESCOBERO | J33: SPCI | K33: 3150000 | L33: 45315 | N33: 310 468 0508 | O33: Juan Pablo Grajales Gómez | P33: juan.grajales@spci.com.co
B34: 23 | C34: COTIZACION DEL ANÁLISIS DE SEGURIDAD HUMANA PARA EL PROYECTO TORRE DE LA ALIANZA | J34: SOLUCIONES INMOBILIARIAS | K34: 2750000 | L34: 45315 | N34: 3006731128 | O34: Laura Olano | P34: gcia.torresalianza@solucionesinmobiliariassas.com
B35: 24 | C35: COTIZACION DE LA REVISIÓN DE SEGURIDAD HUMANA Y LOS SISTEMAS DE PROTECCIÓN CONTRA INCENDIOS PARA CLÍNICA EN SINCELEJO | J35: CONDISEÑO | K35: 6500000 | L35: 45316 | N35: 3175594091 | O35: Nakary Garcia Romero | P35: n.garcia@condiseno.co
B36: 25 | C36: COTIZACION DE LOS DISEÑOS DE PROTECCIÓN CONTRA INCENDIOS Y SEGURIDAD HUMANA PARA EL PROYECTO USHUAYA | J36: EDYFYCA | K36: 26350000 | L36: 45317 | N36: 3104057513 | O36: Claudia Ramirez | P36: claudia.ramirez@edyfica.co
B37: 26 | C37: COTIZACION DE LOS DISEÑOS DE EXTINCIÓN DE INCENDIOS Y SEGURIDAD HUMANA PARA EL PROYECTO IE RIO GRANDE | J37: Londoño Gomez | K37: 5650000 | L37: 45317 | N37: 3111770 ext 177 | O37: Juan Diego Echeverri | P37: jecheverri@londonogomez.com
B38: 27 | C38: COTIZACION DEL DISEÑO DE EXTINCIÓN DE INCENDIOS PARA EL PROYECTO CLINICA LLANO GRANDE | J38: ML ARQUITECTURA | K38: 1450000 | L38: 45317 | O38: Melissa Lopez Torres | P38: melissalopez@mltarq.com
B39: 28 | C39: COTIZACION DEL DISEÑO DE DETECCIÓN DE INCENDIOS PARA EL PROYECTO PARQUE EMPRESARIAL ELITE II | J39: RCI Ingenieria y Montajes | K39: 4950000 | L39: 45317 | N39: 3175179593 | O39: Diego Alejandro Correa Bedoya | P39: dacorrea@rcimontajes.co
B40: 29 | C40: COTIZACION DE LOS DISEÑOS DE PROTECCIÓN CONTRA INCENDIOS Y SEGURIDAD HUMANA PARA EL PROYECTO CENTRO COMERCIAL X ORIENTE | J40: Arquitectura y Concreto | K40: 59950000 | L40: 45317 | N40: 3127218621 | O40: ROBINSON MARULANDA GUARIN | P40: robinsonmarulanda@arquitecturayconcreto.com
B41: 30 | C41: COTIZACION DEL DISEÑO DE EXTINCIÓN DE INCENDIOS PARA EL PROYECTO LOCALES MEDIPIEL DMODA | J41: SPCI | K41: 7170000 | L41: 45318 | N41: 3137546144 | O41: Juan Camilo Quintero Bedoya | P41: camilo.quintero@spci.com.co
B42: 31 | C42: COTIZACION DEL ANÁLISIS DE SEGURIDAD HUMANA PARA EL PROYECTO PLANTA BIOCLORO | J42: CONCONCRETO | K42: 8500000 | L42: 45320 | N42: 3003404902 | O42: Pilar Arango Restrepo | P42: parangor@conconcreto.com
B43: 32 | C43: COTIZACION DE LOS DISEÑOS DE PROTECCIÓN CONTRA INCENDIOS Y SEGURIDAD HUMANA PARA EL PROYECTO OBRA PREESCOLAR COLEGIO BENEDICTINOS | J43: Tamayo Ingenieros | K43: 6250000 | L43: 45320 | N43: 3137687548 | O43: Herbin Cartagena Montoya
B44: 33 | C44: COTIZACION DEL DISEÑO DE EXTINCIÓN DE INCENDIOS PARA EL PROYECTO PISO 19 CENTRO COMERCIAL LOS MOLINOS | J44: I+ CONSTRUCTORA | K44: 4350000 | L44: 45321 | N44: (604) 4443091 | O44: Lina Maria Montoya Gonzalez | P44: lmontoya@iconstructora.com.co
B45: 34 | C45: COTIZACIÓN DE LA ELABORACIÓN DIGITAL DE LAS PLACAS HIDRÁULICAS PARA JARDINES DE LLANOGRANDE | J45: SPCI | K45: 750000 | L45: 45321 | N45: 3137546144 | O45: Juan Camilo Quintero Bedoya | P45: camilo.quintero@spci.com.co
B46: 35 | C46: COTIZACION DEL DISEÑO DE DETECCIÓN DE INCENDIOS PARA EL PROYECTO PLANTA ZEUUS GIRARDOTA | J46: SERIINCO | K46: 6950000 | L46: 45323 | N46: 3113391008 | O46: Carlos Henao | P46: carlos.henao@seriinco.com
B47: 36 | C47: COTIZACION DE LOS DISEÑOS DE PROTECCIÓN CONTRA INCENDIOS PARA EL PROYECTO SUBESTACIONES EPM | J47: COINSI | K47: 214500000 | L47: 45324 | N47: 3117208541 | O47: Sergio Rodriguez | P47: diseno4@gyd.com.co
B48: 37 | C48: COTIZACION DE LOS DISEÑOS DE PROTECCIÓN CONTRA INCENDIOS Y SEGURIDAD HUMANA PARA EL PROYECTO CENTRO DE SALUD BARRIO GALÁN | J48: Pedro Quiros | K48: 7520000 | L48: 45324 | N48: 3123770102 | O48: Pedro Quiros | P48: pequibo1@gmail.com
B49: 38 | C49: COTIZACION DE LOS DISEÑOS DE PROTECCIÓN CONTRA INCENDIOS PARA EL PROYECTO BANDAS TRANSPORTADORAS | J49: JM Ingenieria | K49: 56500000 | L49: 45324 | O49: Joam Moreno | P49: gerencia@jmingenieriatotal.com.co
B50: 39 | C50: COTIZACION DE LOS DISEÑOS DE PROTECCIÓN CONTRA INCENDIOS PARA EL PROYECTO SMURFIT KAPPA YUMBO | J50: SERIINCO | K50: 58500000 | L50: 45324 | N50: 3113391008 | O50: Carlos Henao | P50: carlos.henao@seriinco.com
B51: 40 | C51: COTIZACION DE LOS DISEÑOS DE PROTECCIÓN CONTRA INCENDIOS Y SEGURIDAD HUMANA PARA EL PROYECTO TORRE FÁTIMA | J51: COMEX INTERNACIONAL SAS | K51: 21850000 | L51: 45324 | N51: 316 496 20 26 | O51: Juan David Ossa Salazar | P51: comercial@comexinternacional.com.co
B52: 41 | C52: COTIZACION DE LOS DISEÑOS DE SEGURIDAD HUMANA Y PROTECCIÓN CONTRA INCENDIOS - BODEGA INDUSTRIAL LOTE 24 Y 26 | J52: SPCI | K52: 27380000 | L52: 45324 | N52: 310 468 0508 | O52: Juan Pablo Grajales Gómez | P52: juan.grajales@spci.com.co
B53: 42 | C53: COTIZACION DE LOS DISEÑOS DE SEGURIDAD HUMANA Y PROTECCIÓN CONTRA INCENDIOS - AOSTA | J53: Htres | K53: 5990000 | L53: 45325 | O53: Nathaly Barrera Palacio | P53: Nathalybarrerapalacio@gmail.com
B54: 43 | C54: COTIZACION DEL RE-DISEÑOS DE SEGURIDAD HUMANA Y PROTECCIÓN CONTRA INCENDIOS PARA PISO 2 TRRAZO | J54: PERFEK | K54: 2970000 | L54: 45325 | N54: 3007701428 | O54: Johana Montoya Zapata | P54: johana.montoya@perfek.com.co
B55: 44 | C55: COTIZACION DEL DISEÑO DE SOPORTERÍA SISMORESISTENTE PARA RISERS - JOHNSON & JOHNSON CALI | J55: JOHNSON & JOHNSON | K55: 7150000 | L55: 45324 | N55: 3187346703 | O55: Jorge Edward Lopez | P55: jlopezv3@kenvue.com
B56: 45 | C56: COTIZACION DE LOS DISEÑOS DE PROTECCIÓN CONTRA INCENDIOS Y SEGURIDAD HUMANA PARA EL PROYECTO VERMONTE | J56: CONAXION | K56: 6350000 | L56: 45327 | N56: (4) 440 9310 | O56: Jorge O. Toro Montes
B57: 46 | C57: COTIZACION DEL ANÁLISIS DE SEGURIDAD HUMANA PARA EL PROYECTO ALMARENA-COSTA RICA | J57: CONCONCRETO | K57: 4950000 | L57: 45328 | N57: 313 610 68 56 | O57: Javier Andres Herrera Uribe | P57: jherrerau@conconcreto.com
B58: 47 | C58: COTIZACION DEL DISEÑO DE DETECCIÓN DE INCENDIOS PARA EL PROYECTO CLINICA DEL ROSARIO | J58: CLINICA DEL ROSARIO | K58: 25000000 | L58: 45328 | N58: 300 4610230 | O58: Juan David Velez Herrera | P58: proyectos@clinicaelrosario.com
B59: 48 | C59: COTIZACION DEL DISEÑO DE EXTINCIÓN DE INCENDIOS PARA EL PROYECTO CLINICA DEL ROSARIO | J59: CLINICA DEL ROSARIO | K59: 8000000 | L59: 45328 | N59: 300 4610230 | O59: Juan David Velez Herrera | P59: proyectos@clinicaelrosario.com
B60: 49 | C60: COTIZACION DEL DIAGNOSTICO RED CONTRA INCENDIOS Y SISTEMA ELECTRICO - INSTITUTO HUMBOLT | J60: INSTITUTO HUMBOLT | K60: 16350000 | L60: 45328 | N60: 3202767 | O60: Lorena Alejandra Valencia Cruz
B61: 50 | C61: COTIZACION DEL DISEÑO DE EXTINCIÓN DE INCENDIOS PARA EL PROYECTO SYM BELT SMURFIT KAPPA | J61: SERIINCO | K61: 7990000 | L61: 45330 | N61: 3113391008 | O61: Carlos Henao | P61: carlos.henao@seriinco.com
B62: 51 | C62: COTIZACION DE LOS DISEÑOS DE PROTECCIÓN CONTRA INCENDIOS PARA EL PROYECTO CLINICA SAN FRANCISCO TULUA | J62: SOLUCIONES INMOBILIARIAS | K62: 3550000 | L62: 45330 | N62: 312 7760909 | O62: Simon Lopera
B63: 52 | C63: COTIZACION DEL DISEÑO DE DETECCIÓN DE INCENDIOS PARA EL PROYECTO PLANTA CROMATEX | J63: Cromatex | K63: 6270000 | L63: 45330 | N63: 315 5334100 | O63: Wendy Oviedo | P63: gestionhumana@cromatex.com.co
B64: 53 | C64: COTIZACION DEL DISEÑO DE DETECCIÓN DE INCENDIOS PARA EL PROYECTO FAMILIA PLANTA MEDELLIN | J64: SERIINCO | K64: 14950000 | L64: 45330 | N64: 3113391008 | O64: Carlos Enrique Henao Londoño | P64: carlos.henao@seriinco.com
B65: 54 | C65: COTIZACIÓN DE LA ELABORACIÓN DIGITAL DE LAS PLACAS HIDRÁULICAS PARA ALGUNOS SISTEMAS DE PLAZA FABRICATO | J65: SPCI | K65: 500000 | L65: 45330 | N65: 3137546144 | O65: Juan Camilo Quintero Bedoya | P65: camilo.quintero@spci.com.co
B66: 55 | C66: COTIZACION DEL INGENIERÍA CONCEPTUAL DE PROTECCIÓN CONTRA INCENDIOS PARA EL PROYECTO PROQUIDENT | J66: SERIINCO | K66: 7500000 | L66: 45330 | N66: 3113391008 | O66: Carlos Henao | P66: carlos.henao@seriinco.com
B67: 56 | C67: COTIZACION DE LOS DISEÑOS DE PROTECCIÓN CONTRA INCENDIOS Y SEGURIDAD HUMANA PARA EL PROYECTO EL NIAGARA | J67: PROJECT& SOLUTIONS | K67: 7520000 | L67: 45334 | N67: 311 3079477 | O67: Sebastian Lopez Duque | P67: gerencia@projectsolutions.com.co
B68: 57 | C68: COTIZACION DE LOS DISEÑOS DE PROTECCIÓN CONTRA INCENDIOS Y SEGURIDAD HUMANA PARA EL PROYECTO MALL BELLOCENTRO | J68: INGESED | K68: 13550000 | L68: 45334 | N68: 313 540 17 14 | O68: Eliana Isabel Cardona Ríos | P68: comercial@ingesed.com
B69: 58 | C69: COTIZACION DE LOS DISEÑOS DE PROTECCIÓN CONTRA INCENDIOS Y SEGURIDAD HUMANA PARA EL PROYECTO PABELLON H2O | J69: INGESED | K69: 12920000 | L69: 45334 | N69: 313 540 17 14 | O69: Eliana Isabel Cardona Ríos | P69: comercial@ingesed.com
B70: 59 | C70: COTIZACION DE LOS DISEÑOS DE PROTECCIÓN CONTRA INCENDIOS Y SEGURIDAD HUMANA PARA EL PROYECTO PARIS CAMPESTRE-ZONA COMERCIAL | J70: AIA | K70: 5930000 | L70: 45334 | N70: 3007582159 | O70: Maria Paula Nieto | P70: mnieto@aia.com.co
B71: 60 | C71: COTIZACION DE LOS DISEÑOS DE PROTECCIÓN CONTRA INCENDIOS Y SEGURIDAD HUMANA PARA EL PROYECTO EDIFICIO SAN LUCAS | J71: Asesorías Balbin | K71: 15650000 | L71: 45334 | N71: 3127463275 | O71: Santiago Cardona Balbin | P71: Santiago Cardona Balbin
B72: 61 | C72: COTIZACION DE LOS DISEÑOS DE PROTECCIÓN CONTRA INCENDIOS Y SEGURIDAD HUMANA PARA EL PROYECTO BLOQUE DE AULAS SEDE CAMPESTRE | J72: INGENIOBIM | K72: 19990000 | L72: 45334 | N72: 3014170260 | O72: Jenifer Vanessa Orozco Ordoñez | P72: jenifer.orozco@ingeniobim.co
B73: 62 | C73: COTIZACION DE LOS DISEÑOS DE PROTECCIÓN CONTRA INCENDIOS PARA EL PROYECTO CRUZ ROJA LOCAL 2 AEROPUERTO EL DORADO | J73: Arkec Soluciones y Proyectos | K73: 2310000 | L73: 45335 | N73: 3004531110 | O73: Juan Pablo Garzón R | P73: proyectos8.arkec@gmail.com
B74: 63 | C74: COTIZACION DE LOS DISEÑOS DE PROTECCIÓN CONTRA INCENDIOS PARA EL PROYECTO LOCAL CLINICA CARDIO VID | J74: Clinica Cardio VID | K74: 5550000 | L74: 45335 | N74: 3227090 Ext. 4399 | O74: Jaime Armando Osorio Giraldo | P74: josorio@vid.org.co
B75: 64 | C75: COTIZACION DE LOS DISEÑOS DE PROTECCIÓN CONTRA INCENDIOS Y SEGURIDAD HUMANA PARA CAFETERÍA Y OFICINAS ESCUELA EARLY YEAR | J75: THE COLUMBUS SCHOOL | K75: 9410000 | L75: 45335 | O75: Puala Duque | P75: pduque@columbus.edu.co
B76: 65 | C76: COTIZACION DEL DISEÑO DE EXTINCIÓN DE INCENDIOS PARA EL PROYECTO CUBIERTA VIVA FONTIBÓN | J76: SPCI | K76: 2850000 | L76: 45336 | N76: 3104680508 | O76: Juan Pablo Grajales Gomez | P76: juan.grajales@spci.com.co
B77: 66 | C77: COTIZACION DEL DISEÑO DE EXTINCIÓN DE INCENDIOS PARA EL PROYECTO EDIFICIO LOS CAMBULOS | J77: Ingeaguas | K77: 4640000 | L77: 45336 | N77: 311 7468517 | O77: Weimar Gonzales
B78: 67 | C78: COTIZACION DE LOS DISEÑOS DE PROTECCIÓN CONTRA INCENDIOS PARA EL PROYECTO COMFAMA COPACABANA | J78: SPCI | K78: 8970000 | L78: 45336 | N78: 3137546144 | O78: Juan Camilo Quintero | P78: camilo.quintero@spci.com.co
B79: 68 | C79: COTIZACION DE LOS DISEÑOS DE PROTECCIÓN CONTRA INCENDIOS PARA EL PROYECTO AVOPAK | J79: SPCI | K79: 4760000 | L79: 45336 | N79: 3104165783 | O79: Cristiam Gustavo Mondragon | P79: dir.tecnico@spci.com.co
B80: 69 | C80: COTIZACION DEL DISEÑO DE DETECCIÓN DE INCENDIOS PARA EL PROYECTO CUERPO DE BOMBEROS SABANETA | J80: SERIINCO | K80: 2510000 | L80: 45338 | N80: 3113391008 | O80: Carlos Enrique Henao Londoño | P80: carlos.henao@seriinco.com
B81: 70 | C81: COTIZACIÓN DE LA REVISIÓN DE DISEÑOS DE PROTECCIÓN CONTRA INCENIDOS PARA EL PROYECTO PUERTO ANTIOQUIA | J81: SERIINCO | K81: 12400000 | L81: 45337 | N81: 3113391008 | O81: Carlos Enrique Henao Londoño | P81: carlos.henao@seriinco.com
B82: 71 | C82: COTIZACION DE LOS DISEÑOS DE PROTECCIÓN CONTRA INCENDIOS Y SEGURIDAD HUMANA PARA EL PROYECTO TEATRO APARTADÓ COMFAMA | J82: Connatural | K82: 19950000 | L82: 45337 | N82: 3218527044 | O82: Edgar Mazo | P82: <teatroapartado@gmail.com
B83: 72 | C83: COTIZACION DE LOS DISEÑOS DE PROTECCIÓN CONTRA INCENDIOS PARA EL PROYECTO MUSEO DE LA MEMORIA | J83: Securetec | K83: 9950000 | L83: 45337 | N83: 3014111727 | O83: Julian David Camacho | P83: ascomercial2@securetec.com.co
B84: 73 | C84: COTIZACION DE LOS DISEÑOS DE PROTECCIÓN CONTRA INCENDIOS PARA EL PROYECTO PLANTA DE BALANCEADO | J84: SERIINCO | K84: 29970000 | L84: 45338 | N84: 3113391008 | O84: Carlos Enrique Henao Londoño | P84: carlos.henao@seriinco.com
B85: 74 | C85: COTIZACION DE LOS DISEÑOS DE PROTECCIÓN CONTRA INCENDIOS Y SEGURIDAD HUMANA PARA EL PROYECTO LOTE COLTABACO-OFICINAS | J85: A&C | K85: 15950000 | L85: 45338 | N85: 3123618 | O85: Germán E. Martínez Arboleda | P85: germanmartinez@arquitecturayconcreto.com
B86: 75 | C86: COTIZACION DE LOS DISEÑOS DE SEGURIDAD HUMANA Y PROTECCIÓN CONTRA INCENDIOS - PROYECTO USHUAYA- REV B | J86: Edyfica | K86: 25160000 | L86: 45338 | N86: 310 4057513 | O86: Claudia Ramirez | P86: claudia.ramirez@edyfica.co
B87: 76 | C87: COTIZACION DEL DISEÑO DE DETECCIÓN DE INCENDIOS PARA EL PROYECTO LEVI’S PLANTA NIVEL 1 Y NIVEL 2 - EXPOFARO | J87: Detectar Systems | K87: 4950000 | L87: 45341 | N87: 301 5421412 | O87: Juan Santiago Londoño Quiceno | P87: detectarsystems@gmail.com
B88: 77 | C88: COTIZACION DE LOS DISEÑOS DE PROTECCIÓN CONTRA INCENDIOS PARA EL PROYECTO LA JAULA DEL ÁNGEL | J88: SPCI | K88: 3300000 | L88: 45342 | O88: Juan Camilo Quintero Bedoya | P88: camilo.quintero@spci.com.co
B89: 78 | C89: COTIZACIÓN CONSULTORÍA HORA INGENIERÍA PROTECCIÓN CONTRA INCENDIOS | J89: INMA | K89: 250000 | L89: 45342 | N89: 57 310 4485610 | O89: Nora Berrio | P89: NBerrio@ingenierosmecanicos.com.co
B90: 79 | C90: COTIZACION DE LOS DISEÑOS DE PROTECCIÓN CONTRA INCENDIOS Y SEGURIDAD HUMANA PARA EL PROYECTO EDIFICIO ADMINISTRATIVO Y APOYO | J90: Pao Arquitectura | K90: 9950000 | L90: 45342 | O90: Paola López | P90: paolopez@paoarq.com
B91: 80 | C91: COTIZACION DEL ANÁLISIS DE SEGURIDAD HUMANA PARA EL PROYECTO INSTITUTO METEREOLÓGICO | J91: CONCONCRETO | K91: 6960000 | L91: 45343 | N91: 313 610 68 56 | O91: Javier Andres Herrera Uribe | P91: jherrerau@conconcreto.com
B92: 81 | C92: COTIZACION DE LOS DISEÑOS DE PROTECCIÓN CONTRA INCENDIOS PARA EL PROYECTO PLAZA DE MERCADO SANTUARIO | J92: GO INGENIERIAYSOLUCIONES | K92: 19940000 | L92: 45343 | N92: 310 5104288 | O92: Christian Gañan Ibarra | P92: goingenieriaysoluciones@gmail.com
B93: 82 | C93: COTIZACION DE LOS DISEÑOS DE PROTECCIÓN CONTRA INCENDIOS Y SEGURIDAD HUMANA PARA EL PROYECTO HARAS DE SANTA LUCIA | J93: MENSULA | K93: 18950000 | L93: 44613 | N93: 320 666 1899 | O93: Santiago López González | P93: santiagolopez@mensulaingenieros.com
B94: 83 | C94: COTIZACION DEL DISEÑO DE DETECCIÓN DE INCENDIOS PARA EL PROYECTO EDIFICIO ADMINISTRATIVO COLEGIO COLOMBO BRITANICO | J94: SPCI | K94: 2510000 | L94: 45343 | N94: 3137546144 | O94: Juan Camilo Quintero Bedoya | P94: camilo.quintero@spci.com.co
B95: 84 | C95: COTIZACION DE LOS DISEÑOS DE PROTECCIÓN CONTRA INCENDIOS Y SEGURIDAD HUMANA PARA EL PROYECTO EDIFICIO ESQUINA DEL HUECO | J95: Clara Inés López | K95: 9900000 | L95: 45344 | N95: 300 6194323 | O95: Ines Lopez de Mesa | P95: obraesquinadelhueco@gmail.com
B96: 85 | C96: COTIZACIÓN REDISEÑO EXTINCIÓN DE INCENDIOS HUMAX | J96: INMA | K96: 15000000 | L96: 45344 | N96: 57 310 4485610 | O96: Nora Berrio | P96: NBerrio@ingenierosmecanicos.com.co
B97: 86 | C97: COTIZACION DEL ANÁLISIS DE SEGURIDAD HUMANA PARA EL PROYECTO PLANTA DE AGUA BENDITA | J97: Agua Bendita | K97: 4950000 | L97: 45348 | O97: Yesica Sanchez Giraldo
B98: 87 | C98: COTIZACION DEL DISEÑO DE EXTINCIÓN DE INCENDIOS PARA EL PROYECTO BIO26 | J98: SPCI | K98: 6880000 | L98: 45348 | N98: 3137546144 | O98: Juan Camilo Quintero Bedoya | P98: camilo.quintero@spci.com.co
B99: 88 | C99: COTIZACION DEL DISEÑO DE EXTINCIÓN DE INCENDIOS PARA EL PROYECTO VIVA SINCELEJO | J99: SPCI | K99: 3250000 | L99: 45348 | N99: 3137546144 | O99: Juan Camilo Quintero Bedoya | P99: camilo.quintero@spci.com.co
B100: 89 | C100: COTIZACION DE LOS DISEÑOS DE PROTECCIÓN CONTRA INCENDIOS Y SEGURIDAD HUMANA PARA EL PROYECTO CQ2 | J100: INGESED | K100: 11950000 | L100: 45348 | N100: 313 540 17 14 | O100: Eliana Isabel Cardona Ríos | P100: comercial@ingesed.com
B101: 90 | C101: COTIZACION DEL DISEÑO DE EXTINCIÓN DE INCENDIOS PARA EL PROYECTO EDIFICIO FOREVER | J101: FIRE MARSHAL | K101: 3500000 | L101: 45344 | N101: 3163564491 | O101: Cristian Eduardo Ortega Ipuchima | P101: cristianortega@firemarshal.com.co
B102: 91 | C102: COTIZACION DE LOS DISEÑOS DE PROTECCIÓN CONTRA INCENDIOS Y SEGURIDAD HUMANA PARA EL PROYECTO BELLO ANDALUCIA | J102: Socomes | K102: 15980000 | L102: 45350 | N102: 3137851941 | O102: David Lopera medina | P102: david.lopera@socomes.com
B103: 92 | C103: COTIZACION DE LOS DISEÑOS DE PROTECCIÓN CONTRA INCENDIOS - EXTRACTORA VERDE PLANTA AVATAR | J103: INGESED | K103: =25000000*1.3 -> 32500000 | L103: 45348 | N103: 313 540 17 14 | O103: Eliana Isabel Cardona Ríos | P103: comercial@ingesed.com
B104: 93 | C104: COTIZACION DEL DISEÑO DE EXTINCIÓN DE INCENDIOS PARA EL PROYECTO PLANTA INDUSTRIAS FAACA COLOMBIA | J104: SPCI | K104: 6960000 | L104: 45348 | N104: 3104165783 | O104: Cristiam Gustavo Mondragon | P104: dir.tecnico@spci.com.co
B105: 94 | C105: COTIZACION DE LOS DISEÑOS DE PROTECCIÓN CONTRA INCENDIOS Y SEGURIDAD HUMANA PARA EL PROYECTO CQ2 | J105: Miguel Ángel Zuluaga | K105: 11950000 | L105: 45348 | N105: 3122492717 | O105: Miguel Ángel Zuluaga | P105: mzuluaga1996@gmail.com
B106: 95 | C106: COTIZACION DE LA ACTUALIZACION DEL SISTEMA DE ROCIADORES PARA EL PROYECTO PLANTA YUMBO SKC | J106: SERIINCO | K106: 9970000 | L106: 45348 | N106: 3113391008 | O106: Carlos Enrique Henao Londoño | P106: carlos.henao@seriinco.com
B107: 96 | C107: COTIZACION DE LOS DISEÑOS DE PROTECCIÓN CONTRA INCENDIOS Y SEGURIDAD HUMANA PARA EL PROYECTO TOLEDANA | J107: Soluciones Civiles | K107: Variable | L107: 45350 | N107: 301 4317086 | O107: Tamara Puerta | P107: fcrtamarapuerta@gmail.com
B108: 97 | C108: COTIZACION DEL DISEÑO DE DETECCIÓN DE INCENDIOS PARA EL PROYECTO SERVIESPRESS LA CEJA ANTIOQUIA | J108: SPCI | K108: 700000 | L108: 45351 | N108: 3137546144 | O108: Juan Camilo Quintero Bedoya | P108: camilo.quintero@spci.com.co
B109: 98 | C109: COTIZACION DE LOS DISEÑOS DE PROTECCIÓN CONTRA INCENDIOS PARA EL PROYECTO PLANTA MOLINOS SAN MIGUEL | J109: SERIINCO | K109: 21320000 | L109: 45350 | N109: 3113391008 | O109: Carlos Enrique Henao Londoño | P109: carlos.henao@seriinco.com
...

Sheet 2025
D2: SEGUIMIENTO A COTIZACIONES - 2025
B10: Número de cotización | C10: Descripción de la cotización | I10: Cliente | J10: Valor sin IVA | K10: Fecha de cotización | L10: Aprobado | M10: Telefono | N10: Persona Encargada | O10: Correo
B11: 1 | C11: COTIZACION DEL ANÁLISIS DE SEGURIDAD HUMANA - MALL LA KONDINA | I11: Raíz Constructora | J11: 4950000 | K11: 45666 | M11: 3113555383 | N11: Daniel Fernando Hernandez | O11: coordinadorobra@gruporaiz.com.co
B12: 2 | C12: COTIZACION DEL ANÁLISIS DE SEGURIDAD HUMANA - ALTA KONDINA | I12: Raíz Constructora | J12: 7550000 | K12: 45666 | M12: 3113555383 | N12: Daniel Fernando Hernandez | O12: coordinadorobra@gruporaiz.com.co
B13: 3 | C13: COTIZACION DE LOS DISEÑOS DE PROTECCIÓN CONTRA INCENDIOS - VILLA CAMPESTRE | I13: Fire y Equipos | J13: 15950000 | K13: 45670 | M13: 3134451063 | N13: Juan Jose Monsalve | O13: dir.proyectos@goodgroup.com.co
B14: 4 | C14: COTIZACION DE LOS DISEÑOS DE SEGURIDAD HUMANA Y PROTECCIÓN CONTRA INCENDIOS - OLMO | I14: Vértice | J14: 26590000 | K14: 45671 | M14: 3216438520 | N14: Luz Aleidy Cuartas Pérez | O14: dcv@altosdelaabadia.com
B15: 5 | C15: COTIZACION DE LOS DISEÑOS DE SEGURIDAD HUMANA Y DETECCIÓN DE INCENDIOS - VIEW POINT ETAPA 2 | I15: Coninsa | J15: 10960000 | K15: 45671 | M15: 3155264386 | N15: Yuliana Tamayo Zapata | O15: ytamayo@coninsa.co
B16: 6 | C16: COTIZACION DE LOS DISEÑOS DE SEGURIDAD HUMANA Y PROTECCIÓN CONTRA INCENDIOS - ACC Y ADS PAILITAS | I16: SRAIC | J16: Variable | K16: 45671 | M16: 3022295772 | N16: Aurora Rios | O16: proyectos@santiagorojas.com.co
B17: 7 | C17: CRISTIAM NO PASÓ A TIEMPO LA INFORMACIÓN Y NO SE PUDO COTIZAR EL PROYECTO | I17: SPCI | J17: NO SE COTIZÓ | K17: 45671 | M17: 3104165783 | N17: Cristiam Gustavo Mondragon | O17: dir.tecnico@spci.com.co
B18: 8 | C18: COTIZACION DEL DISEÑO DE DETECCIÓN DE INCENDIOS - DETECCIÓN ZONA GLP | I18: SPCI | J18: 2500000 | K18: 45671 | M18: 3104203649 | N18: Mauricio Guzman | O18: mauricio.guzman@spci.com.co
B19: 9 | C19: COTIZACION DE LOS DISEÑOS DE PROTECCIÓN CONTRA INCENDIOS - PLAZA DE MERCADO ANDES | I19: Socomes | J19: 13170000 | K19: 45671 | M19: 3137851941 | N19: David Lopera medina | O19: david.lopera@socomes.com
B20: 10 | C20: COTIZACION DE LOS DISEÑOS DE PROTECCIÓN CONTRA INCENDIOS - PLAZA DE MERCADO ANDES | I20: Ingesed | J20: 13170000 | K20: 45671 | M20: 3135401714 | N20: Eliana Isabel Cardona Ríos | O20: comercial@ingesed.com
B21: 11 | C21: COTIZACION DE LOS DISEÑOS DE SEGURIDAD HUMANA Y PROTECCIÓN CONTRA INCENDIOS - MIC GUARNE | I21: Jomark Seguridad SAS | J21: 19950000 | K21: 45671 | M21: 3194913179 | N21: Carlos Almanya Patiño | O21: calmanya@jomarkseguridad.com
B22: 12 | C22: COTIZACION DE LOS DISEÑOS DE SEGURIDAD HUMANA Y PROTECCIÓN CONTRA INCENDIOS - MAZDA VEGAS | I22: Jomark Seguridad SAS | J22: 19850000 | K22: 45671 | M22: 3194913179 | N22: Carlos Almanya Patiño | O22: calmanya@jomarkseguridad.com
B23: 13 | C23: COTIZACION DE LOS DISEÑOS DE SEGURIDAD HUMANA Y PROTECCIÓN CONTRA INCENDIOS - CANCHAS PADEL | I23: Coninsa | J23: 6950000 | K23: 45672 | M23: 3155264386 | N23: Yuliana Tamayo Zapata | O23: ytamayo@coninsa.co
B24: 14 | C24: COTIZACION DEL DISEÑO DE EXTINCIÓN DE INCENDIOS - BODEGA 4000 M2 LA ESTRELLA | I24: ITC Diseños | J24: 18000000 | K24: 45674 | M24: 3044003430 | N24: Gino Alejandro Montoya | O24: gino1037@hotmail.com
B25: 15 | C25: COTIZACION DE LOS DISEÑOS DE PROTECCIÓN CONTRA INCENDIOS - CREACIONES APICE | I25: SPCI | J25: 25810000 | K25: 45674 | M25: 3104165783 | N25: Cristiam Gustavo Mondragon | O25: dir.tecnico@spci.com.co
B26: 16 | C26: COTIZACION DEL ANÁLISIS DE SEGURIDAD HUMANA - EL PRADO | I26: OTACC | J26: 10670000 | K26: 45677 | M26: 3107195105 | N26: Alejandra Rodriguez Sandoval | O26: jrodriguez@otacc.com
B27: 17 | C27: COTIZACION DE LOS DISEÑOS DE SEGURIDAD HUMANA Y PROTECCIÓN CONTRA INCENDIOS - EL ESMERALDAL | I27: Ingesed | J27: 17950000 | K27: 45677 | M27: 3135401714 | N27: Eliana Isabel Cardona Ríos | O27: comercial@ingesed.com
B28: 18 | C28: COTIZACION DE LOS DISEÑOS DE SEGURIDAD HUMANA Y PROTECCIÓN CONTRA INCENDIOS - VERMONTE TORRE 3 | I28: Intervé | J28: 7650000 | K28: 45674 | M28: 3012409366 | N28: Humberto Acevedo | O28: hacevedo@interve.co
B29: 19 | C29: COTIZACION DE LOS DISEÑOS DE SEGURIDAD HUMANA Y PROTECCIÓN CONTRA INCENDIOS - PLAZA EL AGUA | I29: Condiseño | J29: 14850000 | K29: 45677 | M29: 3175594091 | N29: Nakary Garcia Romero | O29: n.garcia@condiseno.co
B30: 20 | C30: COTIZACION DE LOS DISEÑOS DE PROTECCIÓN CONTRA INCENDIOS Y SEGURIDAD HUMANA PARA EL PROYECTO MALL COMERCIAL NATAL | I30: RRP | J30: 11520000 | K30: 45677 | N30: Daniel Andrés Restrepo Ríos | O30: danielrestrepo0804@gmail.com
B31: 21 | C31: COTIZACION DE LOS DISEÑOS DE SEGURIDAD HUMANA Y PROTECCIÓN CONTRA INCENDIOS - PROYECTO GIN | I31: FCR | J31: 24840000 | K31: 45677 | M31: 310 5304562 | N31: Vanessa Zapata | O31: vanessazapata.fcr@gmail.com
B32: 22 | C32: COTIZACION DEL ANÁLISIS DE SEGURIDAD HUMANA - CLÍNICA PEDIÁTRICA COLSUBSIDIO | I32: Condiseño | J32: 14000000 | K32: 45678 | M32: 3175594091 | N32: Nakary Garcia Romero | O32: n.garcia@condiseno.co
B33: 23 | C33: COTIZACION DE LOS DISEÑOS DE PROTECCIÓN CONTRA INCENDIOS - PISOS 36 37 38 Y 40 TORRE COLPATRIA | I33: SPCI | J33: =7900000+4010000 -> 11910000 | K33: 45679 | M33: 3104165783 | N33: Cristiam Gustavo Mondragon | O33: dir.tecnico@spci.com.co
B34: 24 | C34: COTIZACION DE LOS PLANOS Y CANTIDADES DE SEÑALIZACIÓN DE EMERGENCIA - BODEGA CA-20 | I34: Fire Marshal | J34: 2500000 | K34: 45679 | M34: 3224188478 | N34: Andrea Núñez | O34: andreanunez@firemarshal.com.co
B35: 25 | C35: COTIZACION DEL ANÁLISIS DE SEGURIDAD HUMANA - SERENA | I35: Conconcreto | J35: 6270000 | K35: 45679 | M35: 3148721400 | N35: Adriana Agudelo López | O35: aagudelol@conconcreto.com
B36: 26 | C36: COTIZACION DE LOS DISEÑOS DE SEGURIDAD HUMANA Y PROTECCIÓN CONTRA INCENDIOS - CENTRO DE CONVENCIONES ABURRA SUR | I36: Convel | J36: 14450000 | K36: 45679 | M36: 3137337587 | N36: Juan Naranjo | O36: juannarajo@convel.co
B37: 27 | C37: COTIZACION DEL ANÁLISIS DE SEGURIDAD HUMANA - MAKURA | I37: Perfek | J37: 6270000 | K37: 45679 | M37: 3148600291 | N37: Laura Cardona Cardona | O37: laura.cardona@perfek.com.co
B38: 28 | C38: COTIZACION DEL ANÁLISIS DE SEGURIDAD HUMANA - CLINICA CUCUTA 6.850 M2 | I38: Condiseño | J38: 8780000 | K38: 45679 | M38: 3175594091 | N38: Nakary Garcia Romero | O38: n.garcia@condiseno.co
B39: 29 | C39: COTIZACION DEL DISEÑO DE DETECCIÓN DE INCENDIOS - BODEGA QUIMICOS IMUSA | I39: SPCI | J39: 2500000 | K39: 45679 | M39: 3104165783 | N39: Cristiam Gustavo Mondragon | O39: dir.tecnico@spci.com.co
B40: 30 | C40: COTIZACION DEL DISEÑO DE EXTINCIÓN DE INCENDIOS - BODEGAS PEREIRA | I40: Proyect & solution | J40: 12500000 | K40: 45680 | M40: 311 3079477 | N40: Sebastian Lopez Duque | O40: gerencia@projectsolutions.com.co
B41: 31 | C41: COTIZACION DE LOS DISEÑOS DE PROTECCIÓN CONTRA INCENDIOS - INSTITUCION EDUCATIVA LA LIBERTAD | I41: Desarrollo urbano Edu | J41: Variable | K41: 45681 | M41: 3012547727 | N41: Mauricio Sepulveda
B42: 32 | C42: COTIZACION DE LOS DISEÑOS DE PROTECCIÓN CONTRA INCENDIOS - ALTAMONTE | I42: Bitacora ingenieria | J42: 2950000 | K42: 45685 | M42: 3006940601 | N42: Luisa Alarcón | O42: luisa.alarcon@bitacoraingenieria.com
B43: 33 | C43: COTIZACION DE LOS DISEÑOS DE SEGURIDAD HUMANA Y PROTECCIÓN CONTRA INCENDIOS - MALL SANTA CLARA (VIVARI) | I43: Arquitectura y concreto | J43: 66750000 | K43: 45684 | M43: 3127218621 | N43: Robinson Marulanda Guarín | O43: robinsonmarulanda@arquitecturayconcreto.com
B44: 34 | C44: COTIZACION DE LOS DISEÑOS DE SEGURIDAD HUMANA Y PROTECCIÓN CONTRA INCENDIOS - SE VICTOR G Y N | I44: Entretangencia | J44: 21950000 | K44: 45684 | M44: 3045239213 | N44: Daniel Bustamante | O44: gerencia@entretangencia.com
B45: 35 | C45: COTIZACION DEL DISEÑO DE DETECCIÓN DE INCENDIOS - HB FULLER | I45: Seriinco | J45: 12540000 | K45: 45685 | M45: 3113391008 | N45: Carlos Henao | O45: carlos.henao@seriinco.com
B46: 36 | C46: COTIZACION DEL DISEÑO DE EXTINCIÓN DE INCENDIOS - CARPINELO | I46: Good group | J46: 1950000 | K46: 45685 | M46: 3162963854 | N46: Deisy Duque | O46: operaciones@goodgroup.com.co
B47: 37 | C47: COTIZACION DE LOS DISEÑOS DE SEGURIDAD HUMANA Y PROTECCIÓN CONTRA INCENDIOS - VERBENA | I47: FCR | J47: 39510000 | K47: 45685 | M47: 3014317086 | N47: Tamara Puerta | O47: fcrtamarapuerta@gmail.com
B48: 38 | C48: COTIZACION DE LOS DISEÑOS DE PROTECCIÓN CONTRA INCENDIOS - REFRIDCOL-KOBA | I48: SPCI | J48: 6590000 | K48: 45685 | M48: 3104165783 | N48: Cristiam Gustavo Mondragon | O48: dir.tecnico@spci.com.co
B49: 39 | C49: COTIZACION DE LOS DISEÑOS DE SEGURIDAD HUMANA Y PROTECCIÓN CONTRA INCENDIOS - BOLERA DGREEN | I49: Ingesed | J49: 15920000 | K49: 45685 | M49: 321 8338189 | N49: Laura Delgado | O49: operacionesingesed@gmail.com
B50: 40 | C50: COTIZACION DE LOS DISEÑOS DE SEGURIDAD HUMANA Y PROTECCIÓN CONTRA INCENDIOS - SERRERIA JERICO | I50: Go ingenieria y soluciones | J50: NO SE COTIZÓ | K50: 45685 | M50: 310 5104288 | N50: Christian Gañan Ibarra | O50: goingenieriaysoluciones@gmail.com
B51: 41 | C51: COTIZACION DE LOS DISEÑOS DE SEGURIDAD HUMANA Y PROTECCIÓN CONTRA INCENDIOS - COLEGIO JORGE ROBLEDO | I51: Detectar Systems | J51: 20450000 | K51: 45685 | N51: Julián Ortega Gómez | O51: detectarsystems@gmail.com
B52: 42 | C52: COTIZACION DEL DISEÑO DE DETECCIÓN DE INCENDIOS - MUMA | I52: SPCI | J52: 24960000 | K52: 45685 | M52: 3104165783 | N52: Cristiam Gustavo Mondragon | O52: dir.tecnico@spci.com.co
B53: 43 | C53: COTIZACIÓN DE LOS CÁLCULOS SE SUCCIÓN Y PLANOS RECORD DEL CUARTO DE BOMBAS PARA EL PROYECTO PRIMEIRO | I53: Estructurar | J53: 4000000 | K53: 45686 | M53: 3045281069 | N53: Ángela Molina | O53: posventas@estructurar.co
B54: 43 | C54: COTIZACION DEL DISEÑO DE EXTINCIÓN DE INCENDIOS - CC ALMENDROS | I54: SPCI | J54: VARIABLE | K54: 45687 | M54: 3104165783 | N54: Cristiam Gustavo Mondragon | O54: dir.tecnico@spci.com.co
B55: 44 | C55: COTIZACIÓN DE LOS DISEÑOS DE EXTINCIÓN DE INCENDIOS DEL PROYECTO PIAMONTE | I55: Ingesed | J55: 17950000 | K55: 45687 | M55: 3014201614 | N55: Jhon Rodriguez | O55: jrodriguez@ingesed.com
B56: 45 | C56: COTIZACIÓN DE LOS DISEÑOS DE EXTINCIÓN DE INCENDIOS DEL PROYECTO | I56: Proyecto ARQ | J56: 2905100 | K56: 45701 | M56: 3125447366 | N56: Andrea Ruiz
B57: 46 | C57: COTIZACION DE LOS DISEÑOS DE SEGURIDAD HUMANA Y PROTECCIÓN CONTRA INCENDIOS - ANGELES CUSTODIOS | I57: E&F Construcciones | J57: 5640000 | K57: 45687 | M57: 3122426622 | N57: Santiago Castañeda | O57: ef.construccionessas@gmail.com
B58: 47 | C58: COTIZACION DEL DISEÑO DE DETECCIÓN DE INCENDIOS - BODEGA GROUPE SEB RIONEGRO | I58: SPCI | J58: 14950000 | K58: 45688 | M58: 3104165783 | N58: Cristiam Gustavo Mondragon | O58: dir.tecnico@spci.com.co
B59: 48 | C59: COTIZACION DE LOS DISEÑOS DE SEGURIDAD HUMANA Y PROTECCIÓN CONTRA INCENDIOS - URBIT HUB | I59: Juan Arango | J59: 22850000 | K59: 45688 | N59: Juan Arango | O59: jmarangom22@gmail.com
B60: 49 | C60: COTIZACION DE LOS DISEÑOS DE PROTECCIÓN CONTRA INCENDIOS - SUCURSAL EL RETIRO (415) | I60: Trazados Arquitectura | J60: 4950000 | K60: 45692 | M60: 3167417025 | O60: escapeto28@gmail.com
B61: 50 | C61: COTIZACION DE LOS DISEÑOS DE SEGURIDAD HUMANA Y PROTECCIÓN CONTRA INCENDIOS - VILLA CIELO APARTAMENTOS T1 | I61: Detectar Systems | J61: 26340000 | K61: 45692 | N61: Julián Ortega Gómez | O61: detectarsystems@gmail.com
B62: 51 | C62: COTIZACION DEL ANÁLISIS DE SEGURIDAD HUMANA - ANTILLAS | I62: Maz | J62: 29650000 | K62: 45693 | M62: 601 6108010 | N62: Diego Alejandro Arango Gómez | O62: darango@maz.com.co
B63: 52 | C63: COTIZACION DE LOS DISEÑOS DE SEGURIDAD HUMANA Y PROTECCIÓN CONTRA INCENDIOS - EDF. PSICOLOGIA UNIVALLE | I63: IngenioBIM | J63: 39510000 | K63: 45693 | M63: 3014170260 | N63: Jenifer Vanessa Orozco Ordoñez | O63: jenifer.orozco@ingeniobim.co
B64: 53 | C64: COTIZACION DE LOS DISEÑOS DE SEGURIDAD HUMANA Y PROTECCIÓN CONTRA INCENDIOS - MONTEMERANO | I64: Constructora Guasandi | J64: 28850000 | K64: 45692 | N64: Laura Jiménez Grajales | O64: dircambulos@constructoradeobras.com
B65: 54 | C65: COTIZACION DEL DISEÑO DE EXTINCIÓN DE INCENDIOS - GIMNASIO Y CANCHA DE SQUASH PROYECTO MAZANTTI | I65: Conintel | J65: 1500000 | K65: 45692 | M65: 320 6284446 | N65: Marcela Cardona | O65: direccionmazanti@gmail.com
B66: 55 | C66: COTIZACION DEL DIAGNÓSTICO DE LOS SISTEMAS DE PROTECCIÓN CONTRA INCENDIOS - CLÍNICA IMBANACO CALI | I66: IMBANACO | J66: 16600000 | K66: 45694 | M66: 3205535416 | N66: Camilo Andrés Chávez Sandoval | O66: Camilo.Chavez@quironsalud.com
B67: 56 | C67: COTIZACION DE LOS DISEÑOS DE SEGURIDAD HUMANA Y PROTECCIÓN CONTRA INCENDIOS - VERMONTE LOCALES COMERCIALES | I67: Intervé | J67: 6950000 | K67: 45694 | M67: 3004659012 | N67: Martha Lucia Ferrer | O67: mferrer@interve.co
B68: 57 | C68: COTIZACION DE LOS DISEÑOS DE SEGURIDAD HUMANA Y PROTECCIÓN CONTRA INCENDIOS - ETAPA 2 LA SALLE | I68: Intervé | J68: 31950000 | K68: 45695 | M68: 3007808119 | N68: Luis Felipe Arboleda Monsalve | O68: farboleda@interve.co
B69: 58 | C69: COTIZACION DEL DISEÑO DE EXTINCIÓN DE INCENDIOS - TERMILENIO TEXTILES | I69: SPCI | J69: 15000000 | K69: 45700 | M69: 3104165783 | N69: Cristiam Gustavo Mondragon | O69: dir.tecnico@spci.com.co
B70: 59 | C70: COTIZACION DEL DISEÑO DE DETECCIÓN DE INCENDIOS - HOTEL YORK LUXURY SUITES | I70: Detectar Systems | J70: 6250000 | K70: 45698 | N70: Julián Ortega Gómez | O70: detectarsystems@gmail.com
B71: 60 | C71: COTIZACION DEL ANÁLISIS DE SEGURIDAD HUMANA - MERAKI ETAPA 3 | I71: Grupo Valor | J71: 4750000 | K71: 45699 | M71: 3054231775 | N71: Laura Valentina Bello Tovar | O71: arquitectura1@grupovalor.com.co
B72: 61 | C72: COTIZACION DE LOS DISEÑOS DE SEGURIDAD HUMANA Y PROTECCIÓN CONTRA INCENDIOS - PUEBLO PANACA | I72: Perfek | J72: 35550000 | K72: 45699 | N72: Johana Montoya Zapata | O72: Johana.montoya@perfek.com.co
B73: 62 | C73: COTIZACION DE LOS DISEÑOS DE PROTECCIÓN CONTRA INCENDIOS - CORNARE | I73: Coinsi | J73: 2500000 | K73: 45699 | M73: 3117208541 | N73: Sergio Rodriguez | O73: diseno4@gyd.com.co
B74: 63 | C74: COTIZACION DEL DISEÑO DE EXTINCIÓN DE INCENDIOS - SMART FIT GRAN PLAZA SOL | I74: Hidraulica y Montajes | J74: 4000000 | K74: 45699 | M74: 301 4487912 | N74: Evelin Rojas | O74: hidraulicaymontajes@gmail.com
B75: 64 | C75: COTIZACION DEL DISEÑO DE EXTINCIÓN DE INCENDIOS - SMART FIT ECOTEK | I75: Hidraulica y Montajes | J75: 4000000 | K75: 45699 | M75: 301 4487912 | N75: Evelin Rojas | O75: hidraulicaymontajes@gmail.com
B76: 65 | C76: COTIZACION DE LOS DISEÑOS DE SEGURIDAD HUMANA Y PROTECCIÓN CONTRA INCENDIOS - MIIT | I76: Arquitectura y concreto | J76: 26250000 | K76: 45700 | M76: 3127218621 | N76: Robinson Marulanda Guarín | O76: robinsonmarulanda@arquitecturayconcreto.com
B77: 66 | C77: COTIZACION DE LOS DISEÑOS DE PROTECCIÓN CONTRA INCENDIOS - PLANTA DE PRODUCCION DE BISUTERIA | I77: SPCI | J77: 54180000 | K77: 45701 | M77: 3104165783 | N77: Cristiam Gustavo Mondragon | O77: dir.tecnico@spci.com.co
B78: 67 | C78: COTIZACION DEL DISEÑO DE EXTINCIÓN DE INCENDIOS - PLANTA DE REACTIVOS NACIONALES | I78: Consultores e ingenieros Q&M | J78: 11950 | K78: 45700 | M78: +51 940500519 | N78: Luis Martinez | O78: luis.martinez@qymsac.com
B79: 68 | C79: COTIZACION DEL DISEÑO DE DETECCIÓN DE INCENDIOS - LA MAYORIA | I79: INVERSIONES ORBET S.A.S. | K79: 45701 | M79: 3178701188-3505490874 | N79: Catalina Hernandez | O79: reservas@lamayoria.com
B80: 69 | C80: COTIZACION DEL REDISEÑO DE EXTINCIÓN DE INCENDIOS - USHUAYA | I80: Edyfica | J80: 2950000 | K80: 45701 | M80: 310 4057513 | N80: Claudia Ramirez | O80: claudia.ramirez@edyfica.co
B81: 70 | C81: COTIZACION DEL DISEÑO DE EXTINCIÓN DE INCENDIOS - ACTION BLACK FLORIDA | I81: Hidraulica y Montajes | J81: 4000000 | K81: 45701 | M81: 301 4487912 | N81: Evelin Rojas | O81: hidraulicaymontajes@gmail.com
B82: 71 | C82: COTIZACION DE LOS DISEÑOS DE SEGURIDAD HUMANA Y PROTECCIÓN CONTRA INCENDIOS - PUEBLO PANACA | I82: Hidraulica y Montajes | J82: 35550000 | K82: 45701 | M82: 301 4487912 | N82: Evelin Rojas | O82: hidraulicaymontajes@gmail.com
B83: 72 | C83: COTIZACION DE LOS DISEÑOS DE SEGURIDAD HUMANA Y PROTECCIÓN CONTRA INCENDIOS - VERDDE | I83: TIP Interventoria | J83: 21950000 | K83: 45701 | M83: 3053308954 | N83: Juan David Lopez Toro | O83: supervisionflexliving@tipinterventoria.com
B84: 73 | C84: COTIZACION DE LOS DISEÑOS DE SEGURIDAD HUMANA Y PROTECCIÓN CONTRA INCENDIOS - DITRANSA BODEGA CARTAGENA | I84: Ingesed | J84: 13800000 | K84: 45701 | M84: 3135401714 | N84: Eliana Isabel Cardona Ríos | O84: comercial@ingesed.com
B85: 74 | C85: COTIZACION DE LOS DISEÑOS DE SEGURIDAD HUMANA Y PROTECCIÓN CONTRA INCENDIOS - DITRANSA BODEGA HOMED ITAGUI | I85: Ingesed | J85: 21950000 | K85: 45701 | M85: 3135401714 | N85: Eliana Isabel Cardona Ríos | O85: comercial@ingesed.com
B86: 75 | C86: COTIZACION DE LOS DISEÑOS DE SEGURIDAD HUMANA Y PROTECCIÓN CONTRA INCENDIOS - DITRANSA BODEGA PREMIUM | I86: Ingesed | J86: 9970000 | K86: 45701 | M86: 3135401714 | N86: Eliana Isabel Cardona Ríos | O86: comercial@ingesed.com
B87: 76 | C87: COTIZACION DE LOS DISEÑOS DE PROTECCIÓN CONTRA INCENDIOS - TANQUE GLP PREMAC | I87: Ingesed | J87: 8970000 | K87: 45702 | M87: 3135401714 | N87: Eliana Isabel Cardona Ríos | O87: comercial@ingesed.com
B88: 77 | C88: COTIZACION DEL DISEÑO DE DETECCIÓN DE INCENDIOS - ANTILLAS | I88: Fire Marshal | J88: 7650000 | K88: 45701 | M88: 3224188478 | N88: Andrea Núñez | O88: andreanunez@firemarshal.com.co
B89: 78 | C89: COTIZACION DEL ANÁLISIS DE SEGURIDAD HUMANA - SENA DE OCCIDENTE | I89: DESur | J89: 3760000 | K89: 45707 | M89: (604) 4801300 Ext 148 | N89: Manuela Henao López | O89: manuela.henao@desur.gov.co
B90: 79 | C90: COTIZACION DEL ANÁLISIS DE SEGURIDAD HUMANA - FRAKTAL_47 | I90: Tres cubos proyectos SAS | J90: 5270000 | K90: 45707 | M90: 3103964703 | N90: Gabriel Meneses Patiño | O90: gtrescubos@gmail.com
B91: 80 | C91: COTIZACION DEL DISEÑO DE DETECCIÓN DE INCENDIOS - FRAKTAL_47 | I91: Tres cubos proyectos SAS | J91: 6770000 | K91: 45707 | M91: 3103964703 | N91: Gabriel Meneses Patiño | O91: gtrescubos@gmail.com
B92: 81 | C92: COTIZACION DEL DISEÑO DE EXTINCIÓN DE INCENDIOS - FRAKTAL_47 | I92: Tres cubos proyectos SAS | J92: 15240000 | K92: 45707 | M92: 3103964703 | N92: Gabriel Meneses Patiño | O92: gtrescubos@gmail.com
B93: 82 | C93: COTIZACION DEL DISEÑO DE DETECCIÓN DE INCENDIOS - D1 BODEGA P4 | I93: Ingesed | J93: 4950000 | K93: 45707 | M93: 3135401714 | N93: Eliana Isabel Cardona Ríos | O93: comercial@ingesed.com
B94: 83 | C94: COTIZACION DE LOS DISEÑOS DE SEGURIDAD HUMANA Y PROTECCIÓN CONTRA INCENDIOS - D1 BODEGA P8 | I94: Ingesed | J94: 17940000 | K94: 45707 | M94: 3135401714 | N94: Eliana Isabel Cardona Ríos | O94: comercial@ingesed.com
B95: 84 | C95: COTIZACION DEL ANÁLISIS DE SEGURIDAD HUMANA - FRUTOS VERDES TORRE 12 | I95: Conintel | J95: 1000000 | K95: 45707 | M95: (604) 2662377 ext 129 | N95: Yessica Osorno Cardeño | O95: liderbim@conintel.com.co
B96: 85 | C96: COTIZACION DEL DISEÑO DE EXTINCIÓN DE INCENDIOS - CEINTEC | I96: SPCI | J96: 9970000 | K96: 45706 | M96: 3104165783 | N96: Cristiam Gustavo Mondragon | O96: dir.tecnico@spci.com.co
B97: 86 | C97: COTIZACION DE LOS DISEÑOS DE SEGURIDAD HUMANA Y PROTECCIÓN CONTRA INCENDIOS - SANFRCO | I97: Invigeo | J97: 15990000 | K97: 45706 | M97: 3148620055 | N97: Sebastián Amaya | O97: Proyectos.invigeo@gmail.com
B98: 87 | C98: COTIZACION DEL DISEÑO DE EXTINCIÓN DE INCENDIOS - BODEGAS INVESA | I98: Invesa | J98: 55850000 | K98: 45706 | M98: 604 3342727 | N98: Juan Carlos Marín | O98: jmarin@invesa.com
B99: 88 | C99: COTIZACION DE LOS DISEÑOS DE SEGURIDAD HUMANA Y PROTECCIÓN CONTRA INCENDIOS - MULTIFAMILY | I99: Soluciones civiles | J99: 32550000 | K99: 45707 | M99: 604 4483960 | N99: Gustavo Aguirre Arcila | O99: gaguirre@solciviles.com
B100: 89 | C100: COTIZACION DEL ANÁLISIS DE SEGURIDAD HUMANA - EL ROCIO 9 | I100: OTACC | J100: 7110000 | K100: 45709 | M100: 3107195105 | N100: Alejandra Rodríguez Sandoval | O100: jrodriguez@otacc.com
B101: 90 | C101: COTIZACION DE LOS DISEÑOS DE SEGURIDAD HUMANA Y PROTECCIÓN CONTRA INCENDIOS - TRIALA | I101: Fundamental Arquitectura y Urbanismo | J101: 27950000 | K101: 45708 | M101: 3148128006 | N101: Manuela Uribe B | O101: muribe@fundamental-au.com
B102: 91 | C102: COTIZACION DEL ANÁLISIS DE SEGURIDAD HUMANA - PROYECTO BELEN | I102: Perspectiva A y C | J102: 3150000 | K102: 45708 | M102: 3163069332 | N102: John Valencia | O102: John.valencia@perspectivaayc.com
B103: 92 | C103: COTIZACION DE LOS DISEÑOS DE SEGURIDAD HUMANA Y PROTECCIÓN CONTRA INCENDIOS - USHUAYA TORRE 2 | I103: Edyfica | J103: 20700000 | K103: 45709 | M103: 3127575897 | N103: Juan Manuel Russi
B104: 93 | C104: COTIZACION DE LOS DISEÑOS DE SEGURIDAD HUMANA Y PROTECCIÓN CONTRA INCENDIOS - ALGECIRAS | I104: Geinner Montoya | J104: 20950000 | K104: 45709 | M104: 3045950866 | N104: Geinner Montoya | O104: Geinermontoya2015@gmail.com
B105: 94 | C105: COTIZACION DE LOS DISEÑOS DE SEGURIDAD HUMANA Y PROTECCIÓN CONTRA INCENDIOS - UNIK | I105: FCR | J105: 23960000 | K105: 45709 | M105: 311 3304231 | N105: Daniela Vélez | O105: danielavelez.fcr@gmail.com
B106: 95 | C106: COTIZACION DE LOS DISEÑOS DE SEGURIDAD HUMANA Y PROTECCIÓN CONTRA INCENDIOS - MOKARA TORRE 3 | I106: FCR | J106: 16930000 | K106: 45709 | M106: 311 3304231 | N106: Daniela Vélez | O106: danielavelez.fcr@gmail.com
B107: 96 | C107: COTIZACION DEL DISEÑO DE EXTINCIÓN DE INCENDIOS - PROYECTO BODEGA 39 INTEXZONA | I107: SPCI | J107: 18820000 | K107: 45709 | M107: 3104165783 | N107: Cristiam Gustavo Mondragon | O107: dir.tecnico@spci.com.co
B108: 97 | C108: COTIZACION DE LOS DISEÑOS DE SEGURIDAD HUMANA Y PROTECCIÓN CONTRA INCENDIOS - EL CARMEN COLONIAL | I108: FP Civiles | J108: 16450000 | K108: 45709 | M108: 3135204138 | N108: Cristian Miguel Cabrera Rivas | O108: ccabrera@fpciviles.com
...

Sheet 2026
D2: SEGUIMIENTO A COTIZACIONES - 2026
B10: Número de cotización | C10: Descripción de la cotización | I10: Cliente | J10: Valor sin IVA | K10: Fecha de cotización | L10: Aprobado | M10: Telefono | N10: Persona Encargada | O10: Cargo | P10: Correo
B11: 1 | C11: COTIZACION DE LOS DISEÑOS DE SEGURIDAD HUMANA Y PROTECCIÓN CONTRA INCENDIOS - RIVER PARK | I11: Arquitectura y Concreto | J11: 32150000 | K11: 46027 | M11: 3162439535 | N11: Sebastián Ochoa Gómez | O11: Coordinación Técnica | P11: sebastianochoa@arquitecturayconcreto.com
B12: 2 | C12: COTIZACION DE LOS DISEÑOS DE SEGURIDAD HUMANA Y PROTECCIÓN CONTRA INCENDIOS - GUARNE | I12: FCR | J12: No se cotizó | K12: 46027 | M12: 321 6068780 | N12: Luz Stella Ibarra | P12: stellaibarra@gmail.com
B13: 3 | C13: COTIZACION CAPACITACIÓN SISTEMAS CONTRA INCENDIOS | I13: FIREEQUIPOS | J13: 4500000 | K13: 46027 | M13: 3136650714 | N13: Samuel Piedrahíta | O13: Director Técnico | P13: operaciones.fireyequipos@gmail.com
B14: 4 | C14: COTIZACION DE LOS DISEÑOS DE SEGURIDAD HUMANA Y PROTECCIÓN CONTRA INCENDIOS - BOSQUE DE PIEDRA | I14: Comfama | J14: 33870000 | K14: 46035 | M14: 310 4057513 | N14: Claudia Marcela Ramírez Gómez | O14: Coordinadora de Proyectos | P14: ClaudiaRamirez@comfama.com.co
B15: 5 | C15: COTIZACION DE LOS DISEÑOS DE SEGURIDAD HUMANA Y PROTECCIÓN CONTRA INCENDIOS - SAN SIMÓN T3 | I15: Constructora Altos de la Abadía | J15: 29970000 | K15: 46035 | M15: 313 4250445 | N15: Jessica Chiguasuque | O15: Coordinadora BIM | P15: j.chiguasuque@altosdelaabadia.com
B16: 6 | C16: COTIZACION DEL ANÁLISIS DE SEGURIDAD HUMANA - NUEVO POBLADO ETAPA 3 | I16: Conconcreto | J16: 9970000 | K16: 46035 | M16: 300 4938086 | N16: Andrés Felipe Martinez | O16: Coordinador de diseño de arquitectura | P16: amartineza@conconcreto.com
B17: 7 | C17: COTIZACION DEL DISEÑO DE EXTINCIÓN DE INCENDIOS - PARQUEADERO Y ESTADIO DE BEISBOL ATANASIO | I17: AD Arquitectura y diseño urbano | J17: 49950000 | K17: 46029 | M17: 314 8934775 | N17: Diego Fernando Uribe Alvarez
B18: 8 | C18: COTIZACION DEL DISEÑO DE EXTINCIÓN DE INCENDIOS - IRIS AMBAR ALCABAMA | I18: Good group | J18: 3950000 | K18: 46029 | M18: 3155713220 | N18: Adriana Pulido | P18: comercial@goodgroup.com.co
B19: 9 | C19: COTIZACION DEL ANÁLISIS DE SEGURIDAD HUMANA - MALL LA KONDINA | I19: Raiz Constructora | J19: 7550000 | K19: 46029 | M19: 3113555383 | N19: Daniel Fernando Hernández | P19: coordinadorobra@raizconstructora.com.co
B20: 10 | C20: COTIZACION DEL DISEÑO DE EXTINCIÓN DE INCENDIOS - CALMO TORRE 3 Y 4 | I20: Proyectos urbanos | J20: 12550000 | K20: 46029 | M20: 3113733919 | N20: Priscila Quintero | P20: planeacion@proyectosurbanos.com.co
B21: 11 | C21: COTIZACION DE LOS DISEÑOS DE SEGURIDAD HUMANA Y PROTECCIÓN CONTRA INCENDIOS - HOSPITAL NEUROLÓGICO | I21: Hospital Neurologico | J21: 45150000 | K21: 46029 | N21: Maria Isabel Betancur | P21: maria.betancur@neurologico.org.co
B22: 12 | C22: COTIZACION DE LOS DISEÑOS DE PROTECCIÓN CONTRA INCENDIOS - PLANTA DE GLP | I22: Massy Energy | J22: No se cotizó | K22: 46029 | M22: 3205465936 | N22: Jean Pierre López León | P22: jean.lopez@massygroup.com
B23: 13 | C23: COTIZACION DEL DISEÑO DE EXTINCIÓN DE INCENDIOS - ÁREAS CLASIFICADAS | I23: Alcecol ingenieria | J23: 24950000 | K23: 46029 | M23: 3202156014 | N23: David A Ceron | P23: Inspecciones@alcecol.com
B24: 14 | C24: COTIZACION DEL ANÁLISIS DE SEGURIDAD HUMANA - HILTON CALI | I24: Girar Construcciones | J24: 9970000 | K24: 46035 | M24: 310 5377343 | N24: Felipe Giraldo Cube | P24: girarconstrucciones@gmail.com
B25: 15 | C25: COTIZACION DE LOS DISEÑOS DE PROTECCIÓN CONTRA INCENDIOS - D1 MALL SANTANA | I25: Ingesed | J25: 5000000 | K25: 46032 | M25: 321 8338189 | N25: Laura Delgado | P25: operacionesingesed@gmail.com
B26: 16 | C26: COTIZACION DEL DISEÑO DE EXTINCIÓN DE INCENDIOS - AUTOLAND BARRANQUILLA | I26: Ingesed | J26: 13950000 | K26: 46035 | M26: 3014201614 | N26: Jhon Anderson Rodriguez Nieto | P26: jrodriguez@ingesed.com
B27: 17 | C27: COTIZACION DEL DISEÑO DE EXTINCIÓN DE INCENDIOS - TEATRO LIDO | I27: Civilsa | J27: 5000000 | K27: 46032 | M27: 310 4659572 | N27: Julio Alzate | O27: Ingeniero Sanitario | P27: julialzate@une.net.co
B28: 18 | C28: COTIZACION DEL DISEÑO DE EXTINCIÓN DE INCENDIOS - AUTOLAND LAS VEGAS | I28: Ingesed | J28: 15950000 | K28: 46035 | M28: 3014201614 | N28: Jhon Anderson Rodriguez Nieto | P28: jrodriguez@ingesed.com
B29: 19 | C29: COTIZACION DE LOS DISEÑOS DE SEGURIDAD HUMANA Y EXTINCIÓN DE INCENDIOS - ZC MONTERREY | I29: I+Constructora | J29: 9950000 | K29: 46036 | M29: (604) 4443091 | N29: Lina Maria Montoya | P29: lmontoya@iconsultores.com.co
B30: 20 | C30: COTIZACION DE LOS DISEÑOS DE PROTECCIÓN CONTRA INCENDIOS - DISCOLMEDICA | I30: SPCI | J30: 14980000 | K30: 46037 | M30: 3104165783 | N30: Cristiam Gustavo Mondragon | O30: Director técnico | P30: dir.tecnico@spci.com.co
B31: 21 | C31: COTIZACION DE LOS DISEÑOS DE SEGURIDAD HUMANA Y PROTECCIÓN CONTRA INCENDIOS - KRATO | I31: Ingesed | J31: 24980000 | K31: 46037 | M31: 3135401714 | N31: Eliana Isabel Cardona Ríos | P31: comercial@ingesed.com
B32: 22 | C32: COTIZACION DEL ANÁLISIS DE SEGURIDAD HUMANA - MALL MELÉNDEZ | I32: Coninsa | J32: 9980000 | K32: 46037 | M32: 315 5264386 | N32: Yuliana Tamayo Zapata | O32: Profesional Senior de Estructuración Técnica | P32: ytamayo@coninsa.co
B33: 23 | C33: COTIZACION DEL ANÁLISIS DE SEGURIDAD HUMANA - MALL MELÉNDEZ | I33: Condiseño | J33: 9980000 | K33: 46037 | M33: 3175594091 | N33: Nakary García | O33: Directora Comercial | P33: n.garcia@condiseno.co
B34: 24 | C34: COTIZACION DEL DISEÑO DE EXTINCIÓN DE INCENDIOS - FIBRATORE PAVCO | I34: Prosoma | J34: 25000000 | K34: 46037 | M34: 3147537411 | N34: Adolfo Florez Cossio | P34: proyectos@prosoma.com.co
B35: 25 | C35: COTIZACION DE LOS DISEÑOS DE PROTECCIÓN CONTRA INCENDIOS - LUKER AGRICOLA | I35: Ingesed | J35: 12540000 | K35: 46038 | M35: 3014201614 | N35: Jhon A. Rodríguez Nieto | P35: jrodriguez@ingesed.com
B36: 26 | C36: COTIZACION DE LOS DISEÑOS DE SEGURIDAD HUMANA Y PROTECCIÓN CONTRA INCENDIOS - SELVATICO | I36: Constructora Fortich | J36: 26920000 | K36: 46038 | M36: 3153547367 | N36: Tomás Fortich | P36: Constructorafortich@gmail.com
B37: 27 | C37: COTIZACION DEL ANÁLISIS DE SEGURIDAD HUMANA - BOMBEROS CORTIJO | I37: Londoño Gomez | J37: 1450000 | K37: 46038 | M37: 3111770 ext 455 | N37: Lina M Saldarriaga | P37: lsaldarriaga@interlg.com
B38: 28 | C38: COTIZACION DE LOS DISEÑOS DE SEGURIDAD HUMANA Y PROTECCIÓN CONTRA INCENDIOS - BRUMARIA 2 | I38: Redigroup | J38: 9950000 | K38: 46038 | M38: 3053533308 | N38: Santiago Franco | P38: santiago.franco@redigroup.co
B39: 29 | C39: COTIZACION DE LOS DISEÑOS DE PROTECCIÓN CONTRA INCENDIOS - AUTOLAND LAS VEGAS | I39: Ingesed | J39: 21990000 | K39: 46038 | M39: 3014201614 | N39: Jhon Rodriguez | P39: jrodriguez@ingesed.com
B40: 30 | C40: COTIZACION DE LOS DISEÑOS DE PROTECCIÓN CONTRA INCENDIOS - AUTOLAND BARRANQUILLA | I40: Ingesed | J40: 20550000 | K40: 46038 | M40: 3014201614 | N40: Jhon Rodriguez | P40: jrodriguez@ingesed.com
B41: 31 | C41: COTIZACION DEL DISEÑO DE EXTINCIÓN DE INCENDIOS - HOTEL HERITAGE | I41: Fire & Equipos | J41: 15000000 | K41: 46041 | M41: 3134451063 | N41: Juan José Monsalve | O41: Director comercial y de proyectos | P41: Directorcomercial@fireyequipos.com
B42: 32 | C42: COTIZACION DEL DISEÑO DE EXTINCIÓN DE INCENDIOS - SAN NICOLAS | I42: CC San Nicolas | J42: 39950000 | K42: 46041 | M42: 6045614886 ext 132 | N42: Yeremy Sebastián Muñoz Zamarra | O42: Coordinador de infraestructura | P42: infraestructura@sannicolas.co
B43: 33 | C43: COTIZACION DE LOS DISEÑOS DE PROTECCIÓN CONTRA INCENDIOS - MANANTIALES | I43: Seriinco | J43: =9410000*3 -> 28230000 | K43: 46042 | M43: 3052837617 | N43: Alvaro Garcia | P43: alvaro.garcia@seriinco.com
B44: 34 | C44: COTIZACION DE LOS DISEÑOS DE SEGURIDAD HUMANA Y PROTECCIÓN CONTRA INCENDIOS - AZZURI TORRES 3 Y 4 | I44: Conaltura | J44: =15920000*2 -> 31840000 | K44: 46042 | M44: 3122310202 | N44: Yesenia Pareja | O44: Profesional Técnico | P44: ypareja@conaltura.com
B45: 35 | C45: COTIZACION DEL DISEÑO DE EXTINCIÓN DE INCENDIOS - AURORA | I45: Constructora MC | J45: 2950000 | K45: 46042 | N45: Yurany Orozco | P45: yuranyorozcoconstructoramc@gmail.com
B46: 36 | C46: COTIZACION DEL DISEÑO DE EXTINCIÓN DE INCENDIOS - TORRE GÉNESIS | I46: Constructora MC | J46: 3250000 | K46: 46042 | N46: Yurany Orozco | P46: yuranyorozcoconstructoramc@gmail.com
B47: 37 | C47: COTIZACION DE LOS DISEÑOS DE SEGURIDAD HUMANA Y PROTECCIÓN CONTRA INCENDIOS - I.E.NUEVA COLONIA | I47: IngenioBIM | J47: 39880000 | K47: 46042 | M47: 3044244065 | N47: Nasly Caro
B48: 38 | C48: COTIZACION DE LOS DISEÑOS DE SEGURIDAD HUMANA Y PROTECCIÓN CONTRA INCENDIOS - CARDIO INFANTIL PISO 2 | I48: Condiseño | J48: 10950000 | K48: 46042 | M48: 3175594091 | N48: Nakary García | O48: Directora Comercial | P48: n.garcia@condiseno.co
B49: 39 | C49: COTIZACION DE LOS DISEÑOS DE SEGURIDAD HUMANA Y PROTECCIÓN CONTRA INCENDIOS - TIERRAVIVA | I49: Mensula | J49: 39950000 | K49: 46043 | M49: 3188712570 | N49: Javier A. Zapa Oyola | P49: javierzapa@mensulaingenieros.com
B50: 40 | C50: COTIZACIÓN DE LA REVISIÓN TÉCNICA PARA LA RED CONTRA INCENDIOS NUEVA Y EXISTENTE DEL EDIFICIO 43 AVENIDA | I50: ACEIS | J50: 5000000 | K50: 46043 | M50: 3168335985 | N50: Andrés Gómez | O50: Administración Edificio 43 Avenida | P50: administracion.43avenida@aceis.com.co
B51: 41 | C51: COTIZACION DE LOS DISEÑOS DE SEGURIDAD HUMANA Y PROTECCIÓN CONTRA INCENDIOS -LA 30 ETAPA 1 | I51: Constructora Altos de la Abadía | J51: 20000000 | K51: 46044 | M51: 3175180141 | N51: Esteban Ramírez Pineda | O51: Subgerente diseños técnicos | P51: e.ramirez@altosdelaabadia.com
B52: 42 | C52: COTIZACION DEL DISEÑO DE EXTINCIÓN DE INCENDIOS - BLOQUE B | I52: Universidad Pontificia Bolivariana | J52: 19950000 | K52: 46044 | M52: 6044455900 | N52: Maribel Gutiérrez Cifuentes | P52: maribel.gutierrez@upb.edu.co
B53: 43 | C53: COTIZACION DE LOS DISEÑOS DE SEGURIDAD HUMANA Y PROTECCIÓN CONTRA INCENDIOS - CC MONTERREY | I53: I+Constructora | J53: 69950000 | K53: 46044 | M53: 6044443091 | N53: Juan Guillermo Urrea Tabares | P53: juangurreat@iconsultores.com.co
B54: 44 | C54: COTIZACION DE LOS DISEÑOS DE PROTECCIÓN CONTRA INCENDIOS - OKRE | I54: Nivelum | J54: 18150000 | K54: 46044 | M54: 3146620375 | N54: Sergio Osorio | P54: sosorio@nivelum.com
B55: 45 | C55: COTIZACION DE LOS DISEÑOS DE SEGURIDAD HUMANA Y PROTECCIÓN CONTRA INCENDIOS - PROPIEDAD DE 157.000 M2 | I55: Condiseño | J55: 25000000 | K55: 46044 | M55: 3175594091 | N55: Nakary García | O55: Directora Comercial | P55: n.garcia@condiseno.co
B56: 46 | C56: COTIZACION DE LOS DISEÑOS DE SEGURIDAD HUMANA Y PROTECCIÓN CONTRA INCENDIOS - JIBC CHAMBACÚ | I56: MGL Ingenieros | J56: 6950000 | K56: 46044 | M56: 3104297680 | N56: Faber Betancur
B57: 47 | C57: COTIZACION DEL DISEÑO DE EXTINCIÓN DE INCENDIOS - NEIVANA | I57: Fire & Equipos | J57: 11950000 | K57: 46044 | M57: 3136650714 | N57: Samuel Piedrahíta | O57: Director Técnico | P57: operaciones.fireyequipos@gmail.com
B58: 48 | C58: COTIZACION DEL ANÁLISIS DE SEGURIDAD HUMANA - BODEGA JERÓNIMO MARTINS MOSQUERA | I58: Conconcreto | J58: 11950000 | K58: 46046 | M58: 3003404902 | N58: Pilar Arango Restrepo | O58: Coordinadora de Diseño y Arquitectura | P58: parangor@conconcreto.com
B59: 49 | C59: COTIZACION DE LOS DISEÑOS DE SEGURIDAD HUMANA Y DETECCIÓN DE INCENDIOS - BRENTA | I59: Cusezar | J59: 53950000 | K59: 46048 | M59: 6516066 | N59: Olinda Milena Borja Villamil | P59: oborja@cusezar.com
B60: 50 | C60: COTIZACION DEL DISEÑO DE EXTINCIÓN DE INCENDIOS - PORTO | I60: Tres E | J60: 27550000 | K60: 46048 | N60: Alejandro Restrepo | P60: alejandrorestrepo@tres-e.com
B61: 51 | C61: COTIZACION DEL ANÁLISIS DE SEGURIDAD HUMANA - COLEGIO COLUMBUS | I61: Condiseño | J61: 15000000 | K61: 46048 | M61: 3175594091 | N61: Nakary García | O61: Directora Comercial | P61: n.garcia@condiseno.co
B62: 52 | C62: COTIZACION DE LOS DISEÑOS DE SEGURIDAD HUMANA Y PROTECCIÓN CONTRA INCENDIOS - AMPLIACIÓN PARK 10 | I62: Camilo Pineda | J62: 24000000 | K62: 46050 | N62: Camilo Pineda | O62: Arquitecto
B63: 53 | C63: COTIZACION DEL ANÁLISIS DE SEGURIDAD HUMANA - VIVIENDA PRADO PINZÓN | I63: Conconcreto | J63: 8780000 | K63: 46051 | M63: 3148721400 | N63: Adriana Agudelo López | O63: Arquitecta Coordinadora | P63: aagudelol@conconcreto.com
B64: 54 | C64: COTIZACION DEL DISEÑO DE EXTINCIÓN DE INCENDIOS - POLÍGONO | I64: GEODIC | J64: 2500000 | K64: 46050 | N64: Andrés Mauricio Muñoz Molina | P64: directorpoligono.geodic@hotmail.com
B65: 55 | C65: COTIZACION DE LOS DISEÑOS DE SEGURIDAD HUMANA Y PROTECCIÓN CONTRA INCENDIOS - PALAU VOILA Y LEPINOT | I65: Inversiones TP | J65: 26950000 | K65: 46051 | M65: 3207202429 | N65: Diana Patricia Giraldo Roman | P65: sstdianagiraldo@gmail.com
B66: 56 | C66: COTIZACION DEL ANÁLISIS DE SEGURIDAD HUMANA - INSTITUCIÓN ETNOEDUCATIVA NUEVA COLONIA | I66: Conconcreto | J66: 7500000 | K66: 46051 | M66: 3206194853 | N66: Laura Sofia Foronda Vasquez | O66: Auxiliar administrativa ofertas y presupuestos | P66: lforondav@conconcreto.com
B67: 57 | C67: COTIZACION DEL DISEÑO DE EXTINCIÓN DE INCENDIOS - HACEB | I67: Seriinco | J67: 27000000 | K67: 46051 | M67: 3052837617 | N67: Alvaro Garcia | P67: alvaro.garcia@seriinco.com
B68: 58 | C68: COTIZACION DEL DISEÑO DE LA SUCCIÓN DE LA BOMBA CONTRA INCENDIOS - PLANTA RYMEL | I68: Rymel | J68: 4000000 | K68: 46051 | M68: 3209066577 | N68: Juan David Cano
B69: 59 | C69: COTIZACION DEL ANÁLISIS DE SEGURIDAD HUMANA - SEDE ADMINISTRATIVA VERSALLES | I69: Coprocenva | J69: 5950000 | K69: 46052 | N69: Juan Paulo Valdés | P69: coordinadorinfraestructura@coprocenva.coop
B70: 60 | C70: COTIZACION DE LOS DISEÑOS DE SEGURIDAD HUMANA Y PROTECCIÓN CONTRA INCENDIOS - NIWA | I70: IS Civiles | J70: 2500000 | K70: 46052 | M70: 3143624300/3007518982 | N70: Heder Alvarez Cardozo | P70: heder.cardozo@isciviles.com.co
B71: 61 | C71: COTIZACION DEL DISEÑO DE DETECCIÓN DE INCENDIOS - PELDAR TORRE RESIDENCIAL PRIMERA ETAPA | I71: H&Fire | J71: 13550000 | K71: 46052 | M71: 4798165 | N71: Juliana Jaramillo | O71: Delineante de Ingeniería | P71: diseno@hyfiresas.com
B72: 62 | C72: COTIZACION DEL DISEÑO DE DETECCIÓN DE INCENDIOS - CELESTI T1 | I72: H&Fire | J72: 7250000 | K72: 46052 | M72: 4798165 | N72: Juliana Jaramillo | O72: Delineante de Ingeniería | P72: diseno@hyfiresas.com
B73: 63 | C73: COTIZACION DEL DISEÑO DE DETECCIÓN DE INCENDIOS - FANTASIA T2 | I73: H&Fire | J73: 6950000 | K73: 46052 | M73: 4798165 | N73: Juliana Jaramillo | O73: Delineante de Ingeniería | P73: diseno@hyfiresas.com
B74: 64 | C74: COTIZACION DEL DISEÑO DE DETECCIÓN DE INCENDIOS - LAZARITO | I74: H&Fire | J74: 19500000 | K74: 46052 | M74: 4798165 | N74: Juliana Jaramillo | O74: Delineante de Ingeniería | P74: diseno@hyfiresas.com
B75: 65 | C75: COTIZACION DEL DISEÑO DE EXTINCIÓN DE INCENDIOS - HACEB ROCIADORES | I75: SPCI | J75: 42000000 | K75: 46053 | M75: 3104165783 | N75: Cristiam Gustavo Mondragon | O75: Director técnico | P75: dir.tecnico@spci.com.co
B76: 66 | C76: COTIZACION DE LOS DISEÑOS DE PROTECCIÓN CONTRA INCENDIOS - GAS PAÍS | I76: Gas País | J76: =15000000*10 -> 150000000 | K76: 46059 | M76: 3214813898 | N76: María Del Pilar Cortes González | P76: mariacortes@gaspais.com.co
B77: 67 | C77: COTIZACION DEL DISEÑO DE EXTINCIÓN DE INCENDIOS - LOCAL AYURA CENTER | I77: Ingesed | J77: 5000000 | K77: 46058 | M77: 321 8338189 | N77: Laura Delgado | O77: Directora de operaciones | P77: operacionesingesed@gmail.com
B78: 68 | C78: COTIZACION DE LOS DISEÑOS DE SEGURIDAD HUMANA Y PROTECCIÓN CONTRA INCENDIOS - PALAU VOILA Y LEPINOT | I78: Inversiones TP | J78: 26950000 | K78: 46055 | M78: 3207202429 | N78: Diana Patricia Giraldo Roman | P78: sstdianagiraldo@gmail.com
B79: 69 | C79: COTIZACION DE LOS DISEÑOS DE SEGURIDAD HUMANA Y PROTECCIÓN CONTRA INCENDIOS - PROYECTO GIN | I79: FCR | J79: 27320000 | K79: 46056 | M79: 310 5304562 | N79: Vanessa Zapata | P79: vanessazapata.fcr@gmail.com
B80: 70 | C80: COTIZACION DE LOS DISEÑOS DE SEGURIDAD HUMANA Y PROTECCIÓN CONTRA INCENDIOS - PARQUEADEROS NUEVOS WATANA ETAPA 2 | I80: Coninsa | J80: 10000000 | K80: 46056 | M80: 3007549649 | N80: Zully Milena López Molina | O80: Estructuración técnica Medellín | P80: zmlopez@coninsa.co
B81: 71 | C81: COTIZACION DEL ANÁLISIS DE SEGURIDAD HUMANA - CIUDAD CAPRI | I81: Coprocenva | J81: 7550000 | K81: 46057 | N81: Juan Paulo Valdés | P81: coordinadorinfraestructura@coprocenva.coop
B82: 72 | C82: COTIZACION DEL REDISEÑO DE EXTINCIÓN DE INCENDIOS - MADERO DE LOS BOSQUES | I82: Soluciones Civiles | J82: 5000000 | K82: 46058 | M82: 310 4425769 | N82: Juliana Ante
B83: 73 | C83: COTIZACION DE LOS DISEÑOS DE SEGURIDAD HUMANA Y PROTECCIÓN CONTRA INCENDIOS - PRADO BELLO | I83: Tamayo ingenieros SAS | J83: 16310000 | K83: 46059 | N83: Juan Fernando Arroyave
B84: 74 | C84: COTIZACION DE LOS DISEÑOS DE SEGURIDAD HUMANA Y PROTECCIÓN CONTRA INCENDIOS - BASILEA | I84: Coninsa | J84: 75200000 | K84: 46058 | M84: 3007549649 | N84: Zully Milena López Molina | O84: Estructuración técnica Medellín | P84: zmlopez@coninsa.co
B85: 75 | C85: COTIZACION DEL DISEÑO DE DETECCIÓN DE INCENDIOS - BELLA PIEL | I85: SPCI | J85: 1050000 | K85: 46058 | M85: 3104165783 | N85: Cristiam Gustavo Mondragon | O85: Director técnico | P85: dir.tecnico@spci.com.co
B86: 76 | C86: COTIZACION DEL REDISEÑO DE ANÁLISIS DE SEGURIDAD HUMANA - PARQUIAMERICA | I86: SPCI | J86: 2000000 | K86: 46058 | M86: 3104165783 | N86: Cristiam Gustavo Mondragon | O86: Director técnico | P86: dir.tecnico@spci.com.co
B87: 77 | C87: COTIZACION DE LOS DISEÑOS DE SEGURIDAD HUMANA Y PROTECCIÓN CONTRA INCENDIOS - FONTANAR TORRE 8 | I87: Bienes y bienes | J87: 13750000 | K87: 46058 | M87: 3108542361 | N87: Carlos Adolfo Zapata Molina | O87: Coordinador BIM | P87: carlos.zapata@bienesybienes.com.co
B88: 78 | C88: COTIZACION DE LOS DISEÑOS DE PROTECCIÓN CONTRA INCENDIOS - BODEGA 2.000 M2 | I88: CGR SA | J88: 13800000 | K88: 46059 | M88: 3108542361 | N88: Carlos Julio Escamilla Niño | O88: Asesor técnico PMO | P88: carlos.escamilla@cgr-bogota.com
B89: 79 | C89: COTIZACION DEL DISEÑO DE EXTINCIÓN DE INCENDIOS - D1 FACTORY | I89: Ingesed | J89: 3000000 | K89: 46058 | M89: 321 8338189 | N89: Laura Delgado | P89: operacionesingesed@gmail.com
B90: 80 | C90: COTIZACION DE LOS DISEÑOS DE SEGURIDAD HUMANA Y EXTINCIÓN DE INCENDIOS - TORRE SEGUROS BOLÍVAR | I90: STUDIOSUR | J90: Variable | K90: 46062 | M90: 3127764680 | N90: Liliana Gutierrez | O90: Arquitecta | P90: liliana.gutierrez@studiosur.net
B91: 81 | C91: COTIZACION DE LOS DISEÑOS DE PROTECCIÓN CONTRA INCENDIOS LOTE 1 | I91: Ingesed | J91: 19990000 | K91: 46062 | M91: 3014201614 | N91: Jhon Rodriguez | P91: jrodriguez@ingesed.com
B92: 82 | C92: COTIZACION DE LOS DISEÑOS DE PROTECCIÓN CONTRA INCENDIOS - COMODISIMOS | I92: Securetec | J92: 18950000 | K92: 46063 | M92: 3206678830 | N92: Jhonny A. Castro | P92: dirproyectos@securetec.com.co
B93: 83 | C93: COTIZACION DE LOS DISEÑOS DE SEGURIDAD HUMANA Y PROTECCIÓN CONTRA INCENDIOS - CLINICA COA | I93: Control medic plus | J93: 3950000 | K93: 46063 | M93: 3128939595 | N93: Oscar Oosorio
B94: 84 | C94: COTIZACION DE LOS DISEÑOS DE SEGURIDAD HUMANA Y PROTECCIÓN CONTRA INCENDIOS - TORRE VALLENTA | I94: David Duque | J94: 24990000 | K94: 46063 | M94: 322 6861576 | N94: David Duque
B95: 85 | C95: COTIZACION DEL ANÁLISIS DE SEGURIDAD HUMANA - HOTEL EN GUATAPÉ | I95: AFC Profire | J95: 4950000 | K95: 46064 | M95: 3116456726 | N95: Andrés Felipe Cruz Restrepo | O95: Director comercial | P95: andres.cruz@afcprofire.com
B96: 86 | C96: COTIZACION DEL ANÁLISIS DE SEGURIDAD HUMANA - EDIFICIO SAN ANTONIO DE PRADO | I96: AFC Profire | J96: 6250000 | K96: 46064 | M96: 3116456726 | N96: Andrés Felipe Cruz Restrepo | O96: Director comercial | P96: andres.cruz@afcprofire.com
B97: 87 | C97: COTIZACION DE LOS DISEÑOS DE SEGURIDAD HUMANA Y DETECCIÓN DE INCENDIOS - LA FELICIDAD MANZANA 12 Y 19 | I97: Cusezar | J97: 49900000 | K97: 46064 | M97: 3153267338 | N97: Diana Lucia Torres Yunda | P97: dtorres@cusezar.com
B98: 88 | C98: COTIZACION DE LOS DISEÑOS DE PROTECCIÓN CONTRA INCENDIOS - PLANTA PIEDECUESTA | I98: Good group | J98: 53950000 | K98: 46064 | M98: 3162963854 | N98: Deisy Duque | P98: operaciones@goodgroup.com.co
B99: 89 | C99: COTIZACION DE LOS DISEÑOS DE PROTECCIÓN CONTRA INCENDIOS - PLANTA FLORIDABLANCA | I99: Good group | J99: 39750000 | K99: 46064 | M99: 3162963854 | N99: Deisy Duque | P99: operaciones@goodgroup.com.co
B100: 90 | C100: COTIZACION DE LOS DISEÑOS DE PROTECCIÓN CONTRA INCENDIOS - PALACIO DE JUSTICIA | I100: Ingesed | J100: 37930000 | K100: 46066 | M100: 3135401714 | N100: Eliana Isabel Cardona Ríos | P100: comercial@ingesed.com
B101: 91 | C101: COTIZACION DE LOS DISEÑOS DE SEGURIDAD HUMANA Y PROTECCIÓN CONTRA INCENDIOS - MATADERO PORCE | I101: Ingesed | J101: 29980000 | K101: 46066 | M101: 3135401714 | N101: Eliana Isabel Cardona Ríos | P101: comercial@ingesed.com
B102: 92 | C102: COTIZACION DE LOS DISEÑOS DE SEGURIDAD HUMANA Y DETECCIÓN DE INCENDIOS - VIEW POINT ET 3 | I102: Coninsa | J102: 15970000 | K102: 46066 | M102: 315 5264386 | N102: Yuliana Tamayo Zapata | O102: Profesional Senior de Estructuración Técnica | P102: ytamayo@coninsa.co
B103: 93 | C103: COTIZACION DE LOS DISEÑOS DE SEGURIDAD HUMANA Y EXTINCIÓN DE INCENDIOS - OFICINAS CITI BOGOTÁ | I103: STUDIOSUR | J103: 28250000 | K103: 46066 | M103: 3127764680 | N103: Liliana Gutierrez | P103: liliana.gutierrez@studiosur.net
B104: 94 | C104: COTIZACION DE LOS DISEÑOS DE SEGURIDAD HUMANA Y PROTECCIÓN CONTRA INCENDIOS - PUNTA VELA MALL | I104: Convel | J104: 22850000 | K104: 46066 | M104: 604-3508866 | N104: Luis Esteban Gaviria Gomez | P104: luisgaviria@convel.co
B105: 95 | C105: COTIZACION DEL DISEÑO DE DETECCIÓN DE INCENDIOS - CLÍNICA PANAMERICANA | I105: Clínica Panamericana | J105: No se presentó | K105: 46066 | M105: 3112823159 | N105: Jose David Cely Espitia | O105: Coordinador de infraestructura | P105: infraestructura@clinicapanamericana.co
B106: 96 | C106: COTIZACION DE LOS DISEÑOS DE SEGURIDAD HUMANA Y PROTECCIÓN CONTRA INCENDIOS - ALLEGRO ETAPA 3 | I106: Mensula | J106: 18850000 | K106: 46066 | M106: 475 79 81 | N106: Alejandro Giraldo Ospina | P106: alejandrogiraldo@mensulaingenieros.com
B107: 97 | C107: COTIZACION DEL DISEÑO DE EXTINCIÓN DE INCENDIOS - PIMIENTA | I107: Idea base arquitectos | J107: 2420000 | K107: 46066 | M107: 3042614902 | N107: Kely Andrea Castaño Chavarriaga | P107: hola@ideabasearquitectos.com
B108: 98 | C108: COTIZACION DE LOS DISEÑOS DE SEGURIDAD HUMANA Y PROTECCIÓN CONTRA INCENDIOS - CLÍNICA ISIS | I108: Lab Inmobiliario | J108: 37250000 | K108: 46069 | M108: 3134019808 | N108: Maria Camila Pavía Pinzón | P108: camila.pavia@labinmobiliario.com
...

Sheet Hoja1
A1: # | B1: Item | C1: Description | D1: Qty | E1: Valor Proveedor | F1: 30% + | G1: Price USD | I1: trm | J1: 4170.59
A2: 1 | B2: 7010-4FL | C2: 2 1/2" MONITOR W/4" FLG BASE 750 GPM GUARDIAN FIRE | D2: 1 | E2: =1717.9 -> 1717.9 | F2: =+E2*30% -> 515.37 | G2: =+E2+F2 -> 2233.27 | H2: =+G2*$J$1 -> 9314053.5
A3: 2 | B3: 7132 | C3: 2 1/2" NST Brass Nzl w/Eductor 500 GPM (1%or3% foam) Guardian Fire | D3: 1 | E3: 118.2 | F3: =+E3*30% -> 35.46 | G3: =+E3+F3 -> 153.66 | H3: =+G3*$J$1 -> 640852.86
A4: 3 | B4: 7068A-0400 | C4: 4" KENNEDY RW GATE VALVE FLANGE OS&Y | D4: 1 | E4: 521 | F4: =+E4*30% -> 156.3 | G4: =+E4+F4 -> 677.3 | H4: =+G4*$J$1 -> 2824740.6
A5: 4 | B5: 12-3370-05 | C5: ARK 3% 265 GAL FOMTEC ENVIRO FOAM CONCENTRATE | D5: 1 | E5: 13155.16 | F5: =+E5*30% -> 3946.548 | G5: =+E5+F5 -> 17101.708 | H5: =+G5*$J$1 -> 71324212
G6: =SUM(G2:G5) -> 20165.938 | H6: =+G6*$J$1 -> 84103859

Sheet ANÁLISIS COTIZACIONES
C1: VALOR TOTAL COTIZACIONES | I1: COTIZACIONES APROBADAS | N1: COTIZACIONES RECHAZADAS | Q1: PORCENTAJE DE APROBACION
B2: 2020 | C2: 2021 | D2: 2022 | E2: 2023 | H2: 2020 | I2: 2021 | J2: 2022 | K2: 2023 | N2: 2021 | O2: 2022 | P2: 2023 | Q2: 2020 | R2: 2021 | S2: 2022 | T2: 2023
A3: ENERO | B3: =SUMIFS('2020'!$K$14:$K$567,'2020'!$L$14:$L$567,">="&DATE(2020,1,1),'2020'!$L$14:$L$567,"<="&DATE(2020,1,31)) -> 183195000 | C3: =SUMIFS('2021'!$K$14:$K$567,'2021'!$L$14:$L$567,">="&DATE(2021,1,1),'2021'!$L$14:$L$567,"<="&DATE(2021,1,31)) -> 229017540 | D3: =SUMIFS('2022'!$K$12:$K$565,'2022'!$L$12:$L$565,">="&DATE(2022,1,1),'2022'!$L$12:$L$565,"<="&DATE(2022,1,31)) -> 281980000 | E3: =SUMIFS('2023'!$K$12:$K$565,'2023'!$L$12:$L$565,">="&DATE(2023,1,1),'2023'!$L$12:$L$565,"<="&DATE(2023,1,31)) -> 284760000 | G3: ENERO | H3: =SUMIFS('2020'!$K$14:$K$567,'2020'!$L$14:$L$567,">="&DATE(2020,1,1),'2020'!$L$14:$L$567,"<="&DATE(2020,1,31),'2020'!$M$14:$M$567,"X") -> 21770000 | I3: =SUMIFS('2021'!$K$14:$K$567,'2021'!$L$14:$L$567,">="&DATE(2021,1,1),'2021'!$L$14:$L$567,"<="&DATE(2021,1,31),'2021'!$M$14:$M$567,"X") -> 9850000 | J3: =SUMIFS('2022'!$K$12:$K$565,'2022'!$L$12:$L$565,">="&DATE(2022,1,1),'2022'!$L$12:$L$565,"<="&DATE(2022,1,31),'2022'!$M$12:$M$565,"X") -> 54845000 | K3: =SUMIFS('2023'!$K$12:$K$565,'2023'!$L$12:$L$565,">="&DATE(2023,1,1),'2023'!$L$12:$L$565,"<="&DATE(2023,1,31),'2023'!$M$12:$M$565,"X") -> 43550000 | M3: ENERO | P3: =SUMIFS('2023'!$K$12:$K$565,'2023'!$L$12:$L$565,">="&DATE(2023,1,1),'2023'!$L$12:$L$565,"<="&DATE(2023,1,31),'2023'!$M$12:$M$565,"") -> 241210000 | Q3: =H3/B3 -> 0.11883512 | R3: =I3/C3 -> 0.043009806 | S3: =J3/D3 -> 0.19449961 | T3: =K3/E3 -> 0.15293581
A4: FEBRERO | B4: =SUMIFS('2020'!$K$14:$K$567,'2020'!$L$14:$L$567,">="&DATE(2020,2,1),'2020'!$L$14:$L$567,"<="&DATE(2020,2,28)) -> 266885000 | C4: =SUMIFS('2021'!$K$14:$K$567,'2021'!$L$14:$L$567,">="&DATE(2021,2,1),'2021'!$L$14:$L$567,"<="&DATE(2021,2,28)) -> 402786200 | D4: =SUMIFS('2022'!$K$12:$K$565,'2022'!$L$12:$L$565,">="&DATE(2022,2,1),'2022'!$L$12:$L$565,"<="&DATE(2022,2,28)) -> 498860000 | E4: =SUMIFS('2023'!$K$12:$K$565,'2023'!$L$12:$L$565,">="&DATE(2023,2,1),'2023'!$L$12:$L$565,"<="&DATE(2023,2,28)) -> 518030000 | G4: FEBRERO | H4: =SUMIFS('2020'!$K$14:$K$567,'2020'!$L$14:$L$567,">="&DATE(2020,2,1),'2020'!$L$14:$L$567,"<="&DATE(2020,2,28),'2020'!$M$14:$M$567,"X") -> 36930000 | I4: =SUMIFS('2021'!$K$14:$K$567,'2021'!$L$14:$L$567,">="&DATE(2021,2,1),'2021'!$L$14:$L$567,"<="&DATE(2021,2,28),'2021'!$M$14:$M$567,"X") -> 67995000 | J4: =SUMIFS('2022'!$K$12:$K$565,'2022'!$L$12:$L$565,">="&DATE(2022,2,1),'2022'!$L$12:$L$565,"<="&DATE(2022,2,28),'2022'!$M$12:$M$565,"X") -> 147120000 | K4: =SUMIFS('2023'!$K$12:$K$565,'2023'!$L$12:$L$565,">="&DATE(2023,2,1),'2023'!$L$12:$L$565,"<="&DATE(2023,2,28),'2023'!$M$12:$M$565,"X") -> 75090000 | M4: FEBRERO | P4: =SUMIFS('2023'!$K$12:$K$565,'2023'!$L$12:$L$565,">="&DATE(2023,2,1),'2023'!$L$12:$L$565,"<="&DATE(2023,2,28),'2023'!$M$12:$M$565,"") -> 442940000 | Q4: =H4/B4 -> 0.13837421 | R4: =I4/C4 -> 0.16881164 | S4: =J4/D4 -> 0.2949124 | T4: =K4/E4 -> 0.144953
A5: MARZO | B5: =SUMIFS('2020'!$K$14:$K$567,'2020'!$L$14:$L$567,">="&DATE(2020,3,1),'2020'!$L$14:$L$567,"<="&DATE(2020,3,31)) -> 191285000 | C5: =SUMIFS('2021'!$K$14:$K$567,'2021'!$L$14:$L$567,">="&DATE(2021,3,1),'2021'!$L$14:$L$567,"<="&DATE(2021,3,31)) -> 536792150 | D5: =SUMIFS('2022'!$K$12:$K$565,'2022'!$L$12:$L$565,">="&DATE(2022,3,1),'2022'!$L$12:$L$565,"<="&DATE(2022,3,31)) -> 453000400 | E5: =SUMIFS('2023'!$K$12:$K$565,'2023'!$L$12:$L$565,">="&DATE(2023,3,1),'2023'!$L$12:$L$565,"<="&DATE(2023,3,31)) -> 607730000 | G5: MARZO | H5: =SUMIFS('2020'!$K$14:$K$567,'2020'!$L$14:$L$567,">="&DATE(2020,3,1),'2020'!$L$14:$L$567,"<="&DATE(2020,3,31),'2020'!$M$14:$M$567,"X") -> 23999000 | I5: =SUMIFS('2021'!$K$14:$K$567,'2021'!$L$14:$L$567,">="&DATE(2021,3,1),'2021'!$L$14:$L$567,"<="&DATE(2021,3,31),'2021'!$M$14:$M$567,"X") -> 82730000 | J5: =SUMIFS('2022'!$K$12:$K$565,'2022'!$L$12:$L$565,">="&DATE(2022,3,1),'2022'!$L$12:$L$565,"<="&DATE(2022,3,31),'2022'!$M$12:$M$565,"X") -> 105650400 | K5: =SUMIFS('2023'!$K$12:$K$565,'2023'!$L$12:$L$565,">="&DATE(2023,3,1),'2023'!$L$12:$L$565,"<="&DATE(2023,3,31),'2023'!$M$12:$M$565,"X") -> 57070000 | M5: MARZO | P5: =SUMIFS('2023'!$K$12:$K$565,'2023'!$L$12:$L$565,">="&DATE(2023,3,1),'2023'!$L$12:$L$565,"<="&DATE(2023,3,31),'2023'!$M$12:$M$565,"") -> 550660000 | Q5: =H5/B5 -> 0.12546201 | R5: =I5/C5 -> 0.15411924 | S5: =J5/D5 -> 0.23322364 | T5: =K5/E5 -> 0.093906834
A6: ABRIL | B6: =SUMIFS('2020'!$K$14:$K$567,'2020'!$L$14:$L$567,">="&DATE(2020,4,1),'2020'!$L$14:$L$567,"<="&DATE(2020,4,30)) -> 189080000 | C6: =SUMIFS('2021'!$K$14:$K$567,'2021'!$L$14:$L$567,">="&DATE(2021,4,1),'2021'!$L$14:$L$567,"<="&DATE(2021,4,30)) -> 328399950 | D6: =SUMIFS('2022'!$K$12:$K$565,'2022'!$L$12:$L$565,">="&DATE(2022,4,1),'2022'!$L$12:$L$565,"<="&DATE(2022,4,30)) -> 979285000 | E6: =SUMIFS('2023'!$K$12:$K$565,'2023'!$L$12:$L$565,">="&DATE(2023,4,1),'2023'!$L$12:$L$565,"<="&DATE(2023,4,30)) -> 433856950 | G6: ABRIL | H6: =SUMIFS('2020'!$K$14:$K$567,'2020'!$L$14:$L$567,">="&DATE(2020,4,1),'2020'!$L$14:$L$567,"<="&DATE(2020,4,30),'2020'!$M$14:$M$567,"X") -> 49280000 | I6: =SUMIFS('2021'!$K$14:$K$567,'2021'!$L$14:$L$567,">="&DATE(2021,4,1),'2021'!$L$14:$L$567,"<="&DATE(2021,4,30),'2021'!$M$14:$M$567,"X") -> 61350000 | J6: =SUMIFS('2022'!$K$12:$K$565,'2022'!$L$12:$L$565,">="&DATE(2022,4,1),'2022'!$L$12:$L$565,"<="&DATE(2022,4,30),'2022'!$M$12:$M$565,"X") -> 50650000 | K6: =SUMIFS('2023'!$K$12:$K$565,'2023'!$L$12:$L$565,">="&DATE(2023,4,1),'2023'!$L$12:$L$565,"<="&DATE(2023,4,30),'2023'!$M$12:$M$565,"X") -> 0 | M6: ABRIL | P6: =SUMIFS('2023'!$K$12:$K$565,'2023'!$L$12:$L$565,">="&DATE(2023,4,1),'2023'!$L$12:$L$565,"<="&DATE(2023,4,30),'2023'!$M$12:$M$565,"") -> 433856950 | Q6: =H6/B6 -> 0.26063042 | R6: =I6/C6 -> 0.18681489 | S6: =J6/D6 -> 0.051721409
A7: MAYO | B7: =SUMIFS('2020'!$K$14:$K$567,'2020'!$L$14:$L$567,">="&DATE(2020,5,1),'2020'!$L$14:$L$567,"<="&DATE(2020,5,31)) -> 105625000 | C7: =SUMIFS('2021'!$K$14:$K$567,'2021'!$L$14:$L$567,">="&DATE(2021,5,1),'2021'!$L$14:$L$567,"<="&DATE(2021,5,31)) -> 231125000 | D7: =SUMIFS('2022'!$K$12:$K$565,'2022'!$L$12:$L$565,">="&DATE(2022,5,1),'2022'!$L$12:$L$565,"<="&DATE(2022,5,31)) -> 840510000 | E7: =SUMIFS('2023'!$K$12:$K$565,'2023'!$L$12:$L$565,">="&DATE(2023,5,1),'2023'!$L$12:$L$565,"<="&DATE(2023,5,31)) -> 397750000 | G7: MAYO | H7: =SUMIFS('2020'!$K$14:$K$567,'2020'!$L$14:$L$567,">="&DATE(2020,5,1),'2020'!$L$14:$L$567,"<="&DATE(2020,5,31),'2020'!$M$14:$M$567,"X") -> 14930000 | I7: =SUMIFS('2021'!$K$14:$K$567,'2021'!$L$14:$L$567,">="&DATE(2021,5,1),'2021'!$L$14:$L$567,"<="&DATE(2021,5,31),'2021'!$M$14:$M$567,"X") -> 32310000 | J7: =SUMIFS('2022'!$K$12:$K$565,'2022'!$L$12:$L$565,">="&DATE(2022,5,1),'2022'!$L$12:$L$565,"<="&DATE(2022,5,31),'2022'!$M$12:$M$565,"X") -> 231560000 | K7: =SUMIFS('2023'!$K$12:$K$565,'2023'!$L$12:$L$565,">="&DATE(2023,5,1),'2023'!$L$12:$L$565,"<="&DATE(2023,5,31),'2023'!$M$12:$M$565,"X") -> 0 | M7: MAYO | P7: =SUMIFS('2023'!$K$12:$K$565,'2023'!$L$12:$L$565,">="&DATE(2023,5,1),'2023'!$L$12:$L$565,"<="&DATE(2023,5,31),'2023'!$M$12:$M$565,"") -> 397750000 | Q7: =H7/B7 -> 0.14134911 | R7: =I7/C7 -> 0.13979448 | S7: =J7/D7 -> 0.2754994
A8: JUNIO | B8: =SUMIFS('2020'!$K$14:$K$567,'2020'!$L$14:$L$567,">="&DATE(2020,6,1),'2020'!$L$14:$L$567,"<="&DATE(2020,6,30)) -> 105630000 | C8: =SUMIFS('2021'!$K$14:$K$567,'2021'!$L$14:$L$567,">="&DATE(2021,6,1),'2021'!$L$14:$L$567,"<="&DATE(2021,6,30)) -> 345520000 | D8: =SUMIFS('2022'!$K$12:$K$565,'2022'!$L$12:$L$565,">="&DATE(2022,6,1),'2022'!$L$12:$L$565,"<="&DATE(2022,6,30)) -> 458268378 | E8: =SUMIFS('2023'!$K$12:$K$565,'2023'!$L$12:$L$565,">="&DATE(2023,6,1),'2023'!$L$12:$L$565,"<="&DATE(2023,6,30)) -> 652035000 | G8: JUNIO | H8: =SUMIFS('2020'!$K$14:$K$567,'2020'!$L$14:$L$567,">="&DATE(2020,6,1),'2020'!$L$14:$L$567,"<="&DATE(2020,6,30),'2020'!$M$14:$M$567,"X") -> 56185000 | I8: =SUMIFS('2021'!$K$14:$K$567,'2021'!$L$14:$L$567,">="&DATE(2021,6,1),'2021'!$L$14:$L$567,"<="&DATE(2021,6,30),'2021'!$M$14:$M$567,"X") -> 67410000 | J8: =SUMIFS('2022'!$K$12:$K$565,'2022'!$L$12:$L$565,">="&DATE(2022,6,1),'2022'!$L$12:$L$565,"<="&DATE(2022,6,30),'2022'!$M$12:$M$565,"X") -> 76350000 | K8: =SUMIFS('2023'!$K$12:$K$565,'2023'!$L$12:$L$565,">="&DATE(2023,6,1),'2023'!$L$12:$L$565,"<="&DATE(2023,6,30),'2023'!$M$12:$M$565,"X") -> 0 | M8: JUNIO | P8: =SUMIFS('2023'!$K$12:$K$565,'2023'!$L$12:$L$565,">="&DATE(2023,6,1),'2023'!$L$12:$L$565,"<="&DATE(2023,6,30),'2023'!$M$12:$M$565,"") -> 652035000 | Q8: =H8/B8 -> 0.53190382 | R8: =I8/C8 -> 0.19509724 | S8: =J8/D8 -> 0.16660543
A9: JULIO | B9: =SUMIFS('2020'!$K$14:$K$567,'2020'!$L$14:$L$567,">="&DATE(2020,7,1),'2020'!$L$14:$L$567,"<="&DATE(2020,7,31)) -> 380090000 | C9: =SUMIFS('2021'!$K$14:$K$567,'2021'!$L$14:$L$567,">="&DATE(2021,7,1),'2021'!$L$14:$L$567,"<="&DATE(2021,7,31)) -> 493293001 | D9: =SUMIFS('2022'!$K$12:$K$565,'2022'!$L$12:$L$565,">="&DATE(2022,7,1),'2022'!$L$12:$L$565,"<="&DATE(2022,7,31)) -> 229770000 | E9: =SUMIFS('2023'!$K$12:$K$565,'2023'!$L$12:$L$565,">="&DATE(2023,7,1),'2023'!$L$12:$L$565,"<="&DATE(2023,7,31)) -> 371175550 | G9: JULIO | H9: =SUMIFS('2020'!$K$14:$K$567,'2020'!$L$14:$L$567,">="&DATE(2020,7,1),'2020'!$L$14:$L$567,"<="&DATE(2020,7,31),'2020'!$M$14:$M$567,"X") -> 155505000 | I9: =SUMIFS('2021'!$K$14:$K$567,'2021'!$L$14:$L$567,">="&DATE(2021,7,1),'2021'!$L$14:$L$567,"<="&DATE(2021,7,31),'2021'!$M$14:$M$567,"X") -> 102190000 | J9: =SUMIFS('2022'!$K$12:$K$565,'2022'!$L$12:$L$565,">="&DATE(2022,7,1),'2022'!$L$12:$L$565,"<="&DATE(2022,7,31),'2022'!$M$12:$M$565,"X") -> 69700000 | K9: =SUMIFS('2023'!$K$12:$K$565,'2023'!$L$12:$L$565,">="&DATE(2023,7,1),'2023'!$L$12:$L$565,"<="&DATE(2023,7,31),'2023'!$M$12:$M$565,"X") -> 0 | M9: JULIO | P9: =SUMIFS('2023'!$K$12:$K$565,'2023'!$L$12:$L$565,">="&DATE(2023,7,1),'2023'!$L$12:$L$565,"<="&DATE(2023,7,31),'2023'!$M$12:$M$565,"") -> 371175550 | Q9: =H9/B9 -> 0.40912679 | R9: =I9/C9 -> 0.20715883 | S9: =J9/D9 -> 0.30334683
A10: AGOSTO | B10: =SUMIFS('2020'!$K$14:$K$567,'2020'!$L$14:$L$567,">="&DATE(2020,8,1),'2020'!$L$14:$L$567,"<="&DATE(2020,8,31)) -> 217930000 | C10: =SUMIFS('2021'!$K$14:$K$567,'2021'!$L$14:$L$567,">="&DATE(2021,8,1),'2021'!$L$14:$L$567,"<="&DATE(2021,8,31)) -> 386030001 | D10: =SUMIFS('2022'!$K$12:$K$565,'2022'!$L$12:$L$565,">="&DATE(2022,8,1),'2022'!$L$12:$L$565,"<="&DATE(2022,8,31)) -> 754145000 | E10: =SUMIFS('2023'!$K$12:$K$565,'2023'!$L$12:$L$565,">="&DATE(2023,8,1),'2023'!$L$12:$L$565,"<="&DATE(2023,8,31)) -> 544920000 | G10: AGOSTO | H10: =SUMIFS('2020'!$K$14:$K$567,'2020'!$L$14:$L$567,">="&DATE(2020,8,1),'2020'!$L$14:$L$567,"<="&DATE(2020,8,31),'2020'!$M$14:$M$567,"X") -> 37750000 | I10: =SUMIFS('2021'!$K$14:$K$567,'2021'!$L$14:$L$567,">="&DATE(2021,8,1),'2021'!$L$14:$L$567,"<="&DATE(2021,8,31),'2021'!$M$14:$M$567,"X") -> 65225000 | J10: =SUMIFS('2022'!$K$12:$K$565,'2022'!$L$12:$L$565,">="&DATE(2022,8,1),'2022'!$L$12:$L$565,"<="&DATE(2022,8,31),'2022'!$M$12:$M$565,"X") -> 54720000 | K10: =SUMIFS('2023'!$K$12:$K$565,'2023'!$L$12:$L$565,">="&DATE(2023,8,1),'2023'!$L$12:$L$565,"<="&DATE(2023,8,31),'2023'!$M$12:$M$565,"X") -> 0 | M10: AGOSTO | P10: =SUMIFS('2023'!$K$12:$K$565,'2023'!$L$12:$L$565,">="&DATE(2023,8,1),'2023'!$L$12:$L$565,"<="&DATE(2023,8,31),'2023'!$M$12:$M$565,"") -> 544920000 | Q10: =H10/B10 -> 0.17322076 | R10: =I10/C10 -> 0.16896355 | S10: =J10/D10 -> 0.072558991
A11: SEPTIEMBRE | B11: =SUMIFS('2020'!$K$14:$K$567,'2020'!$L$14:$L$567,">="&DATE(2020,9,1),'2020'!$L$14:$L$567,"<="&DATE(2020,9,31)) -> 270465000 | C11: =SUMIFS('2021'!$K$14:$K$567,'2021'!$L$14:$L$567,">="&DATE(2021,9,1),'2021'!$L$14:$L$567,"<="&DATE(2021,9,31)) -> 372690000 | D11: =SUMIFS('2022'!$K$12:$K$565,'2022'!$L$12:$L$565,">="&DATE(2022,9,1),'2022'!$L$12:$L$565,"<="&DATE(2022,9,31)) -> 380630000 | E11: =SUMIFS('2023'!$K$12:$K$565,'2023'!$L$12:$L$565,">="&DATE(2023,9,1),'2023'!$L$12:$L$565,"<="&DATE(2023,9,31)) -> 444120000 | G11: SEPTIEMBRE | H11: =SUMIFS('2020'!$K$14:$K$567,'2020'!$L$14:$L$567,">="&DATE(2020,9,1),'2020'!$L$14:$L$567,"<="&DATE(2020,9,31),'2020'!$M$14:$M$567,"X") -> 30830000 | I11: =SUMIFS('2021'!$K$14:$K$567,'2021'!$L$14:$L$567,">="&DATE(2021,9,1),'2021'!$L$14:$L$567,"<="&DATE(2021,9,31),'2021'!$M$14:$M$567,"X") -> 59640000 | J11: =SUMIFS('2022'!$K$12:$K$565,'2022'!$L$12:$L$565,">="&DATE(2022,9,1),'2022'!$L$12:$L$565,"<="&DATE(2022,9,31),'2022'!$M$12:$M$565,"X") -> 99230000 | K11: =SUMIFS('2023'!$K$12:$K$565,'2023'!$L$12:$L$565,">="&DATE(2023,9,1),'2023'!$L$12:$L$565,"<="&DATE(2023,9,31),'2023'!$M$12:$M$565,"X") -> 0 | M11: SEPTIEMBRE | P11: =SUMIFS('2023'!$K$12:$K$565,'2023'!$L$12:$L$565,">="&DATE(2023,9,1),'2023'!$L$12:$L$565,"<="&DATE(2023,9,31),'2023'!$M$12:$M$565,"") -> 444120000 | Q11: =H11/B11 -> 0.11398887 | R11: =I11/C11 -> 0.16002576 | S11: =J11/D11 -> 0.26069937
A12: OCTUBRE | B12: =SUMIFS('2020'!$K$14:$K$567,'2020'!$L$14:$L$567,">="&DATE(2020,10,1),'2020'!$L$14:$L$567,"<="&DATE(2020,10,31)) -> 338465000 | C12: =SUMIFS('2021'!$K$14:$K$567,'2021'!$L$14:$L$567,">="&DATE(2021,10,1),'2021'!$L$14:$L$567,"<="&DATE(2021,10,31)) -> 354640000 | D12: =SUMIFS('2022'!$K$12:$K$565,'2022'!$L$12:$L$565,">="&DATE(2022,10,1),'2022'!$L$12:$L$565,"<="&DATE(2022,10,31)) -> 370274650 | E12: =SUMIFS('2023'!$K$12:$K$565,'2023'!$L$12:$L$565,">="&DATE(2023,10,1),'2023'!$L$12:$L$565,"<="&DATE(2023,10,31)) -> 757853500 | G12: OCTUBRE | H12: =SUMIFS('2020'!$K$14:$K$567,'2020'!$L$14:$L$567,">="&DATE(2020,10,1),'2020'!$L$14:$L$567,"<="&DATE(2020,10,31),'2020'!$M$14:$M$567,"X") -> 52160000 | I12: =SUMIFS('2021'!$K$14:$K$567,'2021'!$L$14:$L$567,">="&DATE(2021,10,1),'2021'!$L$14:$L$567,"<="&DATE(2021,10,31),'2021'!$M$14:$M$567,"X") -> 51470000 | J12: =SUMIFS('2022'!$K$12:$K$565,'2022'!$L$12:$L$565,">="&DATE(2022,10,1),'2022'!$L$12:$L$565,"<="&DATE(2022,10,31),'2022'!$M$12:$M$565,"X") -> 40290650 | K12: =SUMIFS('2023'!$K$12:$K$565,'2023'!$L$12:$L$565,">="&DATE(2023,10,1),'2023'!$L$12:$L$565,"<="&DATE(2023,10,31),'2023'!$M$12:$M$565,"X") -> 0 | M12: OCTUBRE | P12: =SUMIFS('2023'!$K$12:$K$565,'2023'!$L$12:$L$565,">="&DATE(2023,10,1),'2023'!$L$12:$L$565,"<="&DATE(2023,10,31),'2023'!$M$12:$M$565,"") -> 757853500 | Q12: =H12/B12 -> 0.15410751 | R12: =I12/C12 -> 0.14513309 | S12: =J12/D12 -> 0.10881288
